Workbook

Sheet _PREVENTAS_
A1: Marca temporal | B1: STATUS | C1: SEGMENTO | D1: ASESOR BO | E1: PROGRAMACION BO | F1: COMENTARIOS BO | G1: SEC | H1: SOT | I1: ASESOR | J1: LEAD | K1: TIPO DOCUMENTO | L1: N° DOCUMENTO | M1: NOMBRE COMPLETO CLIENTE | N1: FECHA NACIMIENTO | O1: LUGAR NACIMIENTO | P1: UBIGEO | Q1: AMAZONAS | R1: ANCASH | S1: APURIMAC | T1: AREQUIPA | U1: AYACUCHO | V1: CAJAMARCA | W1: CALLAO | X1: CUSCO | Y1: HUANCAVELICA | Z1: HUANUCO | AA1: ICA | AB1: JUNIN | AC1: LA LIBERTAD | AD1: LAMBAYEQUE | AE1: LIMA | AF1: LIMA METROPOLITANA | AG1: LORETO | AH1: MADRE DE DIOS | AI1: MOQUEGUA | AJ1: PASCO | AK1: PIURA | AL1: PUNO | AM1: SAN MARTIN | AN1: TACNA | AO1: TUMBES | AP1: UCAYALI | AQ1: NOMBRE PADRE | AR1: NOMBRE MADRE | AS1: CORREO ELECTRONICO | AT1: Column 81 | AU1: TELF GRABACION | AV1: TELF REFERENCIA | AW1: DIRECCION INSTALACION | AX1: PISO | AY1: INTERIOR | AZ1: COORDENADAS | BA1: REFERENCIAS | BB1: PLANO | BC1: DEPARTAMENTO | BD1: PROV / DISTRITO | BE1: TECNOLOGIA | BF1: FULL CLARO | BG1: OPERACION | BH1: OPERADOR ORIGEN | BI1: TELF A PORTAR | BJ1: MODALIDAD | BK1: TIPO SERVICIO | BL1: SERVICIO A CONTRATAR | BM1: OFERTA COMERCIAL ALTA NUEVA | BN1: PRECIO REGULAR | BO1: VELOCIDAD PLAN | BP1: LIGA1 MAX | BQ1: TELEFONO | BR1: N° DECODIFICADORES | BS1: N° MESH | BT1: TELF REGISTRO | BU1: FECHA REGISTRO | BV1: FECHA PROGRAMACION | BW1: TRAMO PROGRAMACION | BX1: FECHA INSTALACIÓN | BY1: ORDEN INSTALACION | BZ1: COD STATUS | CA1: COD DPTO | CB1: MES REG | CC1: MES INSTAL
A2: 46190.704 | B2: 7 - INSTALADA | C2: MASIVO RESIDENCIAL | D2: NAYELI | E2: 46196.583 | F2: PROCEDE | G2: 104715891 | H2: 88485225 | I2: JULIANA | J2: 960791381 | K2: DNI | L2: 72187246 | M2: MARIA DEL CARMEN SALAZAR JUUYPA | N2: 36141 | O2: AREQUIPA | P2: 912817 | T2: Arequipa | AQ2: VICTOR | AR2: GABRIELA | AS2: SALAZARMADECA@GMAIL.COM | AU2: 960791381 | AV2: 960791381 | AW2: AV. LOS BOSQUES PASAJE LOS MANGLARES MZ CH LOTE 2, LA CAMPIÑA, SOCABAYA. | AX2: 3 | AY2: 1 | AZ2: -16.45931970461676, -71.52429812641768 | BA2: ESPALDA DEL COLEGIO LA CAMPIÑA | BB2: AQSB022 | BC2: AREQUIPA | BD2: =IF(COUNTA(Q2:AP2)>0,INDEX(Q2:AP2,,max(IF(Q2:AP2<>"",COLUMN(Q2:AP2)))-16),"") -> Arequipa | BE2: HFC | BF2: SI | BG2: ALTA NUEVA | BL2: 1 PLAY | BM2: Campaña Regular | BN2: 89 | BO2: 400MBPS | BP2: NO | BQ2: NO | BR2: Ninguno | BS2: Ninguno | BU2: =IF($A2<>"", DATE(YEAR($A2),MONTH($A2),DAY($A2)),"") -> 46190 | BV2: =IF($E2<>"",DATE(YEAR($E2),MONTH($E2),DAY($E2)),"") -> 46196 | BW2: =IF($E2<>"",TEXT($E2,"HH"),"") -> 14 | BX2: 46195 | BY2: 1 | BZ2: =IF(B2<>"",VALUE(LEFT(B2)),"") -> 7 | CA2: {=IF($A2<>"",INDEX(LISTA!$M$2:$N$27,MATCH($BC2,LISTA!$N$2:$N$27,0),1),"")} -> 7 | CB2: =IF($A2<>"",MONTH(BU2),"") -> 6 | CC2: =IF($BX2<>"",MONTH(BX2),"") -> 6
A3: 46198.862 | B3: 7 - INSTALADA | C3: MASIVO RESIDENCIAL | D3: PAOLA | E3: 46200.458 | F3: ENVIAR ADELANTO 26/06 | G3: 104856405 | H3: 88648893 | I3: ANNY | J3: 989050975 | K3: DNI | L3: 72539720 | M3: AMNER CALEP PEÑA PIÑA | N3: 37407 | O3: SAN MARTIN | P3: 210701 | AM3: San Martín | AQ3: EUSEBIO | AR3: ESTALI | AS3: amnercalep2002@gmail.com | AU3: 989050975 | AV3: 989050975 | AW3: JR 3 DE OCTUBRE URB 9 DE ABRIL | AX3: 1 | AY3: S/I | AZ3: -6.48287703, -76.37514139 | BA3: JR 9 DE ABRIL | BB3: SMTP025-F | BC3: SAN MARTIN | BD3: =IF(COUNTA(Q3:AP3)>0,INDEX(Q3:AP3,,max(IF(Q3:AP3<>"",COLUMN(Q3:AP3)))-16),"") -> San Martín | BE3: FTTH | BF3: SI | BG3: ALTA NUEVA | BL3: 1 PLAY | BM3: Campaña Regular | BN3: 89 | BO3: 400MBPS | BP3: NO | BQ3: NO | BR3: Ninguno | BS3: 1 | BU3: =IF($A3<>"", DATE(YEAR($A3),MONTH($A3),DAY($A3)),"") -> 46198 | BV3: =IF($E3<>"",DATE(YEAR($E3),MONTH($E3),DAY($E3)),"") -> 46200 | BW3: =IF($E3<>"",TEXT($E3,"HH"),"") -> 11 | BX3: 46199 | BY3: 1 | BZ3: =IF(B3<>"",VALUE(LEFT(B3)),"") -> 7 | CA3: {=IF($A3<>"",INDEX(LISTA!$M$2:$N$27,MATCH($BC3,LISTA!$N$2:$N$27,0),1),"")} -> 23 | CB3: =IF($A3<>"",MONTH(BU3),"") -> 6 | CC3: =IF($BX3<>"",MONTH(BX3),"") -> 6
A4: 46193.676 | B4: 7 - INSTALADA | C4: MASIVO RESIDENCIAL | D4: PAOLA | E4: 46196.458 | F4: Nos pidieron reasignación de esta venta | G4: 104713524 | H4: 88484062 | I4: JULIANA | J4: 927604817 | K4: DNI | L4: 02737885 | M4: MILAGROS INES GUERRA RIVERA | N4: 26578 | O4: PIURA | P4: 190101 | AK4: Piura | AQ4: RUBEN | AR4: OLINDA | AS4: Sebasgu1@hotmail.com | AU4: 927604817 | AV4: 927604817 | AW4: AAHH. LOPEZ ALBUJAR MZ P LOTE 18, 26 DE OCTUBRE, PIURA. | AX4: 2 | AY4: 1 | AZ4: -5.199136608082209, -80.65140110426609 | BA4: -5.199136608082209, -80.65140110426609 | BB4: PIOC002-F | BC4: PIURA | BD4: =IF(COUNTA(Q4:AP4)>0,INDEX(Q4:AP4,,max(IF(Q4:AP4<>"",COLUMN(Q4:AP4)))-16),"") -> Piura | BE4: FTTH | BF4: NO | BG4: ALTA NUEVA | BL4: 1 PLAY + L1MAX | BM4: Campaña Regular | BN4: 110 | BO4: 500MBPS | BP4: SI | BQ4: NO | BR4: Ninguno | BS4: 1 | BU4: =IF($A4<>"", DATE(YEAR($A4),MONTH($A4),DAY($A4)),"") -> 46193 | BV4: =IF($E4<>"",DATE(YEAR($E4),MONTH($E4),DAY($E4)),"") -> 46196 | BW4: =IF($E4<>"",TEXT($E4,"HH"),"") -> 11 | BX4: 46194 | BY4: 3 | BZ4: =IF(B4<>"",VALUE(LEFT(B4)),"") -> 7 | CA4: {=IF($A4<>"",INDEX(LISTA!$M$2:$N$27,MATCH($BC4,LISTA!$N$2:$N$27,0),1),"")} -> 21 | CB4: =IF($A4<>"",MONTH(BU4),"") -> 6 | CC4: =IF($BX4<>"",MONTH(BX4),"") -> 6
A5: 46198.421 | B5: 7 - INSTALADA | C5: MASIVO RESIDENCIAL | D5: NAYELI | E5: 46198.667 | F5: PROCEDE CL QUIERE PARA HOY SI O SI | G5: 104828763 | H5: 88612463 | I5: JESSICA | J5: 936888423 | K5: DNI | L5: 47139933 | M5: RICHARDSON LUIS CORDOVA RIVERA | N5: 33617 | O5: PASCO | P5: 180114 | AB5: Chanchamayo | AQ5: LUIS ALBERTO | AR5: NELLY GLADYS | AS5: richi_cr_92@hotmail.com | AU5: 936888423 | AV5: 936888423 | AW5: JR. LAS DUNAS 130 | AX5: 2 | AY5: NA | AZ5: -12.06481115, -75.22763426 | BA5: PASAJE LAS MESETAS | BB5: JNTB067-F | BC5: JUNIN | BD5: =IF(COUNTA(Q5:AP5)>0,INDEX(Q5:AP5,,max(IF(Q5:AP5<>"",COLUMN(Q5:AP5)))-16),"") -> Chanchamayo | BE5: FTTH | BF5: NO | BG5: ALTA NUEVA | BL5: 1 PLAY | BM5: Campaña Promo Mediana | BN5: 89 | BO5: 400MBPS | BP5: NO | BQ5: NO | BR5: Ninguno | BS5: 1 | BU5: =IF($A5<>"", DATE(YEAR($A5),MONTH($A5),DAY($A5)),"") -> 46198 | BV5: =IF($E5<>"",DATE(YEAR($E5),MONTH($E5),DAY($E5)),"") -> 46198 | BW5: =IF($E5<>"",TEXT($E5,"HH"),"") -> 16 | BX5: 46198 | BY5: 2 | BZ5: =IF(B5<>"",VALUE(LEFT(B5)),"") -> 7 | CA5: {=IF($A5<>"",INDEX(LISTA!$M$2:$N$27,MATCH($BC5,LISTA!$N$2:$N$27,0),1),"")} -> 14 | CB5: =IF($A5<>"",MONTH(BU5),"") -> 6 | CC5: =IF($BX5<>"",MONTH(BX5),"") -> 6
A6: 46200.495 | B6: 7 - INSTALADA | C6: MASIVO RESIDENCIAL | D6: NAYELI | E6: 46202.458 | F6: PROCEDE | G6: 104896460 | H6: 88673676 | I6: JESSICA | J6: 954973060 | K6: DNI | L6: 80064841 | M6: LUIS ALBERTO DAVILA PAREDES | N6: 28883 | O6: PASCO | P6: 180101 | Z6: Huánuco | AQ6: DIOGENES | AR6: AMANDA | AS6: Luisalberto22davila79@gmail.com | AU6: 954973060 | AV6: 954973060 | AW6: AV. ANDRES FERNANDEZ GARRIDO URB. LAS GARDENIAS | AX6: 2 | AY6: NA | AZ6: -9.96498585, -76.245660663 | BA6: JR. SAN FAUSTO | BB6: HUPM008-S | BC6: HUANUCO | BD6: =IF(COUNTA(Q6:AP6)>0,INDEX(Q6:AP6,,max(IF(Q6:AP6<>"",COLUMN(Q6:AP6)))-16),"") -> Huánuco | BE6: FTTH | BF6: NO | BG6: ALTA NUEVA | BL6: 1 PLAY + L1MAX | BM6: Campaña Regular PRO | BN6: 110 | BO6: 500MBPS | BQ6: NO | BR6: Ninguno | BS6: 1 | BU6: =IF($A6<>"", DATE(YEAR($A6),MONTH($A6),DAY($A6)),"") -> 46200 | BV6: =IF($E6<>"",DATE(YEAR($E6),MONTH($E6),DAY($E6)),"") -> 46202 | BW6: =IF($E6<>"",TEXT($E6,"HH"),"") -> 11 | BX6: 46202 | BY6: 4 | BZ6: =IF(B6<>"",VALUE(LEFT(B6)),"") -> 7 | CA6: {=IF($A6<>"",INDEX(LISTA!$M$2:$N$27,MATCH($BC6,LISTA!$N$2:$N$27,0),1),"")} -> 12 | CB6: =IF($A6<>"",MONTH(BU6),"") -> 6 | CC6: =IF($BX6<>"",MONTH(BX6),"") -> 6
A7: 46196.508 | B7: 7 - INSTALADA | C7: MASIVO RESIDENCIAL | D7: NAYELI | E7: 46197.458 | F7: PAGO DE INSTALACION - CLIENTE ADELANTA VISITA 24/06 | G7: 104776353 | H7: 88565685 | I7: JUAN DIEGO | J7: 970168191 | K7: DNI | L7: 47430926 | M7: ELIZABETH CRISTINA BARRIENTOS OROSCO | N7: 33581 | O7: LIMA METROPOLITANA | P7: 150133 | AF7: Ate | AQ7: SEBASTIAN | AR7: GLORIA | AS7: eduorosco3@gmail.com | AU7: 970168191 | AV7: 999222641 | AW7: mz g lt 06 URBANIZACIÓN LAS PRADERAS DE PARIACHI tercera etapa | AX7: 2 | AY7: 0 | AZ7: -12.00525274093723, -76.8413549302252 | BA7: AV POSEIDON | BB7: LMAT142-F | BC7: LIMA METROPOLITANA | BD7: =IF(COUNTA(Q7:AP7)>0,INDEX(Q7:AP7,,max(IF(Q7:AP7<>"",COLUMN(Q7:AP7)))-16),"") -> Ate | BE7: FTTH | BF7: NO | BG7: ALTA NUEVA | BL7: 1 PLAY | BM7: Campaña Regular | BN7: 100 | BO7: 800MBPS | BP7: NO | BQ7: NO | BR7: Ninguno | BS7: 2 | BU7: =IF($A7<>"", DATE(YEAR($A7),MONTH($A7),DAY($A7)),"") -> 46196 | BV7: =IF($E7<>"",DATE(YEAR($E7),MONTH($E7),DAY($E7)),"") -> 46197 | BW7: =IF($E7<>"",TEXT($E7,"HH"),"") -> 11 | BX7: 46197 | BY7: 1 | BZ7: =IF(B7<>"",VALUE(LEFT(B7)),"") -> 7 | CA7: {=IF($A7<>"",INDEX(LISTA!$M$2:$N$27,MATCH($BC7,LISTA!$N$2:$N$27,0),1),"")} -> 1 | CB7: =IF($A7<>"",MONTH(BU7),"") -> 6 | CC7: =IF($BX7<>"",MONTH(BX7),"") -> 6
A8: 46179.52 | B8: 7 - INSTALADA | C8: MASIVO RESIDENCIAL | D8: NAYELI | E8: 46185.583 | F8: LYBTEL | G8: 104457724 | H8: 88271126 | I8: ROCIO | J8: 998357850 | K8: DNI | L8: 43729341 | M8: HUGO HERRERA NUÑEZ | N8: 31658 | O8: LIMA | P8: 150131 | AF8: Santiago de Surco | AQ8: HUGO | AR8: MARIA | AS8: jnunezo@hotmail.es | AU8: 997351175 | AV8: 997351175 | AW8: ayacucho 942 santiago de surco dto 402 | AX8: 4 | AY8: 402 | AZ8: -12.136189335877416, -76.99837869182522 | BA8: AV DOñA RAQUEL | BB8: LMSC293-F | BC8: LIMA METROPOLITANA | BD8: =IF(COUNTA(Q8:AP8)>0,INDEX(Q8:AP8,,max(IF(Q8:AP8<>"",COLUMN(Q8:AP8)))-16),"") -> Santiago de Surco | BE8: FTTH | BF8: NO | BG8: ALTA NUEVA | BL8: 2 PLAY + TV ESTANDAR | BM8: Campaña Regular | BN8: 170 | BO8: 400MBPS | BP8: NO | BQ8: NO | BR8: Ninguno | BS8: Ninguno | BU8: =IF($A8<>"", DATE(YEAR($A8),MONTH($A8),DAY($A8)),"") -> 46179 | BV8: =IF($E8<>"",DATE(YEAR($E8),MONTH($E8),DAY($E8)),"") -> 46185 | BW8: =IF($E8<>"",TEXT($E8,"HH"),"") -> 14 | BX8: 46185 | BY8: 1 | BZ8: =IF(B8<>"",VALUE(LEFT(B8)),"") -> 7 | CA8: {=IF($A8<>"",INDEX(LISTA!$M$2:$N$27,MATCH($BC8,LISTA!$N$2:$N$27,0),1),"")} -> 1 | CB8: =IF($A8<>"",MONTH(BU8),"") -> 6 | CC8: =IF($BX8<>"",MONTH(BX8),"") -> 6
A9: 46192.657 | B9: 7 - INSTALADA | C9: MASIVO RESIDENCIAL | D9: PAOLA | E9: 46193.458 | F9: SE MANDA A ANULAR SOT LOS DATOS DE DIRECCIÓN ES INCORRECTO/ CORREGIDO | G9: 104692164 | H9: 88475969 | I9: SAHIR | J9: 995048683 | K9: DNI | L9: 43379508 | M9: JULIO RAMON CHUNG GONZALES | N9: 31436 | O9: LIMA METROPOLITANA | P9: 150121 | AF9: Lince | AQ9: luis fernando | AR9: elvira marina | AS9: julianchungonzales@gmail.com | AU9: 995048683 | AV9: 995048683 | AW9: JIRON INCA GARCILASO DE LA VEGA 1874 URBANIZACION RISSO LINCE | AX9: 1 | AY9: 1 | AZ9: -12.084034, -77.040746 | BA9: av canebaro | BB9: LMLC077-F | BC9: LIMA METROPOLITANA | BD9: =IF(COUNTA(Q9:AP9)>0,INDEX(Q9:AP9,,max(IF(Q9:AP9<>"",COLUMN(Q9:AP9)))-16),"") -> Lince | BE9: FTTH | BF9: SI | BG9: ALTA NUEVA | BL9: 2PLAY + TELF | BM9: Campaña Regular | BN9: 94 | BO9: 400MBPS | BP9: NO | BQ9: SI | BR9: Ninguno | BS9: 1 | BU9: =IF($A9<>"", DATE(YEAR($A9),MONTH($A9),DAY($A9)),"") -> 46192 | BV9: =IF($E9<>"",DATE(YEAR($E9),MONTH($E9),DAY($E9)),"") -> 46193 | BW9: =IF($E9<>"",TEXT($E9,"HH"),"") -> 11 | BX9: 46194 | BY9: 1 | BZ9: =IF(B9<>"",VALUE(LEFT(B9)),"") -> 7 | CA9: {=IF($A9<>"",INDEX(LISTA!$M$2:$N$27,MATCH($BC9,LISTA!$N$2:$N$27,0),1),"")} -> 1 | CB9: =IF($A9<>"",MONTH(BU9),"") -> 6 | CC9: =IF($BX9<>"",MONTH(BX9),"") -> 6
A10: 46196.576 | B10: 7 - INSTALADA | C10: MASIVO RESIDENCIAL | D10: NAYELI | E10: 46199.583 | F10: PROCEDE, EDIFICIO HABILITADO | G10: 104780309 | H10: 88566260 | I10: ANTHONELLA | J10: 968906150 | K10: DNI | L10: 48294663 | M10: KEVIN JUSTIN GUERRA LÓPEZ | N10: 34087 | O10: LIMA METROPOLITANA | P10: 150117 | AF10: Surquillo | AQ10: OSCAR | AR10: MAXIMINA | AS10: kevin.04.gl@gmail.com | AU10: 968906150 | AV10: 968906150 | AW10: Av. Principal 915 Surquillo Edificio: VITTORIE | AX10: 9 | AY10: 901 | AZ10: -12.119644, -77.00413 | BA10: av principal | BB10: LMSQ089-S | BC10: LIMA METROPOLITANA | BD10: =IF(COUNTA(Q10:AP10)>0,INDEX(Q10:AP10,,max(IF(Q10:AP10<>"",COLUMN(Q10:AP10)))-16),"") -> Surquillo | BE10: FTTH | BF10: SI | BG10: ALTA NUEVA | BL10: 1 PLAY | BM10: Campaña Regular | BN10: 110 | BO10: 500MBPS | BP10: SI | BQ10: NO | BR10: Ninguno | BS10: Ninguno | BU10: =IF($A10<>"", DATE(YEAR($A10),MONTH($A10),DAY($A10)),"") -> 46196 | BV10: =IF($E10<>"",DATE(YEAR($E10),MONTH($E10),DAY($E10)),"") -> 46199 | BW10: =IF($E10<>"",TEXT($E10,"HH"),"") -> 14 | BX10: 46199 | BY10: 2 | BZ10: =IF(B10<>"",VALUE(LEFT(B10)),"") -> 7 | CA10: {=IF($A10<>"",INDEX(LISTA!$M$2:$N$27,MATCH($BC10,LISTA!$N$2:$N$27,0),1),"")} -> 1 | CB10: =IF($A10<>"",MONTH(BU10),"") -> 6 | CC10: =IF($BX10<>"",MONTH(BX10),"") -> 6
A11: 46197.502 | B11: 7 - INSTALADA | C11: MASIVO RESIDENCIAL | D11: NAYELI | E11: 46198.583 | F11: CONFIRMA VISITA | G11: 104805604 | H11: 88589466 | I11: JUAN DIEGO | J11: 944551713 | K11: DNI | L11: 42863482 | M11: MARCO ANTONIO BLAS ZUÑIGA | N11: 31111 | O11: LIMA METROPOLITANA | P11: 150113 | AF11: San Juan de Miraflores | AQ11: MANUEL | AR11: BLANCA | AS11: marcoantonioblaszuniga@gmail.com | AU11: 944 551 713 | AV11: 944 551 713 | AW11: Mz 90 lt 12 URB LOS BRILLANTES SAN JUAN DE MIRAFLORES LIMA | AX11: 2 | AY11: NA | AZ11: -12.144510048064456, -76.96690070477077 | BA11: AVENIDA CENTRAL CON PASAJE SANTA ROSA | BB11: LMJR114-F | BC11: LIMA METROPOLITANA | BD11: =IF(COUNTA(Q11:AP11)>0,INDEX(Q11:AP11,,max(IF(Q11:AP11<>"",COLUMN(Q11:AP11)))-16),"") -> San Juan de Miraflores | BE11: FTTH | BF11: SI | BG11: ALTA NUEVA | BL11: 2PLAY + TELF | BM11: Campaña Regular | BN11: 94 | BO11: 400MBPS | BP11: NO | BQ11: SI | BR11: Ninguno | BS11: 1 | BU11: =IF($A11<>"", DATE(YEAR($A11),MONTH($A11),DAY($A11)),"") -> 46197 | BV11: =IF($E11<>"",DATE(YEAR($E11),MONTH($E11),DAY($E11)),"") -> 46198 | BW11: =IF($E11<>"",TEXT($E11,"HH"),"") -> 14 | BX11: 46198 | BY11: 3 | BZ11: =IF(B11<>"",VALUE(LEFT(B11)),"") -> 7 | CA11: {=IF($A11<>"",INDEX(LISTA!$M$2:$N$27,MATCH($BC11,LISTA!$N$2:$N$27,0),1),"")} -> 1 | CB11: =IF($A11<>"",MONTH(BU11),"") -> 6 | CC11: =IF($BX11<>"",MONTH(BX11),"") -> 6
A12: 46198.601 | B12: 7 - INSTALADA | C12: MASIVO RESIDENCIAL | D12: NAYELI | E12: 46201.375 | F12: PROCEDE SE ENVIA ADELANTO 26/06 | G12: 104842396 | H12: 88622310 | I12: ANTHONELLA | J12: 959466891 | K12: DNI | L12: 75454838 | M12: ROCIO LESLY FIGUEROA RODRIGUEZ | N12: 35060 | O12: LIMA | P12: 150101 | W12: Callao | AQ12: TEODOSIO | AR12: BETTY | AS12: figeroa.air23@gmail.com | AU12: 959466891 | AV12: 976269839 | AW12: Albino Herrera 2da Etp. Mz.B1 Lt.20 - Callao | AX12: 3 | AY12: SIN | AZ12: -12.010193, -77.095981 | BA12: AV LOS DOMINICOS | BB12: LMCA009-S | BC12: CALLAO | BD12: =IF(COUNTA(Q12:AP12)>0,INDEX(Q12:AP12,,max(IF(Q12:AP12<>"",COLUMN(Q12:AP12)))-16),"") -> Callao | BE12: FTTH | BF12: NO | BG12: ALTA NUEVA | BL12: 1 PLAY | BM12: Campaña Regular | BN12: 89 | BO12: 400MBPS | BP12: SI | BQ12: NO | BR12: Ninguno | BS12: Ninguno | BU12: =IF($A12<>"", DATE(YEAR($A12),MONTH($A12),DAY($A12)),"") -> 46198 | BV12: =IF($E12<>"",DATE(YEAR($E12),MONTH($E12),DAY($E12)),"") -> 46201 | BW12: =IF($E12<>"",TEXT($E12,"HH"),"") -> 09 | BX12: 46201 | BY12: 1 | BZ12: =IF(B12<>"",VALUE(LEFT(B12)),"") -> 7 | CA12: {=IF($A12<>"",INDEX(LISTA!$M$2:$N$27,MATCH($BC12,LISTA!$N$2:$N$27,0),1),"")} -> 2 | CB12: =IF($A12<>"",MONTH(BU12),"") -> 6 | CC12: =IF($BX12<>"",MONTH(BX12),"") -> 6
A13: 46199.708 | B13: 7 - INSTALADA | C13: MASIVO RESIDENCIAL | D13: NAYELI | E13: 46202.458 | F13: PROCEDE | G13: 104878027 | H13: 88663022 | I13: GABRIEL | J13: 946215729 | K13: DNI | L13: 75416717 | M13: CRISTEL NICOLT LOPEZ ESPADA | N13: 38508 | O13: LIMA | P13: 140501 | AE13: Huaura | AQ13: HILMER | AR13: MARIA | AS13: Crisle.0506@gmail.com | AU13: 946215729 | AV13: 946215729 | AW13: FRANSISCO ROSAS 346 | AX13: 3 | AY13: 1 | AZ13: -11.104527221283575, -77.60735781101647 | BA13: AL COSTADO DE FERRETERIA NANCY | BB13: LMHU018-S | BC13: LIMA | BD13: =IF(COUNTA(Q13:AP13)>0,INDEX(Q13:AP13,,max(IF(Q13:AP13<>"",COLUMN(Q13:AP13)))-16),"") -> Huaura | BE13: FTTH | BF13: NO | BG13: ALTA NUEVA | BL13: 1 PLAY | BM13: Campaña Regular | BN13: 69 | BO13: 200MBPS | BP13: NO | BQ13: NO | BR13: Ninguno | BS13: Ninguno | BU13: =IF($A13<>"", DATE(YEAR($A13),MONTH($A13),DAY($A13)),"") -> 46199 | BV13: =IF($E13<>"",DATE(YEAR($E13),MONTH($E13),DAY($E13)),"") -> 46202 | BW13: =IF($E13<>"",TEXT($E13,"HH"),"") -> 11 | BX13: 46202 | BY13: 1 | BZ13: =IF(B13<>"",VALUE(LEFT(B13)),"") -> 7 | CA13: {=IF($A13<>"",INDEX(LISTA!$M$2:$N$27,MATCH($BC13,LISTA!$N$2:$N$27,0),1),"")} -> 3 | CB13: =IF($A13<>"",MONTH(BU13),"") -> 6 | CC13: =IF($BX13<>"",MONTH(BX13),"") -> 6
A14: 46191.528 | B14: 7 - INSTALADA | C14: MASIVO RESIDENCIAL | D14: NAYELI | E14: 46200.458 | F14: PROCEDE FULL CLARO | G14: 104645330 | H14: 88434668 | I14: JESSICA | J14: 952589629 | K14: DNI | L14: 10811695 | M14: JENNY PAOLY ROJAS BENITO | N14: 28323 | O14: LIMA | P14: 140125 | AF14: Santiago de Surco | AQ14: GUSTAVO | AR14: MARGARITA | AS14: jainy31@hotmail.com | AU14: 953735960 | AV14: 953735960 | AW14: ASENTAMIENTO HUMANO LOS VIÑEDOS DE SURCO MZ H LT 35 | AX14: 3 | AY14: NA | AZ14: -12.162537454 -76.9885167909999 | BA14: Losa deportiva Los viñedos | BB14: LMSC325-F | BC14: LIMA METROPOLITANA | BD14: =IF(COUNTA(Q14:AP14)>0,INDEX(Q14:AP14,,max(IF(Q14:AP14<>"",COLUMN(Q14:AP14)))-16),"") -> Santiago de Surco | BE14: FTTH | BF14: SI | BG14: ALTA NUEVA | BL14: 2 PLAY + TV ESTANDAR | BM14: Campaña Regular PRO | BN14: 170 | BO14: 400MBPS | BP14: SI | BQ14: NO | BR14: 2 | BS14: 1 | BU14: =IF($A14<>"", DATE(YEAR($A14),MONTH($A14),DAY($A14)),"") -> 46191 | BV14: =IF($E14<>"",DATE(YEAR($E14),MONTH($E14),DAY($E14)),"") -> 46200 | BW14: =IF($E14<>"",TEXT($E14,"HH"),"") -> 11 | BX14: 46202 | BY14: 2 | BZ14: =IF(B14<>"",VALUE(LEFT(B14)),"") -> 7 | CA14: {=IF($A14<>"",INDEX(LISTA!$M$2:$N$27,MATCH($BC14,LISTA!$N$2:$N$27,0),1),"")} -> 1 | CB14: =IF($A14<>"",MONTH(BU14),"") -> 6 | CC14: =IF($BX14<>"",MONTH(BX14),"") -> 6
A15: 46190.379 | B15: 7 - INSTALADA | C15: MASIVO RESIDENCIAL | D15: NAYELI | E15: 46191.583 | F15: PROCEDE/ EDIFICIO HABILITADO | G15: 104605460 | H15: 88405389 | I15: JESSICA | J15: 987579907 | K15: DNI | L15: 70350550 | M15: CLAUDIA ISABEL GIL VIDAL | N15: 33362 | O15: LIMA | P15: 140115 | AF15: Miraflores | AQ15: FERNANDO HUMBERTO | AR15: IRMA BETTY | AS15: cgilvidal@gmail.com | AU15: 987579907 | AV15: 987579907 | AW15: AVENIDA PASEO DE LA REPUBLICA 6373 URBANIZACION SAN ANTONIO | AX15: 16 | AY15: 1601 | AZ15: -12.132422, -77.021475 | BA15: VIA EXPRESA LUIS FERNAN BEDOYA REYES | BB15: LMMF083 | BC15: LIMA METROPOLITANA | BD15: =IF(COUNTA(Q15:AP15)>0,INDEX(Q15:AP15,,max(IF(Q15:AP15<>"",COLUMN(Q15:AP15)))-16),"") -> Miraflores | BE15: HFC | BF15: SI | BG15: ALTA NUEVA | BL15: 1 PLAY + L1MAX | BM15: Campaña Regular PRO | BN15: 110 | BO15: 500MBPS | BP15: SI | BQ15: NO | BR15: Ninguno | BS15: Ninguno | BU15: =IF($A15<>"", DATE(YEAR($A15),MONTH($A15),DAY($A15)),"") -> 46190 | BV15: =IF($E15<>"",DATE(YEAR($E15),MONTH($E15),DAY($E15)),"") -> 46191 | BW15: =IF($E15<>"",TEXT($E15,"HH"),"") -> 14 | BX15: 46191 | BY15: 1 | BZ15: =IF(B15<>"",VALUE(LEFT(B15)),"") -> 7 | CA15: {=IF($A15<>"",INDEX(LISTA!$M$2:$N$27,MATCH($BC15,LISTA!$N$2:$N$27,0),1),"")} -> 1 | CB15: =IF($A15<>"",MONTH(BU15),"") -> 6 | CC15: =IF($BX15<>"",MONTH(BX15),"") -> 6
A16: 46190.494 | B16: 7 - INSTALADA | C16: MASIVO RESIDENCIAL | D16: PAOLA | E16: 46193.458 | F16: LLAMAR 12:30 | G16: 104649549 | H16: 88437602 | I16: PAOLA | J16: 915992860 | K16: DNI | L16: 40537157 | M16: JOHANA MEDALITH MELENDEZ CHINGA | N16: 29369 | O16: LIMA | P16: 140101 | AE16: Huaura | AQ16: JULIO | AR16: ELENA | AS16: RICHARDTJ_3@HOTMAIL.COM | AU16: 963877220 | AV16: 915992860 | AW16: Urb Martir Jose Olaya mz g lote 12 | AX16: 2 | AY16: NA | AZ16: -11.09480528124759, -77.62592378552375 | BA16: JR 28 OCTUBRE | BB16: LMCQ002 | BC16: LIMA | BD16: =IF(COUNTA(Q16:AP16)>0,INDEX(Q16:AP16,,max(IF(Q16:AP16<>"",COLUMN(Q16:AP16)))-16),"") -> Huaura | BE16: HFC | BF16: SI | BG16: ALTA NUEVA | BL16: 1 PLAY | BM16: Campaña Regular | BN16: 110 | BO16: 500MBPS | BP16: NO | BQ16: NO | BR16: 1 | BS16: 1 | BU16: =IF($A16<>"", DATE(YEAR($A16),MONTH($A16),DAY($A16)),"") -> 46190 | BV16: =IF($E16<>"",DATE(YEAR($E16),MONTH($E16),DAY($E16)),"") -> 46193 | BW16: =IF($E16<>"",TEXT($E16,"HH"),"") -> 11 | BX16: 46192 | BY16: 1 | BZ16: =IF(B16<>"",VALUE(LEFT(B16)),"") -> 7 | CA16: {=IF($A16<>"",INDEX(LISTA!$M$2:$N$27,MATCH($BC16,LISTA!$N$2:$N$27,0),1),"")} -> 3 | CB16: =IF($A16<>"",MONTH(BU16),"") -> 6 | CC16: =IF($BX16<>"",MONTH(BX16),"") -> 6
A17: 46184.543 | B17: 7 - INSTALADA | C17: MASIVO RESIDENCIAL | D17: NAYELI | E17: 46185.667 | F17: LYBTEL | G17: 104449975 | H17: 88267394 | I17: ROCIO | J17: 985871277 | K17: DNI | L17: 43252312 | M17: SUSAN IVONNE HEREDIA CORDOVA | N17: 31371 | O17: JUNIN | P17: 110101 | AF17: San Martín de Porres | AQ17: luis | AR17: lucila | AS17: Gabycina@hotmail.com | AU17: 985871277 | AV17: 985871277 | AW17: Urb.San german Jr Ávila Godoy 657 | AX17: 4 | AY17: 1 | AZ17: -12.015793, -77.071245 | BA17: ingreso es por el jardín inicial Germancito | BB17: LMMP233-F | BC17: LIMA METROPOLITANA | BD17: =IF(COUNTA(Q17:AP17)>0,INDEX(Q17:AP17,,max(IF(Q17:AP17<>"",COLUMN(Q17:AP17)))-16),"") -> San Martín de Porres | BE17: FTTH | BF17: SI | BG17: ALTA NUEVA | BL17: 1 PLAY | BM17: Campaña Regular | BN17: 110 | BO17: 500MBPS | BP17: SI | BQ17: NO | BR17: Ninguno | BS17: 1 | BU17: =IF($A17<>"", DATE(YEAR($A17),MONTH($A17),DAY($A17)),"") -> 46184 | BV17: =IF($E17<>"",DATE(YEAR($E17),MONTH($E17),DAY($E17)),"") -> 46185 | BW17: =IF($E17<>"",TEXT($E17,"HH"),"") -> 16 | BX17: 46186 | BY17: 1 | BZ17: =IF(B17<>"",VALUE(LEFT(B17)),"") -> 7 | CA17: {=IF($A17<>"",INDEX(LISTA!$M$2:$N$27,MATCH($BC17,LISTA!$N$2:$N$27,0),1),"")} -> 1 | CB17: =IF($A17<>"",MONTH(BU17),"") -> 6 | CC17: =IF($BX17<>"",MONTH(BX17),"") -> 6
A18: 46196.789 | B18: 7 - INSTALADA | C18: MASIVO RESIDENCIAL | D18: PAOLA | E18: 46197.458 | F18: PROCEDE | G18: 104793755 | H18: 88574820 | I18: GABRIEL | J18: 959579554 | K18: DNI | L18: 72000616 | M18: KARELIA BEATRIZ GAVILAN PURILLA | N18: 33908 | O18: ICA | P18: 110101 | AA18: Ica | AQ18: Javier | AR18: Nancy | AS18: kareliagp.gp@gmail.com | AU18: 959579554 | AV18: 959579554 | AW18: Av pachacutec yupanqui 986 parcona , ica , ica | AX18: 1 | AY18: S/I | AZ18: -14.04519699, -75.70771398 | BA18: CADIMOTORS/MOTO REPUESTOS Y TALLER | BB18: ICPN008 | BC18: ICA | BD18: =IF(COUNTA(Q18:AP18)>0,INDEX(Q18:AP18,,max(IF(Q18:AP18<>"",COLUMN(Q18:AP18)))-16),"") -> Ica | BE18: HFC | BF18: NO | BG18: ALTA NUEVA | BL18: 1 PLAY | BM18: Campaña Promo Mediana | BN18: 89 | BO18: 400MBPS | BP18: NO | BQ18: NO | BR18: Ninguno | BS18: Ninguno | BU18: =IF($A18<>"", DATE(YEAR($A18),MONTH($A18),DAY($A18)),"") -> 46196 | BV18: =IF($E18<>"",DATE(YEAR($E18),MONTH($E18),DAY($E18)),"") -> 46197 | BW18: =IF($E18<>"",TEXT($E18,"HH"),"") -> 11 | BX18: 46197 | BY18: 2 | BZ18: =IF(B18<>"",VALUE(LEFT(B18)),"") -> 7 | CA18: {=IF($A18<>"",INDEX(LISTA!$M$2:$N$27,MATCH($BC18,LISTA!$N$2:$N$27,0),1),"")} -> 13 | CB18: =IF($A18<>"",MONTH(BU18),"") -> 6 | CC18: =IF($BX18<>"",MONTH(BX18),"") -> 6
A19: 46190.47 | B19: 7 - INSTALADA | C19: MASIVO RESIDENCIAL | D19: NAYELI | E19: 46198.375 | F19: CONFIRMA VISITA /Rechazado por mala oferta - Campo - SE MANDO A LEVANTAR LA SOT | G19: 104610174 | H19: 88407642 | I19: JESSICA | J19: 993793126 | K19: DNI | L19: 06063811 | M19: ALEJANDRO ENRIQUE PALOMINO LEON | N19: 21472 | O19: JUNIN | P19: 110101 | AF19: Rimac | AQ19: ADALBERTO | AR19: OLGA | AS19: abogadopalomino@hotmail.com | AU19: 993793126 | AV19: 993793126 | AW19: PASAJE CENTRAL 123 | AX19: 4 | AY19: 401 | AZ19: -12.030148683042182, -77.04209244735932 | BA19: NEGOCIOS Y SERVICIOS D. ALCANTARA | BB19: LMRC044-F | BC19: LIMA METROPOLITANA | BD19: =IF(COUNTA(Q19:AP19)>0,INDEX(Q19:AP19,,max(IF(Q19:AP19<>"",COLUMN(Q19:AP19)))-16),"") -> Rimac | BE19: FTTH | BF19: SI | BG19: ALTA NUEVA | BL19: 1 PLAY + L1MAX | BM19: Campaña Regular PRO | BN19: 110 | BO19: 500MBPS | BP19: SI | BQ19: NO | BR19: Ninguno | BS19: 1 | BU19: =IF($A19<>"", DATE(YEAR($A19),MONTH($A19),DAY($A19)),"") -> 46190 | BV19: =IF($E19<>"",DATE(YEAR($E19),MONTH($E19),DAY($E19)),"") -> 46198 | BW19: =IF($E19<>"",TEXT($E19,"HH"),"") -> 09 | BX19: 46198 | BY19: 1 | BZ19: =IF(B19<>"",VALUE(LEFT(B19)),"") -> 7 | CA19: {=IF($A19<>"",INDEX(LISTA!$M$2:$N$27,MATCH($BC19,LISTA!$N$2:$N$27,0),1),"")} -> 1 | CB19: =IF($A19<>"",MONTH(BU19),"") -> 6 | CC19: =IF($BX19<>"",MONTH(BX19),"") -> 6
A20: 46200.749 | B20: 7 - INSTALADA | C20: MASIVO RESIDENCIAL | D20: NAYELI | E20: 46203.375 | F20: PROCEDE | G20: 104909457 | H20: 88679217 | I20: GABRIEL | J20: 997867217 | K20: DNI | L20: 08450266 | M20: NORMA MONICA, PACHECHO AGUILAR | N20: 24235 | O20: CUSCO | P20: 080101 | AF20: San Martín de Porres | AQ20: CARLOS | AR20: ANA | AS20: monikapachecho840@gmail.com | AU20: 997867217 | AV20: 997867217 | AW20: AV UNIVERSITARIA 621 URB SEÑOR DE CONDEVILLA | AX20: 2 | AY20: S/I | AZ20: -12.020495, -77.075867 | BA20: JR LAS AMERICAS | BB20: LMMP059-S | BC20: LIMA METROPOLITANA | BD20: =IF(COUNTA(Q20:AP20)>0,INDEX(Q20:AP20,,max(IF(Q20:AP20<>"",COLUMN(Q20:AP20)))-16),"") -> San Martín de Porres | BE20: FTTH | BF20: NO | BG20: ALTA NUEVA | BL20: 3 PLAY + TV ESTANDAR | BM20: Campaña Regular | BN20: 155 | BO20: 200MBPS | BP20: NO | BQ20: NO | BR20: Ninguno | BS20: Ninguno | BU20: =IF($A20<>"", DATE(YEAR($A20),MONTH($A20),DAY($A20)),"") -> 46200 | BV20: =IF($E20<>"",DATE(YEAR($E20),MONTH($E20),DAY($E20)),"") -> 46203 | BW20: =IF($E20<>"",TEXT($E20,"HH"),"") -> 09 | BX20: 46203 | BY20: 1 | BZ20: =IF(B20<>"",VALUE(LEFT(B20)),"") -> 7 | CA20: {=IF($A20<>"",INDEX(LISTA!$M$2:$N$27,MATCH($BC20,LISTA!$N$2:$N$27,0),1),"")} -> 1 | CB20: =IF($A20<>"",MONTH(BU20),"") -> 6 | CC20: =IF($BX20<>"",MONTH(BX20),"") -> 6
A21: 46193.5 | B21: 7 - INSTALADA | C21: MASIVO RESIDENCIAL | D21: PAOLA | E21: 46195.458 | F21: no coincide | G21: 104449975 | H21: 88480813 | I21: ANGHELL | J21: 977370315 | K21: DNI | L21: 75081907 | M21: MANUEL ALDAYR MONTUFAR LAIME | N21: 37189 | O21: CUSCO | P21: 07081 | X21: Espinar | AQ21: MANUEL | AR21: FILOMENA | AS21: AQPFEX1@GMAIL.COM | AU21: 977370315 | AV21: 977370315 | AW21: ubr huarcanto mz a1 lt 17 | AX21: 2 | AY21: 2A | AZ21: -14.799989, -71.411517 | BA21: calle nueva baja | BB21: CZES020-F | BC21: CUSCO | BD21: =IF(COUNTA(Q21:AP21)>0,INDEX(Q21:AP21,,max(IF(Q21:AP21<>"",COLUMN(Q21:AP21)))-16),"") -> Espinar | BE21: FTTH | BF21: NO | BG21: ALTA NUEVA | BL21: 2PLAY + TELF | BM21: Campaña Relámpago | BN21: 94 | BO21: 400MBPS | BP21: NO | BQ21: SI | BR21: Ninguno | BS21: Ninguno | BU21: =IF($A21<>"", DATE(YEAR($A21),MONTH($A21),DAY($A21)),"") -> 46193 | BV21: =IF($E21<>"",DATE(YEAR($E21),MONTH($E21),DAY($E21)),"") -> 46195 | BW21: =IF($E21<>"",TEXT($E21,"HH"),"") -> 11 | BX21: 46194 | BY21: 2 | BZ21: =IF(B21<>"",VALUE(LEFT(B21)),"") -> 7 | CA21: {=IF($A21<>"",INDEX(LISTA!$M$2:$N$27,MATCH($BC21,LISTA!$N$2:$N$27,0),1),"")} -> 10 | CB21: =IF($A21<>"",MONTH(BU21),"") -> 6 | CC21: =IF($BX21<>"",MONTH(BX21),"") -> 6
A22: 46199.594 | B22: 7 - INSTALADA | C22: MASIVO RESIDENCIAL | D22: NAYELI | E22: 46201.458 | F22: CL QUIERE INSTALACION PARA EL LUNES | G22: 104872550 | H22: 88659360 | I22: JESSICA | J22: 959385387 | K22: DNI | L22: 40494768 | M22: TEODORO SAICO SUCLLE | N22: 28834 | O22: CUSCO | P22: 070801 | T22: Arequipa | AQ22: NOLASCO | AR22: PAULINA | AS22: Teosaico@hotmail.com | AU22: 959385387 | AV22: 959385387 | AW22: CALLE CAHUIDE 315 URB. LA LIBERTAD | AX22: 2 | AY22: NA | AZ22: -16.37709499, -71.56237894 | BA22: CALLE MIGUEL GRAU | BB22: AQCC004-S | BC22: AREQUIPA | BD22: =IF(COUNTA(Q22:AP22)>0,INDEX(Q22:AP22,,max(IF(Q22:AP22<>"",COLUMN(Q22:AP22)))-16),"") -> Arequipa | BE22: FTTH | BF22: SI | BG22: ALTA NUEVA | BL22: 1 PLAY + L1MAX | BM22: Campaña Regular PRO | BN22: 110 | BO22: 500MBPS | BP22: SI | BQ22: NO | BR22: Ninguno | BS22: 1 | BU22: =IF($A22<>"", DATE(YEAR($A22),MONTH($A22),DAY($A22)),"") -> 46199 | BV22: =IF($E22<>"",DATE(YEAR($E22),MONTH($E22),DAY($E22)),"") -> 46201 | BW22: =IF($E22<>"",TEXT($E22,"HH"),"") -> 11 | BX22: 46201 | BY22: 2 | BZ22: =IF(B22<>"",VALUE(LEFT(B22)),"") -> 7 | CA22: {=IF($A22<>"",INDEX(LISTA!$M$2:$N$27,MATCH($BC22,LISTA!$N$2:$N$27,0),1),"")} -> 7 | CB22: =IF($A22<>"",MONTH(BU22),"") -> 6 | CC22: =IF($BX22<>"",MONTH(BX22),"") -> 6
A23: 46193.413 | B23: 7 - INSTALADA | C23: MASIVO RESIDENCIAL | D23: PAOLA | E23: 46196.458 | F23: PROCEDE ERROR EN DIRECCION | G23: 104714476 | H23: 88484483 | I23: YESSENIA | J23: 937542448 | K23: DNI | L23: 74602108 | M23: BRYAN ALFREDO MOREANO OBANDO | N23: 35956 | O23: CALLAO | P23: 070103 | AF23: La Victoria | AQ23: ALFREDO | AR23: MARITA | AS23: bmoreanoo@gmail.com | AU23: 937542448 | AV23: 937542448 | AW23: Jr. Carlos Gutiérrez Noriega 480 | AX23: 5 | AY23: 504 | AZ23: -12.07782297,-77.01624108 | BA23: JR CARLOS LOPEZ ALDANA | BB23: LMLV009-S | BC23: LIMA METROPOLITANA | BD23: =IF(COUNTA(Q23:AP23)>0,INDEX(Q23:AP23,,max(IF(Q23:AP23<>"",COLUMN(Q23:AP23)))-16),"") -> La Victoria | BE23: FTTH | BF23: NO | BG23: ALTA NUEVA | BL23: 1 PLAY | BM23: Campaña Promo Mediana | BN23: 89 | BO23: 400MBPS | BP23: NO | BQ23: NO | BR23: Ninguno | BS23: 1 | BU23: =IF($A23<>"", DATE(YEAR($A23),MONTH($A23),DAY($A23)),"") -> 46193 | BV23: =IF($E23<>"",DATE(YEAR($E23),MONTH($E23),DAY($E23)),"") -> 46196 | BW23: =IF($E23<>"",TEXT($E23,"HH"),"") -> 11 | BX23: 46196 | BY23: 1 | BZ23: =IF(B23<>"",VALUE(LEFT(B23)),"") -> 7 | CA23: {=IF($A23<>"",INDEX(LISTA!$M$2:$N$27,MATCH($BC23,LISTA!$N$2:$N$27,0),1),"")} -> 1 | CB23: =IF($A23<>"",MONTH(BU23),"") -> 6 | CC23: =IF($BX23<>"",MONTH(BX23),"") -> 6
A24: 46198.728 | B24: 7 - INSTALADA | C24: MASIVO RESIDENCIAL | D24: NAYELI | E24: 46200.5 | F24: CL CONFIRMA VISITA | G24: 104849431 | H24: 88626343 | I24: JESSICA | J24: 974629301 | K24: DNI | L24: 45346787 | M24: LEWIS RICHARD CORDOVA HUAMAN | N24: 32425 | O24: CAJAMARCA | P24: 061102 | AF24: Comas | AQ24: HECTOR | AR24: ERNESTINA | AS24: lrcordovah88@gmail.com | AU24: 974629301 | AV24: 974629301 | AW24: AV MICAELA BASTIDAS Mz G Lt - BLOCK 6 ( AV. MICAELA BASTIDAS S/N BLOCK 06 - TORRE A ETAPA 7 MZ. G ) Edificio: VISTA SOL - SOL DE COLLIQUE - TORRE A - BLOCK 06 | AX24: 10 | AY24: 1008 | AZ24: -11.927046, -77.059691 | BA24: AV. LOS CHASQUIS | BB24: LMCO181 | BC24: LIMA METROPOLITANA | BD24: =IF(COUNTA(Q24:AP24)>0,INDEX(Q24:AP24,,max(IF(Q24:AP24<>"",COLUMN(Q24:AP24)))-16),"") -> Comas | BE24: HFC | BF24: SI | BG24: ALTA NUEVA | BL24: 2 PLAY + TV ESTANDAR | BM24: Campaña Regular PRO | BN24: 170 | BO24: 400MBPS | BP24: SI | BQ24: NO | BR24: 2 | BS24: Ninguno | BU24: =IF($A24<>"", DATE(YEAR($A24),MONTH($A24),DAY($A24)),"") -> 46198 | BV24: =IF($E24<>"",DATE(YEAR($E24),MONTH($E24),DAY($E24)),"") -> 46200 | BW24: =IF($E24<>"",TEXT($E24,"HH"),"") -> 12 | BX24: 46200 | BY24: 1 | BZ24: =IF(B24<>"",VALUE(LEFT(B24)),"") -> 7 | CA24: {=IF($A24<>"",INDEX(LISTA!$M$2:$N$27,MATCH($BC24,LISTA!$N$2:$N$27,0),1),"")} -> 1 | CB24: =IF($A24<>"",MONTH(BU24),"") -> 6 | CC24: =IF($BX24<>"",MONTH(BX24),"") -> 6
A25: 46200.619 | B25: 7 - INSTALADA | C25: MASIVO RESIDENCIAL | D25: NAYELI | E25: 46202.458 | F25: PROCEDE | G25: 104901334 | H25: 88675788 | I25: JESSICA | J25: 998420484 | K25: DNI | L25: 32221145 | M25: RUSBEL MANUEL OQUEÑA PASTOR | N25: 27314 | O25: ANCASH | P25: 020601 | AF25: Comas | AQ25: MANUEL | AR25: HISABEL | AS25: roquenap@gmail.com | AU25: 998420484 | AV25: 998420484 | AW25: CALLE JOSE BERNARDO ALCEDO 370 URB. COLLIQUE | AX25: 3 | AY25: 302 | AZ25: -11.91581521571454, -77.02561845492386 | BA25: CALLE CHICLAYO | BB25: LMCO226-F | BC25: LIMA METROPOLITANA | BD25: =IF(COUNTA(Q25:AP25)>0,INDEX(Q25:AP25,,max(IF(Q25:AP25<>"",COLUMN(Q25:AP25)))-16),"") -> Comas | BE25: FTTH | BF25: NO | BG25: ALTA NUEVA | BL25: 1 PLAY | BM25: Campaña Promo Mediana | BN25: 89 | BO25: 400MBPS | BP25: NO | BQ25: NO | BR25: Ninguno | BS25: 1 | BU25: =IF($A25<>"", DATE(YEAR($A25),MONTH($A25),DAY($A25)),"") -> 46200 | BV25: =IF($E25<>"",DATE(YEAR($E25),MONTH($E25),DAY($E25)),"") -> 46202 | BW25: =IF($E25<>"",TEXT($E25,"HH"),"") -> 11 | BX25: 46202 | BY25: 3 | BZ25: =IF(B25<>"",VALUE(LEFT(B25)),"") -> 7 | CA25: {=IF($A25<>"",INDEX(LISTA!$M$2:$N$27,MATCH($BC25,LISTA!$N$2:$N$27,0),1),"")} -> 1 | CB25: =IF($A25<>"",MONTH(BU25),"") -> 6 | CC25: =IF($BX25<>"",MONTH(BX25),"") -> 6
A26: 46195.509 | B26: 7 - INSTALADA | C26: MASIVO RESIDENCIAL | D26: NAYELI | E26: 46196.458 | F26: PROCEDE AXB | G26: 104742955 | H26: 88519977 | I26: JESSICA | J26: 935195970 | K26: DNI | L26: 42520693 | M26: MARCO ANTONIO JAMANCA ESPINOZA | N26: 30888 | O26: ANCASH | P26: 020101 | R26: Huaraz | AQ26: DIONICIO | AR26: EUGENIA MARCELA | AS26: Marcojmanca@gmail.com | AU26: 935195970 | AV26: 935195970 | AW26: PS. SANTO DOMINGO 120 | AX26: 3 | AY26: 1 | AZ26: -9.508119659146413, -77.5320333439741 | BA26: JIRON INDUSTRIAL | BB26: HZIN044-F | BC26: ANCASH | BD26: =IF(COUNTA(Q26:AP26)>0,INDEX(Q26:AP26,,max(IF(Q26:AP26<>"",COLUMN(Q26:AP26)))-16),"") -> Huaraz | BE26: FTTH | BF26: NO | BG26: ALTA NUEVA | BL26: 1 PLAY | BM26: Campaña Regular PRO | BN26: 110 | BO26: 500MBPS | BP26: SI | BQ26: NO | BR26: Ninguno | BS26: 1 | BU26: =IF($A26<>"", DATE(YEAR($A26),MONTH($A26),DAY($A26)),"") -> 46195 | BV26: =IF($E26<>"",DATE(YEAR($E26),MONTH($E26),DAY($E26)),"") -> 46196 | BW26: =IF($E26<>"",TEXT($E26,"HH"),"") -> 11 | BX26: 46196 | BY26: 2 | BZ26: =IF(B26<>"",VALUE(LEFT(B26)),"") -> 7 | CA26: {=IF($A26<>"",INDEX(LISTA!$M$2:$N$27,MATCH($BC26,LISTA!$N$2:$N$27,0),1),"")} -> 5 | CB26: =IF($A26<>"",MONTH(BU26),"") -> 6 | CC26: =IF($BX26<>"",MONTH(BX26),"") -> 6
A27: 46192.698 | B27: 7 - INSTALADA | C27: MASIVO RESIDENCIAL | D27: PAOLA | E27: 46200.458 | F27: INSTALACION A MEDIAS - RESERVA TERMINARAN EL 28/06 POR DECOS, CONFIRMADO CON CLIENTE. | G27: 104867348 | H27: 88655700 | I27: JULIANA | J27: 978345537 | K27: DNI | L27: 76586680 | M27: ERICK ABRAHAM HIGINIO SOTELO | N27: 36140 | O27: LIMA METROPOLITANA | P27: 150128 | AF27: Comas | AQ27: ABRAHAM | AR27: LUZ | AS27: ERICK_1199@HOTMAIL.COM | AU27: 978 345 537 | AV27: 978 345 537 | AW27: DIRECCION: MZ G2 LOTE 30 URB. EL ALAMO 2DA ETAPA, COMAS. | AX27: 2 | AY27: 1 | AZ27: -11.924353, -77.063183 | BA27: AV. MICAELA CON AV. TRAPICHE. | BB27: LMCO023 | BC27: LIMA METROPOLITANA | BD27: =IF(COUNTA(Q27:AP27)>0,INDEX(Q27:AP27,,max(IF(Q27:AP27<>"",COLUMN(Q27:AP27)))-16),"") -> Comas | BE27: HFC | BF27: SI | BG27: ALTA NUEVA | BL27: 2 PLAY + TV ESTANDAR | BM27: Campaña Regular | BN27: 170 | BO27: 400MBPS | BP27: SI | BQ27: NO | BR27: 2 | BS27: Ninguno | BU27: =IF($A27<>"", DATE(YEAR($A27),MONTH($A27),DAY($A27)),"") -> 46192 | BV27: =IF($E27<>"",DATE(YEAR($E27),MONTH($E27),DAY($E27)),"") -> 46200 | BW27: =IF($E27<>"",TEXT($E27,"HH"),"") -> 11 | BX27: 46203 | BY27: 2 | BZ27: =IF(B27<>"",VALUE(LEFT(B27)),"") -> 7 | CA27: {=IF($A27<>"",INDEX(LISTA!$M$2:$N$27,MATCH($BC27,LISTA!$N$2:$N$27,0),1),"")} -> 1 | CB27: =IF($A27<>"",MONTH(BU27),"") -> 6 | CC27: =IF($BX27<>"",MONTH(BX27),"") -> 6
A28: 46198.753 | B28: 7 - INSTALADA | C28: MASIVO RESIDENCIAL | D28: NAYELI | E28: 46203.375 | F28: PENDIENTE CULMINAR INSTALACION A LAS 3PM | G28: 104850593 | H28: 88626803 | I28: GABRIEL | J28: 923619505 | K28: DNI | L28: 47883104 | M28: MINES BALTIERREZ, FLOR STEFANY | N28: 34151 | O28: LIMA METROPOLITANA | P28: 150113 | AF28: Carabayllo | AQ28: RAFAEL | AR28: FLOR | AS28: stefmines2@gmail.com | AU28: 923619505 | AV28: 923619505 | AW28: JIRON 9 DE OCTUBRE 501 CARABAYLLO | AX28: 1 | AY28: S/I | AZ28: -11.886848358,-77.020306622 | BA28: A 1 CDRA DE HABLA BROSTER | BB28: LMBY014-S | BC28: LIMA METROPOLITANA | BD28: =IF(COUNTA(Q28:AP28)>0,INDEX(Q28:AP28,,max(IF(Q28:AP28<>"",COLUMN(Q28:AP28)))-16),"") -> Carabayllo | BE28: FTTH | BF28: NO | BG28: ALTA NUEVA | BL28: 1 PLAY | BM28: Campaña Promo Mediana | BN28: 89 | BO28: 400MBPS | BP28: NO | BQ28: NO | BR28: Ninguno | BS28: Ninguno | BU28: =IF($A28<>"", DATE(YEAR($A28),MONTH($A28),DAY($A28)),"") -> 46198 | BV28: =IF($E28<>"",DATE(YEAR($E28),MONTH($E28),DAY($E28)),"") -> 46203 | BW28: =IF($E28<>"",TEXT($E28,"HH"),"") -> 09 | BX28: 46203 | BY28: 3 | BZ28: =IF(B28<>"",VALUE(LEFT(B28)),"") -> 7 | CA28: {=IF($A28<>"",INDEX(LISTA!$M$2:$N$27,MATCH($BC28,LISTA!$N$2:$N$27,0),1),"")} -> 1 | CB28: =IF($A28<>"",MONTH(BU28),"") -> 6 | CC28: =IF($BX28<>"",MONTH(BX28),"") -> 6
A29: 46192.563 | B29: 5 - CTO - EXCEDE METRAJE | C29: MASIVO RESIDENCIAL | D29: PAOLA | E29: 46196.542 | F29: SE ENVIA CORREO PARA VALIDAR COBERTURA. SI SE PUEDE JALAR | G29: 104679491 | H29: 88466519 | I29: ANTHONELLA | J29: 957120462 | K29: DNI | L29: 71493074 | M29: ALIS MERCEDES FLORES | N29: 35028 | O29: LA LIBERTAD | P29: 130901 | AC29: Sánchez Carrión | AQ29: AGUSTIN | AR29: VENANCIA | AS29: alismercedesflores@gmail.com | AU29: 957120462 | AV29: 957120462 | AW29: JR ALFONZO HUGARTE 131 HUAMACHUCO | AX29: 3 | AY29: CASA | AZ29: -7.812432448, -78.050758315 | BA29: CRUCE CON JR TAFUR | BB29: LLHM003-F | BC29: LA LIBERTAD | BD29: =IF(COUNTA(Q29:AP29)>0,INDEX(Q29:AP29,,max(IF(Q29:AP29<>"",COLUMN(Q29:AP29)))-16),"") -> Sánchez Carrión | BE29: FTTH | BF29: NO | BG29: ALTA NUEVA | BL29: 1 PLAY | BM29: Campaña Regular | BN29: 89 | BO29: 400MBPS | BP29: SI | BQ29: NO | BR29: 1 | BS29: Ninguno | BU29: =IF($A29<>"", DATE(YEAR($A29),MONTH($A29),DAY($A29)),"") -> 46192 | BV29: =IF($E29<>"",DATE(YEAR($E29),MONTH($E29),DAY($E29)),"") -> 46196 | BW29: =IF($E29<>"",TEXT($E29,"HH"),"") -> 13 | BZ29: =IF(B29<>"",VALUE(LEFT(B29)),"") -> 5 | CA29: {=IF($A29<>"",INDEX(LISTA!$M$2:$N$27,MATCH($BC29,LISTA!$N$2:$N$27,0),1),"")} -> 15 | CB29: =IF($A29<>"",MONTH(BU29),"") -> 6 | CC29: =IF($BX29<>"",MONTH(BX29),"")
A30: 46200.641 | B30: 5 - CTO - EXCEDE METRAJE | C30: MASIVO RESIDENCIAL | D30: NAYELI | E30: 46203.667 | F30: Rechazado Por Falta De Infraestructura De Red - Campo | G30: 104904353 | H30: 88676944 | I30: JULIANA | J30: 929113007 | K30: DNI | L30: 76186707 | M30: MEDALYT ROCIO COAQUERA PONGO | N30: 35617 | O30: TACNA | P30: 220201 | AN30: Tacna | AQ30: TEODORO | AR30: IRMA | AS30: DF0889538@GMAIL.COM | AU30: 929113007 | AV30: 929113007 | AW30: URB. EL CHOLOLO MZ A2 LOTE 3, TACNA CERCADO. | AX30: 1 | AY30: 1 | AZ30: -18.022236, -70.27216687 | BA30: POR LA AV. ZARUMILLA | BB30: TCNA147-F | BC30: TACNA | BD30: =IF(COUNTA(Q30:AP30)>0,INDEX(Q30:AP30,,max(IF(Q30:AP30<>"",COLUMN(Q30:AP30)))-16),"") -> Tacna | BE30: FTTH | BF30: NO | BG30: ALTA NUEVA | BL30: 1 PLAY + L1MAX | BM30: Campaña Regular | BN30: 110 | BO30: 1000MBPS | BP30: SI | BQ30: NO | BR30: Ninguno | BS30: 1 | BU30: =IF($A30<>"", DATE(YEAR($A30),MONTH($A30),DAY($A30)),"") -> 46200 | BV30: =IF($E30<>"",DATE(YEAR($E30),MONTH($E30),DAY($E30)),"") -> 46203 | BW30: =IF($E30<>"",TEXT($E30,"HH"),"") -> 16 | BZ30: =IF(B30<>"",VALUE(LEFT(B30)),"") -> 5 | CA30: {=IF($A30<>"",INDEX(LISTA!$M$2:$N$27,MATCH($BC30,LISTA!$N$2:$N$27,0),1),"")} -> 24 | CB30: =IF($A30<>"",MONTH(BU30),"") -> 6 | CC30: =IF($BX30<>"",MONTH(BX30),"")
A31: 46195.416 | B31: 5 - BAJA-NO DESEA | C31: MASIVO RESIDENCIAL | D31: NAYELI | E31: 46196.583 | F31: CLIENTE QUERIA SU INSTALACION PARA ESE MISMO DIA, SI O SI, NO DESEA REPROGRAMACION | G31: 104737775 | H31: 88515175 | I31: JESSICA | J31: 917707080 | K31: DNI | L31: 70090949 | M31: KRISTIAN COLLANQUI FLORES | N31: 33904 | O31: PUNO | P31: 200604 | AL31: San Román | AQ31: PASCUAL MARCIAL | AR31: LEONCIA | AS31: kristiancollanqui2705@gmail.com | AU31: 917707080 | AV31: 917707080 | AW31: kristiancollanqui2705@gmail.com | AX31: 2 | AY31: NA | AZ31: -15.466703, -70.143151 | BA31: JIRON COPACABANA | BB31: PUJL123-F | BC31: PUNO | BD31: =IF(COUNTA(Q31:AP31)>0,INDEX(Q31:AP31,,max(IF(Q31:AP31<>"",COLUMN(Q31:AP31)))-16),"") -> San Román | BE31: FTTH | BF31: SI | BG31: ALTA NUEVA | BL31: 1 PLAY | BM31: Campaña Promo Mediana | BN31: 89 | BO31: 400MBPS | BP31: NO | BQ31: NO | BR31: Ninguno | BS31: 1 | BU31: =IF($A31<>"", DATE(YEAR($A31),MONTH($A31),DAY($A31)),"") -> 46195 | BV31: =IF($E31<>"",DATE(YEAR($E31),MONTH($E31),DAY($E31)),"") -> 46196 | BW31: =IF($E31<>"",TEXT($E31,"HH"),"") -> 14 | BZ31: =IF(B31<>"",VALUE(LEFT(B31)),"") -> 5 | CA31: {=IF($A31<>"",INDEX(LISTA!$M$2:$N$27,MATCH($BC31,LISTA!$N$2:$N$27,0),1),"")} -> 22 | CB31: =IF($A31<>"",MONTH(BU31),"") -> 6 | CC31: =IF($BX31<>"",MONTH(BX31),"")
A32: 46191.461 | B32: 5 - BAJA-NO DESEA | C32: MASIVO RESIDENCIAL | D32: NAYELI | E32: 46197.375 | F32: VENTA ANTIGUO, CLIENTE RECIBIO PROMOCION DE CLARO SOBRE SU INSTALACION ACTUAL, DECIDE QUEDARSE CON ELLOS. | G32: 104642463 | H32: 88433432 | I32: JESSICA | J32: 945547763 | K32: DNI | L32: 21122076 | M32: RAUL DIEGO YARASCA MANDUJANO | N32: 25972 | O32: JUNIN | P32: 110325 | AB32: Chanchamayo | AQ32: FELIX | AR32: ESTEFANIA | AS32: ryarasca123@gmail.com | AU32: 945547763 | AV32: 945547763 | AW32: AV. ASHANINKA 235 URB. EL PARAISO | AX32: 4 | AY32: 4A | AZ32: -11.0675295, -75.339234545 | BA32: IEP. Santa Maria Reyna | BB32: JNCM008-F | BC32: JUNIN | BD32: =IF(COUNTA(Q32:AP32)>0,INDEX(Q32:AP32,,max(IF(Q32:AP32<>"",COLUMN(Q32:AP32)))-16),"") -> Chanchamayo | BE32: FTTH | BF32: SI | BG32: ALTA NUEVA | BL32: 1 PLAY | BM32: Campaña Promo Mediana | BN32: 89 | BO32: 400MBPS | BP32: NO | BQ32: NO | BR32: Ninguno | BS32: 1 | BU32: =IF($A32<>"", DATE(YEAR($A32),MONTH($A32),DAY($A32)),"") -> 46191 | BV32: =IF($E32<>"",DATE(YEAR($E32),MONTH($E32),DAY($E32)),"") -> 46197 | BW32: =IF($E32<>"",TEXT($E32,"HH"),"") -> 09 | BZ32: =IF(B32<>"",VALUE(LEFT(B32)),"") -> 5 | CA32: {=IF($A32<>"",INDEX(LISTA!$M$2:$N$27,MATCH($BC32,LISTA!$N$2:$N$27,0),1),"")} -> 14 | CB32: =IF($A32<>"",MONTH(BU32),"") -> 6 | CC32: =IF($BX32<>"",MONTH(BX32),"")
A33: 46195.545 | B33: 5 - BAJA-NO DESEA | C33: MASIVO RESIDENCIAL | D33: NAYELI | E33: 46197.583 | F33: LLAMARON A CLIENTE PARA INDICARLE QUE SU RED ESTA SATURADA, CLIENTE CONTRATÓ CON OTRO OPERADOR | G33: 104748456 | H33: 88524046 | I33: ANGHELL | J33: 963188744 | K33: DNI | L33: 74079616 | M33: PAMELA YVETTE MALDONADO QUISPE | N33: 35257 | O33: AREQUIPA | P33: 040109 | T33: Arequipa | AQ33: VICTOR MANUEL | AR33: DIONISIA | AS33: maldonadopamela986@gmail.com | AU33: 963188744 | AV33: 963188744 | AW33: urb CAMPO DE MARTE MZ P LT 42, PAUCARPATA, AREQUIPA | AX33: 3 | AY33: 0 | AZ33: -16.427180557097067, -71.4941595331016 | BA33: CALLE TUPAC AMARU | BB33: AQPP047 | BC33: AREQUIPA | BD33: =IF(COUNTA(Q33:AP33)>0,INDEX(Q33:AP33,,max(IF(Q33:AP33<>"",COLUMN(Q33:AP33)))-16),"") -> Arequipa | BE33: HFC | BF33: SI | BG33: ALTA NUEVA | BL33: 1 PLAY | BM33: Campaña Promo Mediana | BN33: 89 | BO33: 400MBPS | BP33: NO | BQ33: NO | BR33: Ninguno | BS33: 1 | BU33: =IF($A33<>"", DATE(YEAR($A33),MONTH($A33),DAY($A33)),"") -> 46195 | BV33: =IF($E33<>"",DATE(YEAR($E33),MONTH($E33),DAY($E33)),"") -> 46197 | BW33: =IF($E33<>"",TEXT($E33,"HH"),"") -> 14 | BZ33: =IF(B33<>"",VALUE(LEFT(B33)),"") -> 5 | CA33: {=IF($A33<>"",INDEX(LISTA!$M$2:$N$27,MATCH($BC33,LISTA!$N$2:$N$27,0),1),"")} -> 7 | CB33: =IF($A33<>"",MONTH(BU33),"") -> 6 | CC33: =IF($BX33<>"",MONTH(BX33),"")
A34: 46200.72 | B34: 5 - BAJA-MALA INFO VENTA | C34: MASIVO RESIDENCIAL | D34: NAYELI | E34: 46202.458 | F34: Rechazado Por Mala Oferta - Campo | G34: 104908264 | H34: 88678456 | I34: GABRIEL | J34: 912145179 | K34: DNI | L34: 74650613 | M34: JIMENEZ VASQUEZ SOLIS, JACK ISMAEL | N34: 35732 | O34: LIMA METROPOLITANA | P34: 150132 | AF34: San Juan de Lurigancho | AQ34: ABEL | AR34: YOVANA | AS34: jackismaeljimenezvasquezsolis@gmail.com | AU34: 912145179 | AV34: 912145179 | AW34: jr tahuantinsuyo 638 URB Zarate | AX34: 4 | AY34: 5 | AZ34: -12.027747, -77.002502 | BA34: A 1 CDRA DE LA COMISARIA ZARATE | BB34: LMJL062 | BC34: LIMA METROPOLITANA | BD34: =IF(COUNTA(Q34:AP34)>0,INDEX(Q34:AP34,,max(IF(Q34:AP34<>"",COLUMN(Q34:AP34)))-16),"") -> San Juan de Lurigancho | BE34: HFC | BF34: NO | BG34: ALTA NUEVA | BL34: 1 PLAY | BM34: Campaña Regular | BN34: 89 | BO34: 400MBPS | BP34: NO | BQ34: NO | BR34: Ninguno | BS34: Ninguno | BU34: =IF($A34<>"", DATE(YEAR($A34),MONTH($A34),DAY($A34)),"") -> 46200 | BV34: =IF($E34<>"",DATE(YEAR($E34),MONTH($E34),DAY($E34)),"") -> 46202 | BW34: =IF($E34<>"",TEXT($E34,"HH"),"") -> 11 | BZ34: =IF(B34<>"",VALUE(LEFT(B34)),"") -> 5 | CA34: {=IF($A34<>"",INDEX(LISTA!$M$2:$N$27,MATCH($BC34,LISTA!$N$2:$N$27,0),1),"")} -> 1 | CB34: =IF($A34<>"",MONTH(BU34),"") -> 6 | CC34: =IF($BX34<>"",MONTH(BX34),"")
A35: 46200.44 | B35: 4 - FLIPPING | C35: MASIVO RESIDENCIAL | D35: NAYELI | E35: 46200.667 | F35: PROCEDE | G35: 104889152 | H35: 88671317 | I35: ANTHONELLA | J35: 974306888 | K35: DNI | L35: 74861925 | M35: JUAN JOSE MARTIN GUTIERREZ ESCALANTE | N35: 35107 | O35: LIMA METROPOLITANA | P35: 150101 | AF35: Carabayllo | AQ35: GILBERTO | AR35: DELA | AS35: JUANJO.GUTIERRESES GMAIL.COM | AU35: 974306888 | AV35: 974306888 | AW35: CALLE LOS LAURES MZ D LT 33 , UB LA RIVERA CARABAYLLO | AX35: 1 | AY35: ND | AZ35: -11.878564699683325 -77.02282265736812 | BA35: URBANIZACION LA RIVERA | BB35: LMBY009-S | BC35: LIMA METROPOLITANA | BD35: =IF(COUNTA(Q35:AP35)>0,INDEX(Q35:AP35,,max(IF(Q35:AP35<>"",COLUMN(Q35:AP35)))-16),"") -> Carabayllo | BE35: FTTH | BF35: SI | BG35: ALTA NUEVA | BL35: 1 PLAY | BM35: Campaña Regular | BN35: 94 | BO35: 400MBPS | BP35: NO | BQ35: SI | BR35: Ninguno | BS35: Ninguno | BU35: =IF($A35<>"", DATE(YEAR($A35),MONTH($A35),DAY($A35)),"") -> 46200 | BV35: =IF($E35<>"",DATE(YEAR($E35),MONTH($E35),DAY($E35)),"") -> 46200 | BW35: =IF($E35<>"",TEXT($E35,"HH"),"") -> 16 | BZ35: =IF(B35<>"",VALUE(LEFT(B35)),"") -> 4 | CA35: {=IF($A35<>"",INDEX(LISTA!$M$2:$N$27,MATCH($BC35,LISTA!$N$2:$N$27,0),1),"")} -> 1 | CB35: =IF($A35<>"",MONTH(BU35),"") -> 6 | CC35: =IF($BX35<>"",MONTH(BX35),"")
A36: 46193.495 | B36: 4 - FLIPPING | C36: MASIVO RESIDENCIAL | D36: PAOLA | E36: 46200.583 | F36: REPRO PARA EL 27/06 | G36: 104702456 | H36: 88479774 | I36: JUAN DIEGO | J36: 920477366 | K36: DNI | L36: 76423649 | M36: ZHANDLER PINEDA SANCHEZ | N36: 37529 | O36: HUANUCO | P36: 100102 | Z36: Huánuco | AQ36: Zacarias | AR36: Mercedes | AS36: zhatisa3909@gmail.com | AU36: 920477366 | AV36: 920477366 | AW36: jiron brasil mz t lt 1 URBANIZACION san luis sector 12 | AX36: 2 | AY36: 1A | AZ36: -9.9401925, -76.236067995 | BA36: Avenida Ricardo Palma | BB36: HNAM002-F | BC36: HUANUCO | BD36: =IF(COUNTA(Q36:AP36)>0,INDEX(Q36:AP36,,max(IF(Q36:AP36<>"",COLUMN(Q36:AP36)))-16),"") -> Huánuco | BE36: FTTH | BF36: SI | BG36: ALTA NUEVA | BL36: 1 PLAY | BM36: Campaña Regular | BN36: 110 | BO36: 500MBPS | BP36: SI | BQ36: NO | BR36: Ninguno | BS36: 1 | BU36: =IF($A36<>"", DATE(YEAR($A36),MONTH($A36),DAY($A36)),"") -> 46193 | BV36: =IF($E36<>"",DATE(YEAR($E36),MONTH($E36),DAY($E36)),"") -> 46200 | BW36: =IF($E36<>"",TEXT($E36,"HH"),"") -> 14 | BZ36: =IF(B36<>"",VALUE(LEFT(B36)),"") -> 4 | CA36: {=IF($A36<>"",INDEX(LISTA!$M$2:$N$27,MATCH($BC36,LISTA!$N$2:$N$27,0),1),"")} -> 12 | CB36: =IF($A36<>"",MONTH(BU36),"") -> 6 | CC36: =IF($BX36<>"",MONTH(BX36),"")
A37: 46188.459 | B37: 4 - FAC TEC-TORRE NO HABILITADA | C37: MASIVO RESIDENCIAL | D37: NAYELI | E37: 46190.375 | F37: EDIFICIO NO HABILITADO CON CLARO, NO PERMITEN TENDIDO AEREO | G37: 104547386 | H37: 88346622 | I37: JESSICA | J37: 987702720 | K37: DNI | L37: 42078293 | M37: JORGE ANIBAL BADO ESPINO | N37: 30630 | O37: LIMA | P37: 140110 | AF37: San Borja | AQ37: JORGE DANILO | AR37: MYRIAM TATIANA | AS37: bado.jorge@gmail.com | AU37: 987702720 | AV37: 987702720 | AW37: Avenida Juan Bielovucic Cavalier 157 Urbanización Chacarilla del Estanque | AX37: 5 | AY37: 501 | AZ37: -12.103503, -76.980941 | BA37: Puerta 4 auditorio pentagonito | BB37: 5222B06AS | BC37: LIMA METROPOLITANA | BD37: =IF(COUNTA(Q37:AP37)>0,INDEX(Q37:AP37,,max(IF(Q37:AP37<>"",COLUMN(Q37:AP37)))-16),"") -> San Borja | BE37: FTTH | BF37: NO | BG37: ALTA NUEVA | BL37: 1 PLAY + L1MAX | BM37: Campaña Regular PRO | BN37: 110 | BO37: 400MBPS | BP37: SI | BQ37: NO | BR37: Ninguno | BS37: 1 | BU37: =IF($A37<>"", DATE(YEAR($A37),MONTH($A37),DAY($A37)),"") -> 46188 | BV37: =IF($E37<>"",DATE(YEAR($E37),MONTH($E37),DAY($E37)),"") -> 46190 | BW37: =IF($E37<>"",TEXT($E37,"HH"),"") -> 09 | BZ37: =IF(B37<>"",VALUE(LEFT(B37)),"") -> 4 | CA37: {=IF($A37<>"",INDEX(LISTA!$M$2:$N$27,MATCH($BC37,LISTA!$N$2:$N$27,0),1),"")} -> 1 | CB37: =IF($A37<>"",MONTH(BU37),"") -> 6 | CC37: =IF($BX37<>"",MONTH(BX37),"")
A38: 46198.74 | B38: 3 - REPROGRAMADA | C38: MASIVO RESIDENCIAL | D38: NAYELI | E38: 46203.375 | F38: EN EJECUCION | G38: 104848535 | H38: 88625537 | I38: BRITNEY | J38: 955847780 | K38: DNI | L38: 40152975 | M38: GROWER HONORATO GARRO HUERTAS | N38: 28048 | O38: ANCASH | P38: 020509 | AF38: Los Olivos | AQ38: Fernando | AR38: Jacoba | AS38: growergarrohuertas@gmail.com | AU38: 955 847 780 | AV38: 955 847 780 | AW38: calle las gardenias mz c lt10 | AX38: 3 | AY38: 1 | AZ38: -11.944502 , -77.073282 | BA38: URBANIZACIÓN LAS GARDENIAS DE PRO | BB38: LMLO101 | BC38: LIMA METROPOLITANA | BD38: =IF(COUNTA(Q38:AP38)>0,INDEX(Q38:AP38,,max(IF(Q38:AP38<>"",COLUMN(Q38:AP38)))-16),"") -> Los Olivos | BE38: HFC | BF38: SI | BG38: ALTA NUEVA | BL38: 1 PLAY + L1MAX | BM38: Campaña Regular | BN38: 110 | BO38: 500MBPS | BP38: SI | BQ38: NO | BR38: Ninguno | BS38: Ninguno | BU38: =IF($A38<>"", DATE(YEAR($A38),MONTH($A38),DAY($A38)),"") -> 46198 | BV38: =IF($E38<>"",DATE(YEAR($E38),MONTH($E38),DAY($E38)),"") -> 46203 | BW38: =IF($E38<>"",TEXT($E38,"HH"),"") -> 09 | BZ38: =IF(B38<>"",VALUE(LEFT(B38)),"") -> 3 | CA38: {=IF($A38<>"",INDEX(LISTA!$M$2:$N$27,MATCH($BC38,LISTA!$N$2:$N$27,0),1),"")} -> 1 | CB38: =IF($A38<>"",MONTH(BU38),"") -> 6 | CC38: =IF($BX38<>"",MONTH(BX38),"")
A39: 46199.696 | B39: 3 - PROGRAMADA | C39: MASIVO RESIDENCIAL | D39: NAYELI | E39: 46206.375 | F39: EN EJECUCION | G39: 104876137 | H39: 88661759 | I39: BRITNEY | J39: 931290676 | K39: DNI | L39: 41673092 | M39: WALTER GUTIERREZ VILLANUEVA | N39: 30241 | O39: AYACUCHO | P39: 050112 | U39: Huamanga | AQ39: Celedonio | AR39: Alberta | AS39: Walter_gv@hotmail.com | AU39: 931290676 | AV39: 931290676 | AW39: Prolongación manco capac N° 1277 | AX39: 3 | AY39: 1 | AZ39: -13.154932, -74.23124 | BA39: Prolongación manco capac | BB39: AYAY016-S | BC39: AYACUCHO | BD39: =IF(COUNTA(Q39:AP39)>0,INDEX(Q39:AP39,,max(IF(Q39:AP39<>"",COLUMN(Q39:AP39)))-16),"") -> Huamanga | BE39: FTTH | BF39: NO | BG39: ALTA NUEVA | BL39: 1 PLAY | BM39: Campaña Promo Mediana | BN39: 89 | BO39: 400MBPS | BP39: NO | BQ39: NO | BR39: Ninguno | BS39: 1 | BU39: =IF($A39<>"", DATE(YEAR($A39),MONTH($A39),DAY($A39)),"") -> 46199 | BV39: =IF($E39<>"",DATE(YEAR($E39),MONTH($E39),DAY($E39)),"") -> 46206 | BW39: =IF($E39<>"",TEXT($E39,"HH"),"") -> 09 | BZ39: =IF(B39<>"",VALUE(LEFT(B39)),"") -> 3 | CA39: {=IF($A39<>"",INDEX(LISTA!$M$2:$N$27,MATCH($BC39,LISTA!$N$2:$N$27,0),1),"")} -> 8 | CB39: =IF($A39<>"",MONTH(BU39),"") -> 6 | CC39: =IF($BX39<>"",MONTH(BX39),"")
A40: 46200.406 | B40: 3 - PROGRAMADA | C40: MASIVO RESIDENCIAL | D40: NAYELI | E40: 46204.667 | F40: EN EJECUCION | G40: 104887811 | H40: 88670937 | I40: JUAN DIEGO | J40: 935507175 | K40: DNI | L40: 26961099 | M40: CESAR WILMAN SALAZAR GAMBOA | N40: 28087 | O40: CAJAMARCA | P40: 060101 | V40: Cajabamba | AQ40: ENRIQUE | AR40: WILBERTA | AS40: Frankzrodriguezsalazar@gmail.com | AU40: 935 507 175 | AV40: 935 507 175 | AW40: JIRON SUAREZ 190 | AX40: 1 | AY40: NA | AZ40: -7.622846114469324, -78.04942980699167 | BA40: JIRON JOSE LEAL | BB40: CJCB005-F | BC40: CAJAMARCA | BD40: =IF(COUNTA(Q40:AP40)>0,INDEX(Q40:AP40,,max(IF(Q40:AP40<>"",COLUMN(Q40:AP40)))-16),"") -> Cajabamba | BE40: FTTH | BF40: SI | BG40: ALTA NUEVA | BL40: 1 PLAY | BM40: Campaña Regular | BN40: 100 | BO40: 800MBPS | BP40: NO | BQ40: NO | BR40: Ninguno | BS40: 1 | BU40: =IF($A40<>"", DATE(YEAR($A40),MONTH($A40),DAY($A40)),"") -> 46200 | BV40: =IF($E40<>"",DATE(YEAR($E40),MONTH($E40),DAY($E40)),"") -> 46204 | BW40: =IF($E40<>"",TEXT($E40,"HH"),"") -> 16 | BZ40: =IF(B40<>"",VALUE(LEFT(B40)),"") -> 3 | CA40: {=IF($A40<>"",INDEX(LISTA!$M$2:$N$27,MATCH($BC40,LISTA!$N$2:$N$27,0),1),"")} -> 9 | CB40: =IF($A40<>"",MONTH(BU40),"") -> 6 | CC40: =IF($BX40<>"",MONTH(BX40),"")
A41: 46200.733 | B41: 3 - PROGRAMADA | C41: MASIVO RESIDENCIAL | D41: NAYELI | E41: 46202.583 | F41: EN EJECUCION | G41: 104907359 | H41: 88678780 | I41: OJT | J41: 925811235 | K41: DNI | L41: 48046824 | M41: Beyker Viera Ariza | N41: 34310 | O41: LIMA | P41: 150125 | AF41: San Martín de Porres | AQ41: Croas | AR41: Aydee | AS41: beyker_japones@hotmail.com | AU41: 925811235 | AV41: 925811235 | AW41: SAN JUAN BAUTISTA 344 | AX41: 1 | AY41: nada | AZ41: -12.016565071032252, -77.05693506451682 | BA41: jiron alheli | BB41: LMMP008-S | BC41: LIMA METROPOLITANA | BD41: =IF(COUNTA(Q41:AP41)>0,INDEX(Q41:AP41,,max(IF(Q41:AP41<>"",COLUMN(Q41:AP41)))-16),"") -> San Martín de Porres | BE41: FTTH | BF41: SI | BG41: ALTA NUEVA | BL41: 2PLAY + TELF | BM41: Campaña Regular | BN41: 94 | BO41: 400MBPS | BP41: NO | BQ41: SI | BR41: Ninguno | BS41: 1 | BU41: =IF($A41<>"", DATE(YEAR($A41),MONTH($A41),DAY($A41)),"") -> 46200 | BV41: =IF($E41<>"",DATE(YEAR($E41),MONTH($E41),DAY($E41)),"") -> 46202 | BW41: =IF($E41<>"",TEXT($E41,"HH"),"") -> 14 | BZ41: =IF(B41<>"",VALUE(LEFT(B41)),"") -> 3 | CA41: {=IF($A41<>"",INDEX(LISTA!$M$2:$N$27,MATCH($BC41,LISTA!$N$2:$N$27,0),1),"")} -> 1 | CB41: =IF($A41<>"",MONTH(BU41),"") -> 6 | CC41: =IF($BX41<>"",MONTH(BX41),"")
A42: 46203.436 | B42: 3 - PROGRAMADA | C42: MASIVO RESIDENCIAL | D42: NAYELI | E42: 46205.458 | F42: EN EJECUCION - DESEA PARA EL SABADO | G42: 104953424 | H42: 88716374 | I42: JESSICA | J42: 984741682 | K42: DNI | L42: 45622906 | M42: FABIOLA ISABEL PEREZ IBARRA | N42: 32454 | O42: CUSCO | P42: 070108 | X42: Cusco | AQ42: MARCIAL | AR42: MARGARITA | AS42: isabel.fiti@gmail.com | AU42: 984741682 | AV42: 984741682 | AW42: H. VIVA EL PERU ETAPA 1 MZ J LT 10 | AX42: 2 | AY42: 2B | AZ42: -13.539285, -71.960379 | BA42: COLEGIO, AV VIVA EL PERU | BB42: CZST011-S | BC42: CUSCO | BD42: =IF(COUNTA(Q42:AP42)>0,INDEX(Q42:AP42,,max(IF(Q42:AP42<>"",COLUMN(Q42:AP42)))-16),"") -> Cusco | BE42: FTTH | BF42: SI | BG42: ALTA NUEVA | BL42: 1 PLAY | BM42: Campaña Promo Mediana | BN42: 89 | BO42: 400MBPS | BQ42: NO | BR42: Ninguno | BS42: 1 | BU42: =IF($A42<>"", DATE(YEAR($A42),MONTH($A42),DAY($A42)),"") -> 46203 | BV42: =IF($E42<>"",DATE(YEAR($E42),MONTH($E42),DAY($E42)),"") -> 46205 | BW42: =IF($E42<>"",TEXT($E42,"HH"),"") -> 11 | BZ42: =IF(B42<>"",VALUE(LEFT(B42)),"") -> 3 | CA42: {=IF($A42<>"",INDEX(LISTA!$M$2:$N$27,MATCH($BC42,LISTA!$N$2:$N$27,0),1),"")} -> 10 | CB42: =IF($A42<>"",MONTH(BU42),"") -> 6 | CC42: =IF($BX42<>"",MONTH(BX42),"")
A43: 46203.455 | B43: 3 - PROGRAMADA | C43: MASIVO RESIDENCIAL | D43: NAYELI | E43: 46206.667 | F43: EN EJECUCION | G43: 104955525 | H43: 88717289 | I43: ANGHELL | J43: 947432126 | K43: DNI | L43: 76223959 | M43: EDY COPA QUISPE | N43: 34519 | O43: PUNO | P43: 140112 | AL43: San Román | AQ43: CECILIO | AR43: NECITARIA | AS43: quispeeddy91@gmail.com | AU43: 947432126 | AV43: 947432126 | AW43: CALLE NUEVA ZELANDA MZ D LT 9 - URB AEROPUERTO | AX43: 3 | AY43: 3A | AZ43: -15.47193, -70.138797 | BA43: CALLE OCONA | BB43: PUJL124-F | BC43: PUNO | BD43: =IF(COUNTA(Q43:AP43)>0,INDEX(Q43:AP43,,max(IF(Q43:AP43<>"",COLUMN(Q43:AP43)))-16),"") -> San Román | BE43: FTTH | BF43: NO | BG43: ALTA NUEVA | BL43: 1 PLAY | BM43: Campaña Promo Mediana | BN43: 89 | BO43: 400MBPS | BP43: NO | BQ43: NO | BR43: Ninguno | BS43: 1 | BU43: =IF($A43<>"", DATE(YEAR($A43),MONTH($A43),DAY($A43)),"") -> 46203 | BV43: =IF($E43<>"",DATE(YEAR($E43),MONTH($E43),DAY($E43)),"") -> 46206 | BW43: =IF($E43<>"",TEXT($E43,"HH"),"") -> 16 | BZ43: =IF(B43<>"",VALUE(LEFT(B43)),"") -> 3 | CA43: {=IF($A43<>"",INDEX(LISTA!$M$2:$N$27,MATCH($BC43,LISTA!$N$2:$N$27,0),1),"")} -> 22 | CB43: =IF($A43<>"",MONTH(BU43),"") -> 6 | CC43: =IF($BX43<>"",MONTH(BX43),"")
A44: 46203.466 | B44: 3 - PROGRAMADA | C44: MASIVO RESIDENCIAL | D44: NAYELI | E44: 46205.583 | F44: ENVIAR REPRO 01/07 | G44: 104957020 | H44: 88772246 | I44: JESSICA | J44: 910274676 | K44: DNI | L44: 47621042 | M44: ANGEL JESUS QUISPE SILVA | N44: 33773 | O44: CALLAO | P44: 240101 | AF44: San Martín de Porres | AQ44: ELIAS | AR44: OFELIA | AS44: angeljesus6600@gmail.com | AU44: 910274676 | AV44: 910274676 | AW44: ASOC. DE VIVIENDA SAN ANTONIO MZ A LT 15 | AX44: 1 | AY44: NA | AZ44: -11.988730439711787, -77.10411644472327 | BA44: VIVERO, FICUS, AUX CANTA | BB44: LMMP132-S | BC44: LIMA METROPOLITANA | BD44: =IF(COUNTA(Q44:AP44)>0,INDEX(Q44:AP44,,max(IF(Q44:AP44<>"",COLUMN(Q44:AP44)))-16),"") -> San Martín de Porres | BE44: FTTH | BF44: SI | BG44: ALTA NUEVA | BL44: 1 PLAY | BM44: Campaña Promo Mediana | BN44: 89 | BO44: 400MBPS | BP44: NO | BQ44: NO | BR44: Ninguno | BS44: 1 | BU44: =IF($A44<>"", DATE(YEAR($A44),MONTH($A44),DAY($A44)),"") -> 46203 | BV44: =IF($E44<>"",DATE(YEAR($E44),MONTH($E44),DAY($E44)),"") -> 46205 | BW44: =IF($E44<>"",TEXT($E44,"HH"),"") -> 14 | BZ44: =IF(B44<>"",VALUE(LEFT(B44)),"") -> 3 | CA44: {=IF($A44<>"",INDEX(LISTA!$M$2:$N$27,MATCH($BC44,LISTA!$N$2:$N$27,0),1),"")} -> 1 | CB44: =IF($A44<>"",MONTH(BU44),"") -> 6 | CC44: =IF($BX44<>"",MONTH(BX44),"")
A45: 46203.481 | B45: 3 - PROGRAMADA | C45: MASIVO RESIDENCIAL | D45: NAYELI | E45: 46204.667 | F45: PROCEDE | G45: 104986822 | H45: 88776097 | I45: ANTHONELLA | J45: 982340413 | K45: DNI | L45: 29676009 | M45: YESENIA TERESA CASTRO NINACONDOR | N45: 27999 | O45: AREQUIPA | P45: 0406 | T45: Arequipa | AQ45: HUGO | AR45: BACILISA | AS45: dediscueva@gmail.com | AU45: 982340413 | AV45: 982340413 | AW45: Asoc- villa confraternidad zona A MZ- j. Lte 4 alto selva alegre AQP | AX45: 2 | AY45: ND | AZ45: -16.358099664125213 -71.5245148240071 | BA45: Cancha caira | BB45: AQSA044-F | BC45: AREQUIPA | BD45: =IF(COUNTA(Q45:AP45)>0,INDEX(Q45:AP45,,max(IF(Q45:AP45<>"",COLUMN(Q45:AP45)))-16),"") -> Arequipa | BE45: FTTH | BF45: SI | BG45: ALTA NUEVA | BL45: 2PLAY + TELF | BM45: Campaña Regular | BN45: 94 | BO45: 400MBPS | BP45: NO | BQ45: NO | BR45: Ninguno | BS45: 1 | BU45: =IF($A45<>"", DATE(YEAR($A45),MONTH($A45),DAY($A45)),"") -> 46203 | BV45: =IF($E45<>"",DATE(YEAR($E45),MONTH($E45),DAY($E45)),"") -> 46204 | BW45: =IF($E45<>"",TEXT($E45,"HH"),"") -> 16 | BZ45: =IF(B45<>"",VALUE(LEFT(B45)),"") -> 3 | CA45: {=IF($A45<>"",INDEX(LISTA!$M$2:$N$27,MATCH($BC45,LISTA!$N$2:$N$27,0),1),"")} -> 7 | CB45: =IF($A45<>"",MONTH(BU45),"") -> 6 | CC45: =IF($BX45<>"",MONTH(BX45),"")
A46: 46203.545 | B46: 3 - PROGRAMADA | C46: MASIVO RESIDENCIAL | D46: NAYELI | E46: 46205.375 | F46: TIENE SEC CREADA DE AYER 29/06 POR TIENDA VIRTUAL | G46: 104965766 | H46: 88724375 | I46: ANTHONELLA | J46: 961883833 | K46: DNI | L46: 72679082 | M46: DANIEL OCTAVIO LUDEÑA ROJAS | N46: 33323 | O46: PIURA | P46: 200000 | AK46: Piura | AQ46: ABEL | AR46: MARI | AS46: dolr2691@gmail.com | AU46: 961883833 | AV46: 961883833 | AW46: urb. FELIPE COSSIO DEL POMAR mz z3 lt 10 | AX46: 2 | AY46: nd | AZ46: -5.183216211245893 -80.59044531819954 | BA46: referencia altura ferretería Jeova mi pastor espaldas | BB46: -5.183216211245893 -80.59044531819954 | BC46: PIURA | BD46: =IF(COUNTA(Q46:AP46)>0,INDEX(Q46:AP46,,max(IF(Q46:AP46<>"",COLUMN(Q46:AP46)))-16),"") -> Piura | BE46: FTTH | BF46: NO | BG46: ALTA NUEVA | BL46: 2PLAY + TELF | BM46: Campaña Regular | BN46: 94 | BO46: 400MBPS | BP46: NO | BQ46: SI | BR46: Ninguno | BS46: Ninguno | BU46: =IF($A46<>"", DATE(YEAR($A46),MONTH($A46),DAY($A46)),"") -> 46203 | BV46: =IF($E46<>"",DATE(YEAR($E46),MONTH($E46),DAY($E46)),"") -> 46205 | BW46: =IF($E46<>"",TEXT($E46,"HH"),"") -> 09 | BZ46: =IF(B46<>"",VALUE(LEFT(B46)),"") -> 3 | CA46: {=IF($A46<>"",INDEX(LISTA!$M$2:$N$27,MATCH($BC46,LISTA!$N$2:$N$27,0),1),"")} -> 21 | CB46: =IF($A46<>"",MONTH(BU46),"") -> 6 | CC46: =IF($BX46<>"",MONTH(BX46),"")
A47: 46203.554 | B47: 3 - PROGRAMADA | C47: MASIVO RESIDENCIAL | D47: NAYELI | E47: 46205.375 | F47: PROCEDE EN HFC | G47: 104984180 | H47: 88773507 | I47: OJT | J47: 912327595 | K47: DNI | L47: 42138364 | M47: MIRIAM GARDENIA CHAVEZ ZAVALETA | N47: 24524 | O47: CAJAMARCA | P47: 06 | AF47: Comas | AQ47: TERMOPILO | AR47: AURELIA | AS47: chacezzavaletamiriangardenia@gmail.com | AU47: 912327595 | AV47: 912327595 | AW47: av lima 358 | AX47: 1 | AY47: 1 | AZ47: -11.9043606,-77.04013908 | BA47: parque Manhatan | BB47: LMCO047 | BC47: LIMA METROPOLITANA | BD47: =IF(COUNTA(Q47:AP47)>0,INDEX(Q47:AP47,,max(IF(Q47:AP47<>"",COLUMN(Q47:AP47)))-16),"") -> Comas | BE47: HFC | BF47: NO | BG47: ALTA NUEVA | BL47: 2PLAY + TELF | BM47: Campaña Regular | BN47: 94 | BO47: 400MBPS | BP47: NO | BQ47: SI | BR47: Ninguno | BS47: Ninguno | BU47: =IF($A47<>"", DATE(YEAR($A47),MONTH($A47),DAY($A47)),"") -> 46203 | BV47: =IF($E47<>"",DATE(YEAR($E47),MONTH($E47),DAY($E47)),"") -> 46205 | BW47: =IF($E47<>"",TEXT($E47,"HH"),"") -> 09 | BZ47: =IF(B47<>"",VALUE(LEFT(B47)),"") -> 3 | CA47: {=IF($A47<>"",INDEX(LISTA!$M$2:$N$27,MATCH($BC47,LISTA!$N$2:$N$27,0),1),"")} -> 1 | CB47: =IF($A47<>"",MONTH(BU47),"") -> 6 | CC47: =IF($BX47<>"",MONTH(BX47),"")
A48: 46203.565 | B48: 3 - PROGRAMADA | C48: MASIVO RESIDENCIAL | D48: NAYELI | E48: 46204.583 | F48: EN EJECUCION | G48: 104963507 | H48: 88721861 | I48: ANTHONELLA | J48: 904383310 | K48: DNI | L48: 78717821 | M48: ADRIANA MARIA NATALIA RIVAS GRIMALDO | N48: 38561 | O48: LIMA | P48: 150135 | AF48: San Martín de Porres | AQ48: MIGUEL | AR48: NATALIA | AS48: eithanmibebe63@gmail.com | AU48: 904383310 | AV48: 904383310 | AW48: Jirón Alberto Bartón 310 | AX48: 5 | AY48: ND | AZ48: -12.023854272942264 -77.07918538474682 | BA48: JR. THOMAS COCHRANE | BB48: -12.023854272942264 -77.07918538474682 | BC48: LIMA METROPOLITANA | BD48: =IF(COUNTA(Q48:AP48)>0,INDEX(Q48:AP48,,max(IF(Q48:AP48<>"",COLUMN(Q48:AP48)))-16),"") -> San Martín de Porres | BE48: FTTH | BF48: NO | BG48: ALTA NUEVA | BL48: 2PLAY + TELF | BM48: Campaña Regular | BN48: 94 | BO48: 400MBPS | BP48: NO | BQ48: SI | BR48: Ninguno | BS48: Ninguno | BU48: =IF($A48<>"", DATE(YEAR($A48),MONTH($A48),DAY($A48)),"") -> 46203 | BV48: =IF($E48<>"",DATE(YEAR($E48),MONTH($E48),DAY($E48)),"") -> 46204 | BW48: =IF($E48<>"",TEXT($E48,"HH"),"") -> 14 | BZ48: =IF(B48<>"",VALUE(LEFT(B48)),"") -> 3 | CA48: {=IF($A48<>"",INDEX(LISTA!$M$2:$N$27,MATCH($BC48,LISTA!$N$2:$N$27,0),1),"")} -> 1 | CB48: =IF($A48<>"",MONTH(BU48),"") -> 6 | CC48: =IF($BX48<>"",MONTH(BX48),"")
A49: 46203.575 | B49: 3 - PROGRAMADA | C49: MASIVO RESIDENCIAL | D49: NAYELI | E49: 46204.458 | F49: EN EJECUCION | G49: 104964242 | H49: 88722956 | I49: JESSICA | J49: 947587852 | K49: DNI | L49: 06430190 | M49: CESAR AUGUSTO ALARCON FARFAN | N49: 24562 | O49: JUNIN | P49: 110101 | AF49: Santiago de Surco | AQ49: GILBERTO | AR49: JULIA | AS49: calarconfarfan67@gmail.com | AU49: 957603615 | AV49: 957603615 | AW49: CALLE TACNA 146 URB. MANSERICHE | AX49: 2 | AY49: NA | AZ49: -12.143664623, -77.004367208 | BA49: FRANCISCO BOLOGNESI | BB49: LMSC347-F | BC49: LIMA METROPOLITANA | BD49: =IF(COUNTA(Q49:AP49)>0,INDEX(Q49:AP49,,max(IF(Q49:AP49<>"",COLUMN(Q49:AP49)))-16),"") -> Santiago de Surco | BE49: FTTH | BF49: SI | BG49: ALTA NUEVA | BL49: 1 PLAY + L1MAX | BM49: Campaña Regular PRO | BN49: 110 | BO49: 500MBPS | BP49: SI | BQ49: NO | BR49: Ninguno | BS49: 1 | BU49: =IF($A49<>"", DATE(YEAR($A49),MONTH($A49),DAY($A49)),"") -> 46203 | BV49: =IF($E49<>"",DATE(YEAR($E49),MONTH($E49),DAY($E49)),"") -> 46204 | BW49: =IF($E49<>"",TEXT($E49,"HH"),"") -> 11 | BZ49: =IF(B49<>"",VALUE(LEFT(B49)),"") -> 3 | CA49: {=IF($A49<>"",INDEX(LISTA!$M$2:$N$27,MATCH($BC49,LISTA!$N$2:$N$27,0),1),"")} -> 1 | CB49: =IF($A49<>"",MONTH(BU49),"") -> 6 | CC49: =IF($BX49<>"",MONTH(BX49),"")
A50: 46203.603 | B50: 3 - PROGRAMADA | C50: MASIVO RESIDENCIAL | D50: NAYELI | E50: 46204.458 | F50: EN EJECUCION | G50: 104965377 | H50: 88723630 | I50: ANGHELL | J50: 988223633 | K50: DNI | L50: 03658870 | M50: MARLON EDUARDO BARCENAS ALVAREZ | N50: 25591 | O50: PIURA | P50: 190601 | AK50: Sullana | AQ50: SEGUNDO | AR50: NORMA | AS50: M.BARCENAS7@GMAIL.COM | AU50: 988223633 | AV50: 988223633 | AW50: AAHH JOSE CARLOS MARIATEGUI CALLE CESAR SANDINO MZ H LT 39 | AX50: 1 | AY50: NA | AZ50: 4.914671, -80.691132 | BA50: CL CESAR SANDINO | BB50: PIUS057-F | BC50: PIURA | BD50: =IF(COUNTA(Q50:AP50)>0,INDEX(Q50:AP50,,max(IF(Q50:AP50<>"",COLUMN(Q50:AP50)))-16),"") -> Sullana | BE50: FTTH | BF50: SI | BG50: ALTA NUEVA | BL50: 1 PLAY | BM50: Campaña Promo Mediana | BN50: 89 | BO50: 400MBPS | BP50: NO | BQ50: NO | BR50: Ninguno | BS50: 1 | BU50: =IF($A50<>"", DATE(YEAR($A50),MONTH($A50),DAY($A50)),"") -> 46203 | BV50: =IF($E50<>"",DATE(YEAR($E50),MONTH($E50),DAY($E50)),"") -> 46204 | BW50: =IF($E50<>"",TEXT($E50,"HH"),"") -> 11 | BZ50: =IF(B50<>"",VALUE(LEFT(B50)),"") -> 3 | CA50: {=IF($A50<>"",INDEX(LISTA!$M$2:$N$27,MATCH($BC50,LISTA!$N$2:$N$27,0),1),"")} -> 21 | CB50: =IF($A50<>"",MONTH(BU50),"") -> 6 | CC50: =IF($BX50<>"",MONTH(BX50),"")
A51: 46203.746 | B51: 3 - PROGRAMADA | C51: MASIVO RESIDENCIAL | D51: NAYELI | E51: 46206.667 | F51: PROCEDE | G51: 104974476 | H51: 88740283 | I51: GABRIEL | J51: 949588974 | K51: DNI | L51: 72118081 | M51: ESTHER JHAJANDRA, SANTIAGO HUANCA | N51: 36128 | O51: HUANUCO | P51: 100101 | Z51: Huánuco | AQ51: FAUSTINO | AR51: NILDA | AS51: jhajandrasantiagohuanca@gmail.com | AU51: 949588974 | AV51: 949588974 | AW51: AV UNIVERSITARIA 2076 | AX51: 2 | AY51: S/I | AZ51: -9.961946198761577, -76.24575559893029 | BA51: Referencia el colegio Juan Velasco Alvarado | BB51: HUPM010-S | BC51: HUANUCO | BD51: =IF(COUNTA(Q51:AP51)>0,INDEX(Q51:AP51,,max(IF(Q51:AP51<>"",COLUMN(Q51:AP51)))-16),"") -> Huánuco | BE51: FTTH | BF51: NO | BG51: ALTA NUEVA | BL51: 2PLAY + TELF | BM51: Campaña Regular | BN51: 94 | BO51: 400MBPS | BQ51: SI | BR51: Ninguno | BS51: Ninguno | BU51: =IF($A51<>"", DATE(YEAR($A51),MONTH($A51),DAY($A51)),"") -> 46203 | BV51: =IF($E51<>"",DATE(YEAR($E51),MONTH($E51),DAY($E51)),"") -> 46206 | BW51: =IF($E51<>"",TEXT($E51,"HH"),"") -> 16 | BZ51: =IF(B51<>"",VALUE(LEFT(B51)),"") -> 3 | CA51: {=IF($A51<>"",INDEX(LISTA!$M$2:$N$27,MATCH($BC51,LISTA!$N$2:$N$27,0),1),"")} -> 12 | CB51: =IF($A51<>"",MONTH(BU51),"") -> 6 | CC51: =IF($BX51<>"",MONTH(BX51),"")
A52: 46203.773 | B52: 3 - PROGRAMADA | C52: MASIVO RESIDENCIAL | D52: NAYELI | E52: 46205.458 | F52: PNDT CREAR SOT | G52: 104975485 | I52: JULIANA | J52: 989125595 | K52: DNI | L52: 91028262 | M52: MISUKY AZAÑA ROJAS | N52: 38471 | O52: LIMA METROPOLITANA | P52: 140142 | AF52: San Martín de Porres | AQ52: ADRIAN | AR52: HONORATA | AS52: MISUKYAZANAROJAS655@GMAIL.COM | AU52: 989125595 | AV52: 989125595 | AW52: JIRON ELIAS AGUIRRE 213, URB. ALMIRANTE MIGUEL GRAU - SPM | AX52: 2 | AY52: 1 | AZ52: -11.997201026, -77.095018313 | BA52: A LA VUELTA DE LA CURVA. | BB52: LMMP149-S | BC52: LIMA METROPOLITANA | BD52: =IF(COUNTA(Q52:AP52)>0,INDEX(Q52:AP52,,max(IF(Q52:AP52<>"",COLUMN(Q52:AP52)))-16),"") -> San Martín de Porres | BE52: FTTH | BF52: SI | BG52: ALTA NUEVA | BL52: 2PLAY + TELF | BM52: Campaña Regular | BN52: 94 | BO52: 400MBPS | BP52: NO | BQ52: SI | BR52: Ninguno | BS52: 1 | BU52: =IF($A52<>"", DATE(YEAR($A52),MONTH($A52),DAY($A52)),"") -> 46203 | BV52: =IF($E52<>"",DATE(YEAR($E52),MONTH($E52),DAY($E52)),"") -> 46205 | BW52: =IF($E52<>"",TEXT($E52,"HH"),"") -> 11 | BZ52: =IF(B52<>"",VALUE(LEFT(B52)),"") -> 3 | CA52: {=IF($A52<>"",INDEX(LISTA!$M$2:$N$27,MATCH($BC52,LISTA!$N$2:$N$27,0),1),"")} -> 1 | CB52: =IF($A52<>"",MONTH(BU52),"") -> 6 | CC52: =IF($BX52<>"",MONTH(BX52),"")
A53: 46184.495 | B53: 3 - PROG_CANCELADA | C53: MASIVO RESIDENCIAL | D53: PAOLA | E53: 46186.458 | F53: LYBTEL/ REGULARIZACION / cl indica por chat que ya no desea | G53: 104471266 | H53: 88291548 | I53: PAOLA | J53: 928502261 | K53: DNI | L53: 74146223 | M53: FABRIZIOALEJANDRO MAURICIO CASANA | N53: 35962 | O53: LIMA | P53: 140101 | AF53: San Martín de Porres | AQ53: ALEJANDRO | AR53: JANET | AS53: FABRIZZIOMC20@GMAIL.COM | AU53: 928502261 | AV53: 928502261 | AW53: JR CUSCO 3679 SAN MARTIN DE PORRES | AX53: 4 | AY53: 1 | AZ53: -12.034971, -77.089403 | BA53: CALLE PUNO | BB53: LMMP036 | BC53: LIMA METROPOLITANA | BD53: =IF(COUNTA(Q53:AP53)>0,INDEX(Q53:AP53,,max(IF(Q53:AP53<>"",COLUMN(Q53:AP53)))-16),"") -> San Martín de Porres | BE53: HFC | BF53: SI | BG53: ALTA NUEVA | BL53: 1 PLAY | BM53: Campaña Regular | BN53: 89 | BO53: 400MBPS | BP53: NO | BQ53: NO | BR53: Ninguno | BS53: Ninguno | BU53: =IF($A53<>"", DATE(YEAR($A53),MONTH($A53),DAY($A53)),"") -> 46184 | BV53: =IF($E53<>"",DATE(YEAR($E53),MONTH($E53),DAY($E53)),"") -> 46186 | BW53: =IF($E53<>"",TEXT($E53,"HH"),"") -> 11 | BZ53: =IF(B53<>"",VALUE(LEFT(B53)),"") -> 3 | CA53: {=IF($A53<>"",INDEX(LISTA!$M$2:$N$27,MATCH($BC53,LISTA!$N$2:$N$27,0),1),"")} -> 1 | CB53: =IF($A53<>"",MONTH(BU53),"") -> 6 | CC53: =IF($BX53<>"",MONTH(BX53),"")
A54: 46185.628 | B54: 3 - PROG_CANCELADA | C54: MASIVO RESIDENCIAL | D54: PAOLA | E54: 46187.458 | F54: CLIENTE DE MUDANZA/VIAJE, SE LE TRATA DE CONTACTA | G54: 104496502 | H54: 88308463 | I54: JULIANA | J54: 913970912 | K54: DNI | L54: 71471954 | M54: MAYCOL JEYSON SOUZA MURAYARI | N54: 38660 | O54: LORETO | P54: 160101 | AF54: San Martín de Porres | AQ54: BETTMAN | AR54: MAGNOLIA | AS54: maycosouzamirayari@gmail.com | AU54: 913970912 | AV54: 913970912 | AW54: URB. LOS LIRIOS MZ M LOTE 10, SAN MARTIN DE PORRES. | AX54: 4 | AY54: 1 | AZ54: -12.000956, -77.096207 | BA54: ULT. PAREDERO DEL METROPOLITANO | BB54: LMMP152-S | BC54: LIMA METROPOLITANA | BD54: =IF(COUNTA(Q54:AP54)>0,INDEX(Q54:AP54,,max(IF(Q54:AP54<>"",COLUMN(Q54:AP54)))-16),"") -> San Martín de Porres | BE54: FTTH | BF54: SI | BG54: ALTA NUEVA | BL54: 1 PLAY | BM54: Campaña Regular | BN54: 89 | BO54: 400MBPS | BP54: NO | BQ54: NO | BR54: Ninguno | BS54: 1 | BU54: =IF($A54<>"", DATE(YEAR($A54),MONTH($A54),DAY($A54)),"") -> 46185 | BV54: =IF($E54<>"",DATE(YEAR($E54),MONTH($E54),DAY($E54)),"") -> 46187 | BW54: =IF($E54<>"",TEXT($E54,"HH"),"") -> 11 | BZ54: =IF(B54<>"",VALUE(LEFT(B54)),"") -> 3 | CA54: {=IF($A54<>"",INDEX(LISTA!$M$2:$N$27,MATCH($BC54,LISTA!$N$2:$N$27,0),1),"")} -> 1 | CB54: =IF($A54<>"",MONTH(BU54),"") -> 6 | CC54: =IF($BX54<>"",MONTH(BX54),"")
A55: 46185.751 | B55: 3 - PROG_CANCELADA | C55: MASIVO RESIDENCIAL | D55: PAOLA | E55: 46189.083 | F55: CL INDICA QUE NUNCA PIDIO NADA, Y EL YA TIENE CLARO / NO CONTESTA | G55: 104514769 | H55: 88313687 | I55: ANTHONELLA | J55: 943621382 | K55: DNI | L55: 60818341 | M55: MILAGROS ANGELY PISCOCHE RUIZ | N55: 39000 | O55: ANCASH | P55: 021801 | R55: Santa | AQ55: WILMER ESTEBAN | AR55: JOVITA MARILUZ | AS55: WEPAMA@HOTMAIL.COM | AU55: 943621382 | AV55: 943621382 | AW55: URBANISACION.BRUCES MZ C LT 44 NUEVO CHIMBOTE | AX55: 2 | AY55: 1 | AZ55: -9.134094, -78.520609 | BA55: AV SAGRADA FAMILIA | BB55: CBNV020-S | BC55: ANCASH | BD55: =IF(COUNTA(Q55:AP55)>0,INDEX(Q55:AP55,,max(IF(Q55:AP55<>"",COLUMN(Q55:AP55)))-16),"") -> Santa | BE55: FTTH | BF55: NO | BG55: ALTA NUEVA | BL55: 2 PLAY + TV ESTANDAR | BM55: Campaña Regular | BN55: 170 | BO55: 400MBPS | BP55: NO | BQ55: NO | BR55: 1 | BS55: Ninguno | BU55: =IF($A55<>"", DATE(YEAR($A55),MONTH($A55),DAY($A55)),"") -> 46185 | BV55: =IF($E55<>"",DATE(YEAR($E55),MONTH($E55),DAY($E55)),"") -> 46189 | BW55: =IF($E55<>"",TEXT($E55,"HH"),"") -> 02 | BZ55: =IF(B55<>"",VALUE(LEFT(B55)),"") -> 3 | CA55: {=IF($A55<>"",INDEX(LISTA!$M$2:$N$27,MATCH($BC55,LISTA!$N$2:$N$27,0),1),"")} -> 5 | CB55: =IF($A55<>"",MONTH(BU55),"") -> 6 | CC55: =IF($BX55<>"",MONTH(BX55),"")
A56: 46186.466 | B56: 3 - PROG_CANCELADA | C56: MASIVO RESIDENCIAL | D56: NAYELI | E56: 46201.667 | F56: CLIENTE NO DESEA SERVICIO | G56: 104744258 | H56: 88521522 | I56: PAOLA | J56: 917530843 | K56: DNI | L56: 75428864 | M56: ANGEL WILFREDO PONCE HUAMANI | N56: 37813 | O56: LIMA | P56: 140135 | AF56: Ate | AQ56: WILFREDO | AR56: NORMA | AS56: Ficholuis20@gmail.com | AU56: 917530843 | AV56: 917530843 | AW56: Av. Jose Carlos Mariategui : 515 | AX56: 2 | AY56: NA | AZ56: -12.083683752088596, -76.98236004273923 | BA56: LA MARGINAL | BB56: LMAT009-S | BC56: LIMA METROPOLITANA | BD56: =IF(COUNTA(Q56:AP56)>0,INDEX(Q56:AP56,,max(IF(Q56:AP56<>"",COLUMN(Q56:AP56)))-16),"") -> Ate | BE56: FTTH | BF56: NO | BG56: ALTA NUEVA | BL56: 1 PLAY | BM56: Campaña Promo Mediana | BN56: 89 | BO56: 400MBPS | BP56: NO | BQ56: NO | BR56: Ninguno | BS56: 1 | BU56: =IF($A56<>"", DATE(YEAR($A56),MONTH($A56),DAY($A56)),"") -> 46186 | BV56: =IF($E56<>"",DATE(YEAR($E56),MONTH($E56),DAY($E56)),"") -> 46201 | BW56: =IF($E56<>"",TEXT($E56,"HH"),"") -> 16 | BZ56: =IF(B56<>"",VALUE(LEFT(B56)),"") -> 3 | CA56: {=IF($A56<>"",INDEX(LISTA!$M$2:$N$27,MATCH($BC56,LISTA!$N$2:$N$27,0),1),"")} -> 1 | CB56: =IF($A56<>"",MONTH(BU56),"") -> 6 | CC56: =IF($BX56<>"",MONTH(BX56),"")
A57: 46195.708 | B57: 3 - PROG_CANCELADA | C57: MASIVO RESIDENCIAL | D57: NAYELI | E57: 46201.667 | F57: Rechazado Por Falta De Contacto - Mesa | G57: 104756361 | H57: 88528089 | I57: BRITNEY | J57: 964087211 | K57: DNI | L57: 76145719 | M57: PIERO ALESSANDRO SUSANIBAR RODRIGUEZ | N57: 37717 | O57: LIMA | P57: 150125 | AF57: Carabayllo | AQ57: Andrés Susanibar Rodríguez | AR57: Janet Rodríguez Atalaya | AS57: salvamax04@gmail.com | AU57: 964 087 211 | AV57: 901468885 | AW57: av mariano condorcanqui 1327 carabayllo lima | AX57: 3 | AY57: 1 | AZ57: -11.882002232231077, -77.03316442334543 | BA57: Calle N | BB57: LMBY028-S | BC57: LIMA METROPOLITANA | BD57: =IF(COUNTA(Q57:AP57)>0,INDEX(Q57:AP57,,max(IF(Q57:AP57<>"",COLUMN(Q57:AP57)))-16),"") -> Carabayllo | BE57: FTTH | BF57: NO | BG57: ALTA NUEVA | BL57: 1 PLAY + L1MAX | BM57: Campaña Regular | BN57: 110 | BO57: 500MBPS | BP57: SI | BQ57: NO | BR57: Ninguno | BS57: 1 | BU57: =IF($A57<>"", DATE(YEAR($A57),MONTH($A57),DAY($A57)),"") -> 46195 | BV57: =IF($E57<>"",DATE(YEAR($E57),MONTH($E57),DAY($E57)),"") -> 46201 | BW57: =IF($E57<>"",TEXT($E57,"HH"),"") -> 16 | BZ57: =IF(B57<>"",VALUE(LEFT(B57)),"") -> 3 | CA57: {=IF($A57<>"",INDEX(LISTA!$M$2:$N$27,MATCH($BC57,LISTA!$N$2:$N$27,0),1),"")} -> 1 | CB57: =IF($A57<>"",MONTH(BU57),"") -> 6 | CC57: =IF($BX57<>"",MONTH(BX57),"")
A58: 46196.443 | B58: 3 - PROG_CANCELADA | C58: MASIVO RESIDENCIAL | D58: NAYELI | E58: 46201.458 | F58: cl no responde la visita tecnica. | G58: 104770921 | H58: 88560198 | I58: JUAN DIEGO | J58: 946511766 | K58: DNI | L58: 70832523 | M58: DANNIA NAYSHA CHAVEZ QUISPE | N58: 34628 | O58: LIMA METROPOLITANA | P58: 150137 | AF58: Ate | AQ58: Misael | AR58: Reyna | AS58: danniachq21@gmail.com | AU58: 946511766 | AV58: 946511766 | AW58: urb. los amigos de la paz mz u lt 2, ate vitarte | AX58: 4 | AY58: 1 | AZ58: -12.038334259535137, -76.9056703519862 | BA58: iglesia las americas vitarte c | BB58: LMAT161-F | BC58: LIMA METROPOLITANA | BD58: =IF(COUNTA(Q58:AP58)>0,INDEX(Q58:AP58,,max(IF(Q58:AP58<>"",COLUMN(Q58:AP58)))-16),"") -> Ate | BE58: FTTH | BF58: NO | BG58: ALTA NUEVA | BL58: 1 PLAY | BM58: Campaña Regular | BN58: 110 | BO58: 500MBPS | BP58: NO | BQ58: NO | BR58: 4 | BS58: 1 | BU58: =IF($A58<>"", DATE(YEAR($A58),MONTH($A58),DAY($A58)),"") -> 46196 | BV58: =IF($E58<>"",DATE(YEAR($E58),MONTH($E58),DAY($E58)),"") -> 46201 | BW58: =IF($E58<>"",TEXT($E58,"HH"),"") -> 11 | BZ58: =IF(B58<>"",VALUE(LEFT(B58)),"") -> 3 | CA58: {=IF($A58<>"",INDEX(LISTA!$M$2:$N$27,MATCH($BC58,LISTA!$N$2:$N$27,0),1),"")} -> 1 | CB58: =IF($A58<>"",MONTH(BU58),"") -> 6 | CC58: =IF($BX58<>"",MONTH(BX58),"")
A59: 46197.46 | B59: 3 - PROG_CANCELADA | C59: MASIVO RESIDENCIAL | D59: NAYELI | E59: 46198.667 | F59: PROCEDE/ CL DESEA INSTALACION PARA LA PROXIMA SEMANA/ RECLAMANDO VENTA | G59: 104806111 | H59: 88589753 | I59: ANTHONELLA | J59: 997252193 | K59: DNI | L59: 74540671 | M59: ELIU CALEB BERNA BASILIO | N59: 38309 | O59: LIMA | P59: 1501 | AF59: San Martín de Porres | AQ59: juan | AR59: brenda | AS59: Karla31415911@gmail.com | AU59: 997252193 | AV59: 997252193 | AW59: Jr. Eloy Reategui 624 san martin de porres | AX59: 1 | AY59: nd | AZ59: -12.013260717061199 -77.07302889212735 | BA59: parque san amadeo garagay | BB59: LMMP068-S | BC59: LIMA METROPOLITANA | BD59: =IF(COUNTA(Q59:AP59)>0,INDEX(Q59:AP59,,max(IF(Q59:AP59<>"",COLUMN(Q59:AP59)))-16),"") -> San Martín de Porres | BE59: FTTH | BF59: NO | BG59: ALTA NUEVA | BL59: 2 PLAY + TV ESTANDAR | BM59: Campaña Regular | BN59: 170 | BO59: 400MBPS | BP59: SI | BQ59: NO | BR59: 2 | BS59: 1 | BU59: =IF($A59<>"", DATE(YEAR($A59),MONTH($A59),DAY($A59)),"") -> 46197 | BV59: =IF($E59<>"",DATE(YEAR($E59),MONTH($E59),DAY($E59)),"") -> 46198 | BW59: =IF($E59<>"",TEXT($E59,"HH"),"") -> 16 | BZ59: =IF(B59<>"",VALUE(LEFT(B59)),"") -> 3 | CA59: {=IF($A59<>"",INDEX(LISTA!$M$2:$N$27,MATCH($BC59,LISTA!$N$2:$N$27,0),1),"")} -> 1 | CB59: =IF($A59<>"",MONTH(BU59),"") -> 6 | CC59: =IF($BX59<>"",MONTH(BX59),"")
A60: 46198.808 | B60: 3 - PROG_CANCELADA | C60: MASIVO RESIDENCIAL | D60: PAOLA | E60: 46200.458 | F60: Rechazado Por Falta De Contacto - Mesa | G60: 104855914 | H60: 88648516 | I60: BRITNEY | J60: 923308318 | K60: RUC | L60: 10748930537 | M60: JORDI PAZOS VELASQUEZ | N60: 35780 | O60: LIMA | P60: 150143 | AF60: Villa María del Triunfo | AQ60: CARLOS MANUEL | AR60: JULIA DEL PILAR | AS60: mirandamirandamia91@gmail.com | AU60: 923308318 | AV60: 937 304 376 | AW60: Jr Carmen 807 villa maria el triunfo | AX60: 2 | AY60: 1 | AZ60: -12.160403, -76.945734 | BA60: Jr Carmen | BB60: LMVM013-S | BC60: LIMA METROPOLITANA | BD60: =IF(COUNTA(Q60:AP60)>0,INDEX(Q60:AP60,,max(IF(Q60:AP60<>"",COLUMN(Q60:AP60)))-16),"") -> Villa María del Triunfo | BE60: FTTH | BF60: NO | BG60: ALTA NUEVA | BL60: 1 PLAY | BM60: Campaña Promo Mediana | BN60: 89 | BO60: 400MBPS | BP60: NO | BQ60: NO | BR60: Ninguno | BS60: 1 | BU60: =IF($A60<>"", DATE(YEAR($A60),MONTH($A60),DAY($A60)),"") -> 46198 | BV60: =IF($E60<>"",DATE(YEAR($E60),MONTH($E60),DAY($E60)),"") -> 46200 | BW60: =IF($E60<>"",TEXT($E60,"HH"),"") -> 11 | BZ60: =IF(B60<>"",VALUE(LEFT(B60)),"") -> 3 | CA60: {=IF($A60<>"",INDEX(LISTA!$M$2:$N$27,MATCH($BC60,LISTA!$N$2:$N$27,0),1),"")} -> 1 | CB60: =IF($A60<>"",MONTH(BU60),"") -> 6 | CC60: =IF($BX60<>"",MONTH(BX60),"")
A61: 46199.675 | B61: 3 - PROG_CANCELADA | C61: MASIVO RESIDENCIAL | D61: NAYELI | E61: 46202.5 | F61: Rechazado Por Falta De Contacto - Mesa | G61: 104874717 | H61: 88661898 | I61: JULIANA | J61: 919580373 | K61: DNI | L61: 48323268 | M61: CRISPIN VEGA MARRUJO | N61: 34098 | O61: HUANUCO | P61: 090110 | Z61: Huánuco | AQ61: TEODORO | AR61: CLEMENTINA | AS61: CRISPINVEGAMARRUJO75@GMAIL.COM | AU61: 919580373 | AV61: 933729487 / 976877119 | AW61: JIRON PANAMA MZ 3 LOTE 13 URB. SAN LUIS, AMARILIS HUANUCO. | AX61: 1 | AY61: 1 | AZ61: 9.946541, -76.239578 | BA61: AV.AV. PERU o CERCA AL COLEGIO RENE GUARDIAN | BB61: HNAM004-F | BC61: HUANUCO | BD61: =IF(COUNTA(Q61:AP61)>0,INDEX(Q61:AP61,,max(IF(Q61:AP61<>"",COLUMN(Q61:AP61)))-16),"") -> Huánuco | BE61: FTTH | BF61: NO | BG61: ALTA NUEVA | BL61: 1 PLAY | BM61: Campaña Regular | BN61: 69 | BO61: 200MBPS | BP61: NO | BQ61: NO | BR61: Ninguno | BS61: Ninguno | BU61: =IF($A61<>"", DATE(YEAR($A61),MONTH($A61),DAY($A61)),"") -> 46199 | BV61: =IF($E61<>"",DATE(YEAR($E61),MONTH($E61),DAY($E61)),"") -> 46202 | BW61: =IF($E61<>"",TEXT($E61,"HH"),"") -> 12 | BZ61: =IF(B61<>"",VALUE(LEFT(B61)),"") -> 3 | CA61: {=IF($A61<>"",INDEX(LISTA!$M$2:$N$27,MATCH($BC61,LISTA!$N$2:$N$27,0),1),"")} -> 12 | CB61: =IF($A61<>"",MONTH(BU61),"") -> 6 | CC61: =IF($BX61<>"",MONTH(BX61),"")
A62: 46200.384 | B62: 3 - PROG_CANCELADA | C62: MASIVO RESIDENCIAL | D62: NAYELI | E62: 46202.667 | F62: SE ENVIO RESCATE COMERCIAL 01/07 | G62: 104886907 | H62: 88670638 | I62: OJT | J62: 980808162 | K62: DNI | L62: 09989234 | M62: DINO IVAN GALLARDO ESTELA | N62: 22897 | O62: LIMA | P62: 150804 | AF62: Los Olivos | AQ62: SANTIAGO | AR62: CELINA | AS62: gallardoandres089@gmail.com | AU62: 930860834 | AV62: 948294957 | AW62: URBANIZACIÒN LOS OLIVOS DE PRO mz s2 lt 3 | AX62: 2 | AY62: 0 | AZ62: -11.947674165824195, -77.08054264511327 | BA62: av betancourt | BB62: LMLO099-S | BC62: LIMA METROPOLITANA | BD62: =IF(COUNTA(Q62:AP62)>0,INDEX(Q62:AP62,,max(IF(Q62:AP62<>"",COLUMN(Q62:AP62)))-16),"") -> Los Olivos | BE62: FTTH | BF62: SI | BG62: ALTA NUEVA | BL62: 1 PLAY | BM62: Campaña Promo Mediana | BN62: 89 | BO62: 400MBPS | BP62: NO | BQ62: NO | BR62: Ninguno | BS62: 1 | BU62: =IF($A62<>"", DATE(YEAR($A62),MONTH($A62),DAY($A62)),"") -> 46200 | BV62: =IF($E62<>"",DATE(YEAR($E62),MONTH($E62),DAY($E62)),"") -> 46202 | BW62: =IF($E62<>"",TEXT($E62,"HH"),"") -> 16 | BZ62: =IF(B62<>"",VALUE(LEFT(B62)),"") -> 3 | CA62: {=IF($A62<>"",INDEX(LISTA!$M$2:$N$27,MATCH($BC62,LISTA!$N$2:$N$27,0),1),"")} -> 1 | CB62: =IF($A62<>"",MONTH(BU62),"") -> 6 | CC62: =IF($BX62<>"",MONTH(BX62),"")
A63: 46191.475 | B63: 2 - TRANSACCIÓN N/A | C63: MASIVO RESIDENCIAL | D63: PAOLA | E63: 46193.083 | F63: ERROR EN EL CONTRATO - Transacción no autorizada - Motor : Control de irregularidades | G63: 104677835 | H63: 88465583 | I63: PAOLA | J63: 922088573 | K63: DNI | L63: 42880941 | M63: ESTHER JAIMES INGA | N63: 31043 | O63: HUANUCO | P63: 090101 | AF63: San Juan de Lurigancho | AQ63: BENANCIO | AR63: LIBERATA | AS63: aylaniosorioparedes@gmail.com | AU63: 922 088 573 | AV63: 969384309 | AW63: JR LOS QUINUALES 329 | AX63: 1 | AY63: NA | AZ63: -12 .022425,-77013923 | BA63: LOS QUINUALES | BB63: LMJL079-S | BC63: LIMA METROPOLITANA | BD63: =IF(COUNTA(Q63:AP63)>0,INDEX(Q63:AP63,,max(IF(Q63:AP63<>"",COLUMN(Q63:AP63)))-16),"") -> San Juan de Lurigancho | BE63: HFC | BF63: NO | BG63: ALTA NUEVA | BL63: 2 PLAY + TV ESTANDAR | BM63: Campaña Regular | BN63: 170 | BO63: 400MBPS | BP63: SI | BQ63: NO | BR63: 2 | BS63: 1 | BU63: =IF($A63<>"", DATE(YEAR($A63),MONTH($A63),DAY($A63)),"") -> 46191 | BV63: =IF($E63<>"",DATE(YEAR($E63),MONTH($E63),DAY($E63)),"") -> 46193 | BW63: =IF($E63<>"",TEXT($E63,"HH"),"") -> 02 | BZ63: =IF(B63<>"",VALUE(LEFT(B63)),"") -> 2 | CA63: {=IF($A63<>"",INDEX(LISTA!$M$2:$N$27,MATCH($BC63,LISTA!$N$2:$N$27,0),1),"")} -> 1 | CB63: =IF($A63<>"",MONTH(BU63),"") -> 6 | CC63: =IF($BX63<>"",MONTH(BX63),"")
A64: 46191.551 | B64: 2 - TRANSACCIÓN N/A | C64: MASIVO RESIDENCIAL | D64: PAOLA | E64: 46195.458 | F64: 32 | G64: 104671134 | H64: 88471837 | I64: JESSICA | J64: 918416553 | K64: CE | L64: 007198876 | M64: NATHALY JOSE MARQUEZ MARIN | N64: 35994 | O64: OTRO PAIS | P64: 09 | AF64: La Victoria | AQ64: LEONEL | AR64: MARVYS | AS64: Leonardmarcano511@gmail.com | AU64: 918416553 | AV64: 918416553 | AW64: URB. MATUTE MZ B LT 25 | AX64: 2 | AY64: NA | AZ64: -12.070171587854961, -77.02040258202793 | BA64: Parque Marcos Calderón | BB64: LMLV073-F | BC64: LIMA METROPOLITANA | BD64: =IF(COUNTA(Q64:AP64)>0,INDEX(Q64:AP64,,max(IF(Q64:AP64<>"",COLUMN(Q64:AP64)))-16),"") -> La Victoria | BE64: FTTH | BF64: NO | BG64: ALTA NUEVA | BL64: 1 PLAY | BM64: Campaña Promo Mediana | BN64: 89 | BO64: 400MBPS | BP64: NO | BQ64: NO | BR64: Ninguno | BS64: 1 | BU64: =IF($A64<>"", DATE(YEAR($A64),MONTH($A64),DAY($A64)),"") -> 46191 | BV64: =IF($E64<>"",DATE(YEAR($E64),MONTH($E64),DAY($E64)),"") -> 46195 | BW64: =IF($E64<>"",TEXT($E64,"HH"),"") -> 11 | BZ64: =IF(B64<>"",VALUE(LEFT(B64)),"") -> 2 | CA64: {=IF($A64<>"",INDEX(LISTA!$M$2:$N$27,MATCH($BC64,LISTA!$N$2:$N$27,0),1),"")} -> 1 | CB64: =IF($A64<>"",MONTH(BU64),"") -> 6 | CC64: =IF($BX64<>"",MONTH(BX64),"")
A65: 46191.7 | B65: 2 - TRANSACCIÓN N/A | C65: MASIVO RESIDENCIAL | D65: PAOLA | E65: 46193.458 | F65: Rechazado por transacción no autorizada | G65: 104655056 | H65: 88439634 | I65: OJT | J65: 936929624 | K65: DNI | L65: 40545693 | M65: ERIKA MAGALI LEON PINILLOS | N65: 29300 | O65: LIMA | P65: 140101 | AF65: San Martín de Porres | AQ65: griserio | AR65: shirley | AS65: ekalepini@gmail.com | AU65: 936929624 | AV65: 936929624 | AW65: CALLE TOBIAS MELLER 289 SAN MARTIN DE PORRES | AX65: 3 | AY65: 1 | AZ65: -12.000458, -77.088086 | BA65: calle juan pichert | BB65: LMMP224-F | BC65: LIMA METROPOLITANA | BD65: =IF(COUNTA(Q65:AP65)>0,INDEX(Q65:AP65,,max(IF(Q65:AP65<>"",COLUMN(Q65:AP65)))-16),"") -> San Martín de Porres | BE65: FTTH | BF65: NO | BG65: ALTA NUEVA | BL65: 1 PLAY | BM65: Campaña 1 sol | BN65: 89 | BO65: 400MBPS | BP65: NO | BQ65: NO | BR65: Ninguno | BS65: Ninguno | BU65: =IF($A65<>"", DATE(YEAR($A65),MONTH($A65),DAY($A65)),"") -> 46191 | BV65: =IF($E65<>"",DATE(YEAR($E65),MONTH($E65),DAY($E65)),"") -> 46193 | BW65: =IF($E65<>"",TEXT($E65,"HH"),"") -> 11 | BZ65: =IF(B65<>"",VALUE(LEFT(B65)),"") -> 2 | CA65: {=IF($A65<>"",INDEX(LISTA!$M$2:$N$27,MATCH($BC65,LISTA!$N$2:$N$27,0),1),"")} -> 1 | CB65: =IF($A65<>"",MONTH(BU65),"") -> 6 | CC65: =IF($BX65<>"",MONTH(BX65),"")
A66: 46191.82 | B66: 2 - TRANSACCIÓN N/A | C66: MASIVO RESIDENCIAL | F66: GRABADO - ADJUNTAR DNI ambas caras, Foto de cliente mostrando DNI y Recibo de Servicio de dirección de instalación DE AGUA o luz. | I66: OJT | J66: 922379687 | K66: RUC | L66: 10327336962 | M66: AGUIRRE BLANQUILLO MIGUEL ANGEL | N66: 26631 | O66: ANCASH | P66: 021301 | AF66: Cercado de Lima | AQ66: AUGUSTO | AR66: CARMEN | AS66: aguirremiguel1972@gmail.com | AU66: 922 379 687 | AV66: 922 379 687 | AW66: Urbanización palomino mz m lt32 | AX66: 3 | AY66: 1 | AZ66: -12.060967, -77.070769 | BA66: Avenida santa catalina de Siena | BB66: LMLM 228-F | BC66: LIMA METROPOLITANA | BD66: =IF(COUNTA(Q66:AP66)>0,INDEX(Q66:AP66,,max(IF(Q66:AP66<>"",COLUMN(Q66:AP66)))-16),"") -> Cercado de Lima | BE66: FTTH | BF66: NO | BG66: ALTA NUEVA | BL66: 2 PLAY + TV ESTANDAR | BM66: Campaña Promo Entrada | BN66: 170 | BO66: 400MBPS | BP66: SI | BQ66: NO | BR66: 2 | BS66: 1 | BU66: =IF($A66<>"", DATE(YEAR($A66),MONTH($A66),DAY($A66)),"") -> 46191 | BV66: =IF($E66<>"",DATE(YEAR($E66),MONTH($E66),DAY($E66)),"") | BW66: =IF($E66<>"",TEXT($E66,"HH"),"") | BZ66: =IF(B66<>"",VALUE(LEFT(B66)),"") -> 2 | CA66: {=IF($A66<>"",INDEX(LISTA!$M$2:$N$27,MATCH($BC66,LISTA!$N$2:$N$27,0),1),"")} -> 1 | CB66: =IF($A66<>"",MONTH(BU66),"") -> 6 | CC66: =IF($BX66<>"",MONTH(BX66),"")
A67: 46196.809 | B67: 2 - TRANSACCIÓN N/A | C67: MASIVO RESIDENCIAL | D67: NAYELI | E67: 46197.583 | F67: ADJUNTAR DNI ambas caras, Foto de cliente mostrando DNI y Recibo de Servicio de dirección de instalación DE AGUA o luz. | G67: 104797604 | H67: 88585134 | I67: JULIANA | J67: 950490504 | K67: DNI | L67: 10180654 | M67: SIGIFREDO ALBERTO TAPIA LUQUE | N67: 27814 | O67: LIMA METROPOLITANA | P67: 140133 | U67: Huanta | AQ67: SIGIFREDO | AR67: MERCEDES | AS67: bet6otapia@hotmail.com | AU67: 950490504 | AV67: 950490504 | AW67: Jr Razuhuillca 438 URB. CERCADO HUANTA HUANTA AYACUCHO. | AX67: 1 | AY67: 1 | AZ67: -12.938042415, -74.246330888 | BA67: A DOS CUADRAS Y MEDIA DEL PARQUE DE LA MUNICIPALIDAD | BB67: AYHU005-F | BC67: AYACUCHO | BD67: =IF(COUNTA(Q67:AP67)>0,INDEX(Q67:AP67,,max(IF(Q67:AP67<>"",COLUMN(Q67:AP67)))-16),"") -> Huanta | BE67: FTTH | BF67: NO | BG67: ALTA NUEVA | BL67: 1 PLAY | BM67: Campaña Promo Mediana | BN67: 89 | BO67: 400MBPS | BP67: NO | BQ67: NO | BR67: Ninguno | BS67: 1 | BU67: =IF($A67<>"", DATE(YEAR($A67),MONTH($A67),DAY($A67)),"") -> 46196 | BV67: =IF($E67<>"",DATE(YEAR($E67),MONTH($E67),DAY($E67)),"") -> 46197 | BW67: =IF($E67<>"",TEXT($E67,"HH"),"") -> 14 | BZ67: =IF(B67<>"",VALUE(LEFT(B67)),"") -> 2 | CA67: {=IF($A67<>"",INDEX(LISTA!$M$2:$N$27,MATCH($BC67,LISTA!$N$2:$N$27,0),1),"")} -> 8 | CB67: =IF($A67<>"",MONTH(BU67),"") -> 6 | CC67: =IF($BX67<>"",MONTH(BX67),"")
A68: 46197.765 | B68: 2 - TRANSACCIÓN N/A | C68: MASIVO RESIDENCIAL | D68: NAYELI | E68: 46199.375 | F68: ADJUNTAR DNI ambas caras, Foto de cliente mostrando DNI y Recibo de Servicio de dirección de instalación DE AGUA o luz. | G68: 104819915 | H68: 88609906 | I68: BRITNEY | J68: 949875878 | K68: DNI | L68: 42906830 | M68: EDWIN ABNER PAICO CRUZ | N68: 31113 | O68: TUMBES | P68: 240101 | AO68: Tumbes | AQ68: Marcelino | AR68: Teresa | AS68: edwinpaico8@gmail.com | AU68: 949 875 878 | AV68: 949 875 878 | AW68: CIUDADELA NOE MZ H LT 7 PISO TUMBES | AX68: 1 | AY68: 1 | AZ68: -3.573075, -80.420756 | BA68: Urb ciudadela noe | BB68: TBTB029-S | BC68: TUMBES | BD68: =IF(COUNTA(Q68:AP68)>0,INDEX(Q68:AP68,,max(IF(Q68:AP68<>"",COLUMN(Q68:AP68)))-16),"") -> Tumbes | BE68: FTTH | BF68: NO | BG68: ALTA NUEVA | BL68: 2 PLAY + TV ESTANDAR | BM68: Campaña Regular | BN68: 170 | BO68: 400MBPS | BP68: SI | BQ68: NO | BR68: 2 | BS68: 1 | BU68: =IF($A68<>"", DATE(YEAR($A68),MONTH($A68),DAY($A68)),"") -> 46197 | BV68: =IF($E68<>"",DATE(YEAR($E68),MONTH($E68),DAY($E68)),"") -> 46199 | BW68: =IF($E68<>"",TEXT($E68,"HH"),"") -> 09 | BZ68: =IF(B68<>"",VALUE(LEFT(B68)),"") -> 2 | CA68: {=IF($A68<>"",INDEX(LISTA!$M$2:$N$27,MATCH($BC68,LISTA!$N$2:$N$27,0),1),"")} -> 25 | CB68: =IF($A68<>"",MONTH(BU68),"") -> 6 | CC68: =IF($BX68<>"",MONTH(BX68),"")
A69: 46200.743 | B69: 2 - AUDIO OBSERVADO | C69: MASIVO RESIDENCIAL | D69: PAOLA | E69: 46203.375 | F69: direccion incompleta en sistema | G69: 104908032 | H69: 88679843 | I69: JESSICA | J69: 931807375 | K69: DNI | L69: 20083833 | M69: ROBERTH SALAS JORGE | N69: 27949 | O69: HUANCAVELICA | P69: 080311 | AB69: Huancayo | AQ69: HERMINIO | AR69: DELIA | AS69: sajo0707@hotmail.com | AU69: 931807375 | AV69: 931807375 | AW69: PASAJE JESÚS MARÍA 00 OSEA S/N | AX69: 2 | AY69: NA | AZ69: -12.05561432456769, -75.19688191632616 | BA69: OLAYA, PUENTE, RIACHUELO | BB69: JNHY023-F | BC69: JUNIN | BD69: =IF(COUNTA(Q69:AP69)>0,INDEX(Q69:AP69,,max(IF(Q69:AP69<>"",COLUMN(Q69:AP69)))-16),"") -> Huancayo | BE69: FTTH | BF69: SI | BG69: ALTA NUEVA | BL69: 1 PLAY + L1MAX | BM69: Campaña Regular PRO | BN69: 110 | BO69: 500MBPS | BP69: SI | BQ69: NO | BR69: Ninguno | BS69: 1 | BU69: =IF($A69<>"", DATE(YEAR($A69),MONTH($A69),DAY($A69)),"") -> 46200 | BV69: =IF($E69<>"",DATE(YEAR($E69),MONTH($E69),DAY($E69)),"") -> 46203 | BW69: =IF($E69<>"",TEXT($E69,"HH"),"") -> 09 | BZ69: =IF(B69<>"",VALUE(LEFT(B69)),"") -> 2 | CA69: {=IF($A69<>"",INDEX(LISTA!$M$2:$N$27,MATCH($BC69,LISTA!$N$2:$N$27,0),1),"")} -> 14 | CB69: =IF($A69<>"",MONTH(BU69),"") -> 6 | CC69: =IF($BX69<>"",MONTH(BX69),"")
A70: 46185.777 | B70: 1 - SIN ING-NO CALIFICA | C70: MASIVO RESIDENCIAL | F70: SE NECESITA EVIDENCIA DE BOLETA DE PAGO PARA CREAR SEC CORRECTA | G70: 104462641 | I70: JULIANA | J70: 984710884 | K70: DNI | L70: 42268305 | M70: BRUNO MIGUEL FLORES TITO | N70: 30726 | O70: LIMA | P70: 150101 | AF70: Independencia | AQ70: MIGUEL | AR70: DORIS | AS70: bflorest.pe@gmail.com | AU70: 984710884 | AV70: 984710884 | AW70: Av.Gerardo Unger 3601 Torre, independencia | AX70: 16 | AY70: 1606 | AZ70: -11.992682, -77.057553 | BA70: Espalda de Megaplaza | BB70: LMIN048-F | BC70: LIMA METROPOLITANA | BD70: =IF(COUNTA(Q70:AP70)>0,INDEX(Q70:AP70,,max(IF(Q70:AP70<>"",COLUMN(Q70:AP70)))-16),"") -> Independencia | BE70: FTTH | BF70: SI | BG70: ALTA NUEVA | BL70: 2 PLAY + TV PRO | BM70: Campaña Regular PRO | BN70: 225 | BO70: 800MBPS | BP70: SI | BQ70: NO | BR70: 1 | BS70: 2 | BU70: =IF($A70<>"", DATE(YEAR($A70),MONTH($A70),DAY($A70)),"") -> 46185 | BV70: =IF($E70<>"",DATE(YEAR($E70),MONTH($E70),DAY($E70)),"") | BW70: =IF($E70<>"",TEXT($E70,"HH"),"") | BZ70: =IF(B70<>"",VALUE(LEFT(B70)),"") -> 1 | CA70: {=IF($A70<>"",INDEX(LISTA!$M$2:$N$27,MATCH($BC70,LISTA!$N$2:$N$27,0),1),"")} -> 1 | CB70: =IF($A70<>"",MONTH(BU70),"") -> 6 | CC70: =IF($BX70<>"",MONTH(BX70),"")
A71: 46188.532 | B71: 1 - CON SEC | C71: MASIVO RESIDENCIAL | F71: CLIENTE NO RESPONDE PARA GRABACION / no contesta 17:18pm | G71: 104553377 | I71: ROCIO | J71: 987923084 | K71: DNI | L71: 42907864 | M71: ROBERTO CARLOS DELGADO CHAPOÑAN | N71: 31003 | O71: LAMBAYEQUE | P71: 130101 | AF71: Pueblo Libre | AQ71: Gilberto | AR71: Graciela | AS71: robertodelgado694@gmail.com | AU71: 987923084 | AV71: 987923084 | AW71: Urb. Azcona ,calle Simón Condori 120 Pueblo Libre | AX71: 5 | AY71: 501 | AZ71: -12.06852399, -77.05286892 | BA71: a dos casas de hotel Mariátegui | BB71: LMPL025-S | BC71: LIMA METROPOLITANA | BD71: =IF(COUNTA(Q71:AP71)>0,INDEX(Q71:AP71,,max(IF(Q71:AP71<>"",COLUMN(Q71:AP71)))-16),"") -> Pueblo Libre | BE71: FTTH | BF71: NO | BG71: ALTA NUEVA | BL71: 2 PLAY + TV ESTANDAR | BM71: Campaña Regular | BN71: 170 | BO71: 400MBPS | BP71: SI | BQ71: NO | BR71: 2 | BS71: 1 | BU71: =IF($A71<>"", DATE(YEAR($A71),MONTH($A71),DAY($A71)),"") -> 46188 | BV71: =IF($E71<>"",DATE(YEAR($E71),MONTH($E71),DAY($E71)),"") | BW71: =IF($E71<>"",TEXT($E71,"HH"),"") | BZ71: =IF(B71<>"",VALUE(LEFT(B71)),"") -> 1 | CA71: {=IF($A71<>"",INDEX(LISTA!$M$2:$N$27,MATCH($BC71,LISTA!$N$2:$N$27,0),1),"")} -> 1 | CB71: =IF($A71<>"",MONTH(BU71),"") -> 6 | CC71: =IF($BX71<>"",MONTH(BX71),"")
A72: 46189.711 | B72: 1 - CON SEC | C72: MASIVO RESIDENCIAL | F72: CLIENTE NO DESEA ACEPTAR PLAN CON PAGO DE INSTALACION | G72: 104593919 | I72: PAOLA | J72: 978352937 | K72: CE | L72: 002978213 | M72: ALEXYS ALEXANDER BONALDE SANCHEZ | N72: 26760 | O72: OTRO PAIS | P72: 0 | AF72: Surquillo | AQ72: PEDRO | AR72: MARIA | AS72: AVSREFRIGERACION@GMAIL.COM | AU72: 978352937 | AV72: 978352937 | AW72: JR EL CARMEN 545 | AX72: 1 | AY72: NA | AZ72: -12.115108459, -77.025491806 | BA72: EL CARMEN | BB72: LMSQ153-F | BC72: LIMA METROPOLITANA | BD72: =IF(COUNTA(Q72:AP72)>0,INDEX(Q72:AP72,,max(IF(Q72:AP72<>"",COLUMN(Q72:AP72)))-16),"") -> Surquillo | BE72: FTTH | BF72: SI | BG72: ALTA NUEVA | BL72: 1 PLAY | BM72: Campaña Regular | BN72: 89 | BO72: 400MBPS | BP72: NO | BQ72: NO | BR72: Ninguno | BS72: 1 | BU72: =IF($A72<>"", DATE(YEAR($A72),MONTH($A72),DAY($A72)),"") -> 46189 | BV72: =IF($E72<>"",DATE(YEAR($E72),MONTH($E72),DAY($E72)),"") | BW72: =IF($E72<>"",TEXT($E72,"HH"),"") | BZ72: =IF(B72<>"",VALUE(LEFT(B72)),"") -> 1 | CA72: {=IF($A72<>"",INDEX(LISTA!$M$2:$N$27,MATCH($BC72,LISTA!$N$2:$N$27,0),1),"")} -> 1 | CB72: =IF($A72<>"",MONTH(BU72),"") -> 6 | CC72: =IF($BX72<>"",MONTH(BX72),"")
A73: 46196.771 | B73: 1 - CON SEC | C73: NEGOCIOS | F73: CLIENTE AUN NO SE ANIMA A CONTRATAR, INDICA QUE PUEDE SER DENTRO DE 2 SEMANAS, AUN NO SE MUDA A ESE LUGAR | I73: JULIANA | J73: 945801446 | K73: RUC | L73: 10471065175 | M73: FRETEL MASGO DONNI GEORGE | N73: 33730 | O73: LIMA | P73: 140101 | AF73: Comas | AQ73: HUGO | AR73: AMALIA | AS73: DONNI.FRETEL@GMAIL.COM | AU73: 945801446 | AV73: 945801446 | AW73: URB. CARABAYLLO 2 ETAPA MZ I LOTE 20 | AX73: 2 | AY73: 1 | AZ73: -11.9664275, -77.060547552 | BA73: A UNA CUADRA DEL COLEGIO EE.UU | BB73: LMCO121-S | BC73: LIMA METROPOLITANA | BD73: =IF(COUNTA(Q73:AP73)>0,INDEX(Q73:AP73,,max(IF(Q73:AP73<>"",COLUMN(Q73:AP73)))-16),"") -> Comas | BE73: FTTH | BF73: NO | BG73: ALTA NUEVA | BL73: 2 PLAY + TV ESTANDAR | BM73: Campaña Regular | BN73: 170 | BO73: 400MBPS | BP73: SI | BQ73: NO | BR73: 2 | BS73: 1 | BU73: =IF($A73<>"", DATE(YEAR($A73),MONTH($A73),DAY($A73)),"") -> 46196 | BV73: =IF($E73<>"",DATE(YEAR($E73),MONTH($E73),DAY($E73)),"") | BW73: =IF($E73<>"",TEXT($E73,"HH"),"") | BZ73: =IF(B73<>"",VALUE(LEFT(B73)),"") -> 1 | CA73: {=IF($A73<>"",INDEX(LISTA!$M$2:$N$27,MATCH($BC73,LISTA!$N$2:$N$27,0),1),"")} -> 1 | CB73: =IF($A73<>"",MONTH(BU73),"") -> 6 | CC73: =IF($BX73<>"",MONTH(BX73),"")
A74: 46198.851 | B74: 1 - CON SEC | C74: MASIVO RESIDENCIAL | F74: CLIENTE NO RESPONDE GRABACION | G74: 104853134 | I74: YESSENIA | J74: 901523986 | K74: DNI | L74: 60812872 | M74: ROBERTO FAVIO VIVES RUIDIAS | N74: 38910 | O74: LAMBAYEQUE | P74: 140101 | AF74: Carabayllo | AQ74: ROBERTO | AR74: FIORELLA | AS74: favio.vives.ruidias@gmail.com | AU74: 901523986 | AV74: 901523986 | AW74: :MZ F LT SOL URB EL RETABLO ET.1 Edificio: TORRES DEL CAMPO - BLOCK 24 - TORRE A PISO: 7 dto 703 | AX74: 7 | AY74: 703 | AZ74: -11.938157, -77.053644 | BA74: AV RETABLO | BB74: LMCO085 | BC74: LIMA METROPOLITANA | BD74: =IF(COUNTA(Q74:AP74)>0,INDEX(Q74:AP74,,max(IF(Q74:AP74<>"",COLUMN(Q74:AP74)))-16),"") -> Carabayllo | BE74: HFC | BF74: NO | BG74: ALTA NUEVA | BL74: 1 PLAY | BM74: Campaña Promo Mediana | BN74: 89 | BO74: 400MBPS | BP74: NO | BQ74: NO | BR74: Ninguno | BS74: Ninguno | BU74: =IF($A74<>"", DATE(YEAR($A74),MONTH($A74),DAY($A74)),"") -> 46198 | BV74: =IF($E74<>"",DATE(YEAR($E74),MONTH($E74),DAY($E74)),"") | BW74: =IF($E74<>"",TEXT($E74,"HH"),"") | BZ74: =IF(B74<>"",VALUE(LEFT(B74)),"") -> 1 | CA74: {=IF($A74<>"",INDEX(LISTA!$M$2:$N$27,MATCH($BC74,LISTA!$N$2:$N$27,0),1),"")} -> 1 | CB74: =IF($A74<>"",MONTH(BU74),"") -> 6 | CC74: =IF($BX74<>"",MONTH(BX74),"")
A75: 46197.708 | B75: 0 - PDTE-HABILITAR CONDOMINIO | C75: MASIVO RESIDENCIAL | D75: NAYELI | E75: 46199.458 | F75: SE ESTA CONSULTANDO SI PERMITEN TENDIDO AEREO | G75: 104817893 | H75: 88595396 | I75: SAHIR | J75: 942139797 | K75: DNI | L75: 32912155 | M75: CESAR AMERICO AVALOS GONZALES | N75: 25062 | O75: ANCASH | P75: 021801 | AF75: Miraflores | AQ75: Cesar | AR75: Victoria | AS75: cavalosg2012@gmail.com | AU75: 942139797 | AV75: 942139797 | AW75: av jose larco 658 edif | AX75: 1 | AY75: 1 | AZ75: -12.123832, -77.02943 | BA75: Al costado de Balta y de un hostal | BB75: 5418B04 | BC75: LIMA METROPOLITANA | BD75: =IF(COUNTA(Q75:AP75)>0,INDEX(Q75:AP75,,max(IF(Q75:AP75<>"",COLUMN(Q75:AP75)))-16),"") -> Miraflores | BE75: HFC | BF75: NO | BG75: ALTA NUEVA | BL75: 1 PLAY | BM75: Campaña 1 sol | BN75: 89 | BO75: 400MBPS | BP75: NO | BQ75: NO | BR75: Ninguno | BS75: Ninguno | BU75: =IF($A75<>"", DATE(YEAR($A75),MONTH($A75),DAY($A75)),"") -> 46197 | BV75: =IF($E75<>"",DATE(YEAR($E75),MONTH($E75),DAY($E75)),"") -> 46199 | BW75: =IF($E75<>"",TEXT($E75,"HH"),"") -> 11 | BZ75: =IF(B75<>"",VALUE(LEFT(B75)),"") -> 0 | CA75: {=IF($A75<>"",INDEX(LISTA!$M$2:$N$27,MATCH($BC75,LISTA!$N$2:$N$27,0),1),"")} -> 1 | CB75: =IF($A75<>"",MONTH(BU75),"") -> 6 | CC75: =IF($BX75<>"",MONTH(BX75),"")
A76: 46190.558 | B76: 0 - NO DESEA-GRABAR | C76: MASIVO RESIDENCIAL | F76: desiste , no desea solo internet . el que contrato era el hermano y la titular disiste | I76: OJT | J76: 981241647 | K76: DNI | L76: 71066219 | M76: DIANA MARILIA ROSILLO MARTEL | N76: 33829 | O76: HUANUCO | P76: 090407 | AF76: San Juan de Miraflores | AQ76: FLORESMILO | AR76: silvia | AS76: calderonchistelgimal.com | AU76: 981241647 | AV76: 981241647 | AW76: JR ARICA 195 SAN JUAN De MIRAFLORES | AX76: 1 | AY76: S/I | AZ76: -12.157105, -76.961796 | BA76: av salvador ayendes y av los heroes | BB76: LMJR015-S | BC76: LIMA METROPOLITANA | BD76: =IF(COUNTA(Q76:AP76)>0,INDEX(Q76:AP76,,max(IF(Q76:AP76<>"",COLUMN(Q76:AP76)))-16),"") -> San Juan de Miraflores | BE76: FTTH | BF76: SI | BG76: ALTA NUEVA | BL76: 1 PLAY | BM76: Campaña Regular PRO | BN76: 110 | BO76: 500MBPS | BP76: SI | BQ76: NO | BR76: Ninguno | BS76: 1 | BU76: =IF($A76<>"", DATE(YEAR($A76),MONTH($A76),DAY($A76)),"") -> 46190 | BV76: =IF($E76<>"",DATE(YEAR($E76),MONTH($E76),DAY($E76)),"") | BW76: =IF($E76<>"",TEXT($E76,"HH"),"") | BZ76: =IF(B76<>"",VALUE(LEFT(B76)),"") -> 0 | CA76: {=IF($A76<>"",INDEX(LISTA!$M$2:$N$27,MATCH($BC76,LISTA!$N$2:$N$27,0),1),"")} -> 1 | CB76: =IF($A76<>"",MONTH(BU76),"") -> 6 | CC76: =IF($BX76<>"",MONTH(BX76),"")
A77: 46191.75 | B77: 0 - NO DESEA-GRABAR | C77: MASIVO RESIDENCIAL | F77: LLAMAR VIERNES 10:30AM / NO CONESTA | G77: 104661503 | I77: JULIANA | J77: 958221651 | K77: DNI | L77: 29589745 | M77: FANNY NARDA PONCE TEJADA | N77: 25606 | O77: AREQUIPA | P77: 040122 | T77: Arequipa | AQ77: EUSEBIO | AR77: ELSA | AS77: F_PONCETEJADA@MSN.COM | AU77: 958221651 | AV77: 958221651 | AW77: URB. CASACAMPO MZ D LOTE 8, SACHACA- AREQUIPA. | AX77: 2 | AY77: 1 | AZ77: -16.434984, -71.571174 | BA77: ESPALDA DEL COLEGIO MAX ULE | BB77: AQSC014-S | BC77: AREQUIPA | BD77: =IF(COUNTA(Q77:AP77)>0,INDEX(Q77:AP77,,max(IF(Q77:AP77<>"",COLUMN(Q77:AP77)))-16),"") -> Arequipa | BE77: FTTH | BF77: SI | BG77: ALTA NUEVA | BL77: 2 PLAY + TV ESTANDAR | BM77: Campaña Regular | BN77: 170 | BO77: 400MBPS | BP77: SI | BQ77: NO | BR77: 2 | BS77: 1 | BU77: =IF($A77<>"", DATE(YEAR($A77),MONTH($A77),DAY($A77)),"") -> 46191 | BV77: =IF($E77<>"",DATE(YEAR($E77),MONTH($E77),DAY($E77)),"") | BW77: =IF($E77<>"",TEXT($E77,"HH"),"") | BZ77: =IF(B77<>"",VALUE(LEFT(B77)),"") -> 0 | CA77: {=IF($A77<>"",INDEX(LISTA!$M$2:$N$27,MATCH($BC77,LISTA!$N$2:$N$27,0),1),"")} -> 7 | CB77: =IF($A77<>"",MONTH(BU77),"") -> 6 | CC77: =IF($BX77<>"",MONTH(BX77),"")
A78: 46197.64 | B78: 0 - NO DESEA | C78: MASIVO RESIDENCIAL | D78: NAYELI | E78: 46201.375 | F78: CLIENTE INDICA QUE CONTRATO FTTH, PERO TIENE HFC | G78: 104812017 | H78: 88593039 | I78: GABRIEL | J78: 972916945 | K78: DNI | L78: 40939442 | M78: OMAR ANGEL LIZA LOAYZA | N78: 28755 | O78: LIMA METROPOLITANA | P78: 150111 | AF78: Santa Anita | AQ78: ALFREDO | AR78: ROSALVINA | AS78: angel.omarliza@gmail.com | AU78: 972916945 | AV78: 972916945 | AW78: CL ANTONIO PORTUGAL 703 URB LOS FICUS SANTA ANITA PISO 2 | AX78: 2 | AY78: 202 | AZ78: -12.048692, -76.973261 | BA78: av 7 de junio | BB78: LMSA033 | BC78: LIMA METROPOLITANA | BD78: =IF(COUNTA(Q78:AP78)>0,INDEX(Q78:AP78,,max(IF(Q78:AP78<>"",COLUMN(Q78:AP78)))-16),"") -> Santa Anita | BE78: HFC | BF78: NO | BG78: ALTA NUEVA | BL78: 1 PLAY | BM78: Campaña Promo Mediana | BN78: 89 | BO78: 400MBPS | BP78: NO | BQ78: NO | BR78: Ninguno | BS78: Ninguno | BU78: =IF($A78<>"", DATE(YEAR($A78),MONTH($A78),DAY($A78)),"") -> 46197 | BV78: =IF($E78<>"",DATE(YEAR($E78),MONTH($E78),DAY($E78)),"") -> 46201 | BW78: =IF($E78<>"",TEXT($E78,"HH"),"") -> 09 | BZ78: =IF(B78<>"",VALUE(LEFT(B78)),"") -> 0 | CA78: {=IF($A78<>"",INDEX(LISTA!$M$2:$N$27,MATCH($BC78,LISTA!$N$2:$N$27,0),1),"")} -> 1 | CB78: =IF($A78<>"",MONTH(BU78),"") -> 6 | CC78: =IF($BX78<>"",MONTH(BX78),"")
A79: 46188.667 | B79: 0 - NO CONTESTA | C79: MASIVO RESIDENCIAL | F79: cl esta en la calle , escucho y corto la llamada | I79: BRITNEY | J79: 917209845 | K79: CE | L79: 009222418 | M79: DEWAR JOSE ASCANIO LUGO | N79: 36054 | O79: OTRO PAIS | P79: 090000 | AF79: Rimac | AQ79: FRANCISCO | AR79: YARITZA | AS79: dewarascanio212@gmail.com | AU79: 917209845 | AV79: 917209845 | AW79: CALLE EL CORREGIDOR 238 PUEBLO JOVEN VILLA FATIMA | AX79: 2 | AY79: 1 | AZ79: -12.03537835, -77.021854119 | BA79: Iglesia Adventista del Séptimo Dia Flor de Amancaes | BB79: LMRC064-F | BC79: LIMA METROPOLITANA | BD79: =IF(COUNTA(Q79:AP79)>0,INDEX(Q79:AP79,,max(IF(Q79:AP79<>"",COLUMN(Q79:AP79)))-16),"") -> Rimac | BE79: FTTH | BF79: NO | BG79: ALTA NUEVA | BL79: 1 PLAY + L1MAX | BM79: Campaña Regular PRO | BN79: 110 | BO79: 500MBPS | BP79: SI | BQ79: NO | BR79: Ninguno | BS79: 1 | BU79: =IF($A79<>"", DATE(YEAR($A79),MONTH($A79),DAY($A79)),"") -> 46188 | BV79: =IF($E79<>"",DATE(YEAR($E79),MONTH($E79),DAY($E79)),"") | BW79: =IF($E79<>"",TEXT($E79,"HH"),"") | BZ79: =IF(B79<>"",VALUE(LEFT(B79)),"") -> 0 | CA79: {=IF($A79<>"",INDEX(LISTA!$M$2:$N$27,MATCH($BC79,LISTA!$N$2:$N$27,0),1),"")} -> 1 | CB79: =IF($A79<>"",MONTH(BU79),"") -> 6 | CC79: =IF($BX79<>"",MONTH(BX79),"")
A80: 46203.601 | B80: 0 - NO CONTESTA | C80: MASIVO RESIDENCIAL | I80: JESSICA | J80: 920604149 | K80: DNI | L80: 16625471 | M80: ADRIAN PAICO CHUCAS | N80: 17771 | O80: LAMBAYEQUE | P80: 130202 | AD80: Chiclayo | AQ80: GENARO | AR80: ISIDORA | AS80: mv_henrypaico@hotmail.com | AU80: 920604149 | AV80: 920604149 | AW80: AV. VENEZUELA 160 URB. URRUNAGA | AX80: 1 | AY80: 1 | AZ80: -6.75555372, -79.83194353 | BA80: AV. MEXICO | BB80: LBLO007-F | BC80: LAMBAYEQUE | BD80: =IF(COUNTA(Q80:AP80)>0,INDEX(Q80:AP80,,max(IF(Q80:AP80<>"",COLUMN(Q80:AP80)))-16),"") -> Chiclayo | BE80: FTTH | BF80: NO | BG80: ALTA NUEVA | BL80: 1 PLAY + L1MAX | BM80: Campaña Regular PRO | BN80: 110 | BO80: 500MBPS | BP80: SI | BQ80: NO | BR80: Ninguno | BS80: 1 | BU80: =IF($A80<>"", DATE(YEAR($A80),MONTH($A80),DAY($A80)),"") -> 46203 | BV80: =IF($E80<>"",DATE(YEAR($E80),MONTH($E80),DAY($E80)),"") | BW80: =IF($E80<>"",TEXT($E80,"HH"),"") | BZ80: =IF(B80<>"",VALUE(LEFT(B80)),"") -> 0 | CA80: {=IF($A80<>"",INDEX(LISTA!$M$2:$N$27,MATCH($BC80,LISTA!$N$2:$N$27,0),1),"")} -> 16 | CB80: =IF($A80<>"",MONTH(BU80),"") -> 6 | CC80: =IF($BX80<>"",MONTH(BX80),"")
A81: 46186.666 | B81: 0 - MAL REGISTRADO | C81: MASIVO RESIDENCIAL | D81: PAOLA | E81: 46190.458 | F81: LYBTEL - VENTA NO PROCEDE SE MANDA A ANULAR SOT | G81: 104517133 | H81: 88314647 | I81: JULIANA | J81: 964676992 | K81: DNI | L81: 46297872 | M81: YONNY JUNIOR PONCE BERROSPI | N81: 32672 | O81: LIMA | P81: 150101 | AF81: Villa María del Triunfo | AQ81: MIGUEL | AR81: LILIANA | AS81: YONNY11@GMAIL.COM | AU81: 964676992 | AV81: 964676992 | AW81: Acacias 186, Urb. Villa Jardin 2da zona - Villa María del Triunfo. | AX81: 3 | AY81: 1 | AZ81: -12.168513, -76.952031 | BA81: A dos cuadras de la estación del tren. | BB81: LMJR156-F | BC81: LIMA METROPOLITANA | BD81: =IF(COUNTA(Q81:AP81)>0,INDEX(Q81:AP81,,max(IF(Q81:AP81<>"",COLUMN(Q81:AP81)))-16),"") -> Villa María del Triunfo | BE81: FTTH | BF81: SI | BG81: ALTA NUEVA | BL81: 1 PLAY | BM81: Campaña Regular | BN81: 89 | BO81: 400MBPS | BP81: NO | BQ81: NO | BR81: Ninguno | BS81: 1 | BU81: =IF($A81<>"", DATE(YEAR($A81),MONTH($A81),DAY($A81)),"") -> 46186 | BV81: =IF($E81<>"",DATE(YEAR($E81),MONTH($E81),DAY($E81)),"") -> 46190 | BW81: =IF($E81<>"",TEXT($E81,"HH"),"") -> 11 | BZ81: =IF(B81<>"",VALUE(LEFT(B81)),"") -> 0 | CA81: {=IF($A81<>"",INDEX(LISTA!$M$2:$N$27,MATCH($BC81,LISTA!$N$2:$N$27,0),1),"")} -> 1 | CB81: =IF($A81<>"",MONTH(BU81),"") -> 6 | CC81: =IF($BX81<>"",MONTH(BX81),"")
A82: 46190.792 | B82: 0 - MAL REGISTRADO | C82: MASIVO RESIDENCIAL | D82: NAYELI | E82: 46192.583 | F82: Transacción no autorizada - Motor : Teléfono restringido AXB | G82: 104636435 | H82: 88430553 | I82: JULIANA | J82: 977458142 | K82: DNI | L82: 32764297 | M82: MANUEL ALBERTO SICHE PURIZAGA | N82: 20595 | O82: LA LIBERTAD | P82: 120806 | R82: Santa | AQ82: MANUEL | AR82: INES | AS82: MANUEL.SICHE10@GMAIL.COM | AU82: 977458142 | AV82: 977458142 | AW82: HUP CALIFORNIA MZ A LOTE 15, NUEVO CHIMBOTE, ANCASH. | AX82: 1 | AY82: 1 | AZ82: -9.110619251283516, -78.51559622669309 | BA82: CERCA AL MERCADO VILLAMAR | BB82: CBNV064-S | BC82: ANCASH | BD82: =IF(COUNTA(Q82:AP82)>0,INDEX(Q82:AP82,,max(IF(Q82:AP82<>"",COLUMN(Q82:AP82)))-16),"") -> Santa | BE82: FTTH | BF82: NO | BG82: ALTA NUEVA | BL82: 2 PLAY + TV ESTANDAR | BM82: Campaña Regular | BN82: 170 | BO82: 400MBPS | BP82: SI | BQ82: NO | BR82: 2 | BS82: 1 | BU82: =IF($A82<>"", DATE(YEAR($A82),MONTH($A82),DAY($A82)),"") -> 46190 | BV82: =IF($E82<>"",DATE(YEAR($E82),MONTH($E82),DAY($E82)),"") -> 46192 | BW82: =IF($E82<>"",TEXT($E82,"HH"),"") -> 14 | BZ82: =IF(B82<>"",VALUE(LEFT(B82)),"") -> 0 | CA82: {=IF($A82<>"",INDEX(LISTA!$M$2:$N$27,MATCH($BC82,LISTA!$N$2:$N$27,0),1),"")} -> 5 | CB82: =IF($A82<>"",MONTH(BU82),"") -> 6 | CC82: =IF($BX82<>"",MONTH(BX82),"")
A83: 46192.526 | B83: 0 - MAL REGISTRADO | C83: MASIVO RESIDENCIAL | D83: PAOLA | E83: 46193.458 | F83: CLIENTE CON EXCLUSIVIDAD | G83: 104674851 | H83: 88464212 | I83: JESSICA | J83: 941148818 | K83: DNI | L83: 09855021 | M83: JUAN CARLOS VILLAR FROLETZ | N83: 26505 | O83: LIMA | P83: 140101 | AF83: Magdalena del Mar | AQ83: ORLANDO | AR83: BERTHA | AS83: jc2572vf@gmail.com | AU83: 941148818 | AV83: 941148818 | AW83: CALLE AMAZONAS 525 URB. OYAGUE | AX83: 8 | AY83: 803 | AZ83: -12.085005, -77.068315 | BA83: Jarabar Pueblo Libre | BB83: LMMG006-S | BC83: LIMA METROPOLITANA | BD83: =IF(COUNTA(Q83:AP83)>0,INDEX(Q83:AP83,,max(IF(Q83:AP83<>"",COLUMN(Q83:AP83)))-16),"") -> Magdalena del Mar | BE83: FTTH | BF83: NO | BG83: ALTA NUEVA | BL83: 1 PLAY + L1MAX | BM83: Campaña Regular PRO | BN83: 110 | BO83: 500MBPS | BP83: SI | BQ83: NO | BR83: Ninguno | BS83: 1 | BU83: =IF($A83<>"", DATE(YEAR($A83),MONTH($A83),DAY($A83)),"") -> 46192 | BV83: =IF($E83<>"",DATE(YEAR($E83),MONTH($E83),DAY($E83)),"") -> 46193 | BW83: =IF($E83<>"",TEXT($E83,"HH"),"") -> 11 | BZ83: =IF(B83<>"",VALUE(LEFT(B83)),"") -> 0 | CA83: {=IF($A83<>"",INDEX(LISTA!$M$2:$N$27,MATCH($BC83,LISTA!$N$2:$N$27,0),1),"")} -> 1 | CB83: =IF($A83<>"",MONTH(BU83),"") -> 6 | CC83: =IF($BX83<>"",MONTH(BX83),"")
A84: 46193.54 | B84: 0 - MAL REGISTRADO | C84: MASIVO RESIDENCIAL | F84: CLIENTE DESEA PRECIO FIJO - NO DESEA | I84: OJT | J84: 927649497 | K84: DNI | L84: 73476852 | M84: JUNIOR ALDAIR YOVERA RIVAS | N84: 36812 | O84: LIMA | P84: 140133 | AK84: Piura | AQ84: segundo | AR84: bertha | AS84: junioraldairyoverarivas@gmail.com | AU84: 927649497 | AV84: 927649497 | AW84: jr amazonas 1188 | AX84: 1 | AY84: 1 | AZ84: -5.099549276, -80.168007784 | BA84: cruce con jr tarapaca | BB84: PICH013-F | BC84: PIURA | BD84: =IF(COUNTA(Q84:AP84)>0,INDEX(Q84:AP84,,max(IF(Q84:AP84<>"",COLUMN(Q84:AP84)))-16),"") -> Piura | BE84: FTTH | BF84: NO | BG84: ALTA NUEVA | BL84: 1 PLAY + L1MAX | BM84: Campaña Regular | BN84: 110 | BO84: 500MBPS | BP84: SI | BQ84: NO | BR84: Ninguno | BS84: Ninguno | BU84: =IF($A84<>"", DATE(YEAR($A84),MONTH($A84),DAY($A84)),"") -> 46193 | BV84: =IF($E84<>"",DATE(YEAR($E84),MONTH($E84),DAY($E84)),"") | BW84: =IF($E84<>"",TEXT($E84,"HH"),"") | BZ84: =IF(B84<>"",VALUE(LEFT(B84)),"") -> 0 | CA84: {=IF($A84<>"",INDEX(LISTA!$M$2:$N$27,MATCH($BC84,LISTA!$N$2:$N$27,0),1),"")} -> 21 | CB84: =IF($A84<>"",MONTH(BU84),"") -> 6 | CC84: =IF($BX84<>"",MONTH(BX84),"")
A85: 46193.74 | B85: 0 - MAL REGISTRADO | C85: MASIVO RESIDENCIAL | I85: BRITNEY | J85: 912 095 630 | K85: DNI | L85: 42563656 | M85: JORGE LUIS GAMARRA ARAUCO | N85: 30538 | O85: LIMA | P85: 150101 | AF85: San Juan de Lurigancho | AQ85: Angel Gamarra | AR85: Julia Arauco | AS85: juanalbertogamarraarauco@gmail.com | AU85: 912095630 | AV85: 912095630 | AW85: AV LOS AUMAUTAS 401 | AX85: 2 | AY85: 1 | AZ85: -11.992660, -77.051580 | BA85: Colegio el morro | BB85: LMIN004-S | BC85: LIMA METROPOLITANA | BD85: =IF(COUNTA(Q85:AP85)>0,INDEX(Q85:AP85,,max(IF(Q85:AP85<>"",COLUMN(Q85:AP85)))-16),"") -> San Juan de Lurigancho | BE85: FTTH | BF85: NO | BG85: ALTA NUEVA | BL85: 2 PLAY + TV ESTANDAR | BM85: Campaña Regular | BN85: 170 | BO85: 400MBPS | BP85: SI | BQ85: NO | BR85: 2 | BS85: 1 | BU85: =IF($A85<>"", DATE(YEAR($A85),MONTH($A85),DAY($A85)),"") -> 46193 | BV85: =IF($E85<>"",DATE(YEAR($E85),MONTH($E85),DAY($E85)),"") | BW85: =IF($E85<>"",TEXT($E85,"HH"),"") | BZ85: =IF(B85<>"",VALUE(LEFT(B85)),"") -> 0 | CA85: {=IF($A85<>"",INDEX(LISTA!$M$2:$N$27,MATCH($BC85,LISTA!$N$2:$N$27,0),1),"")} -> 1 | CB85: =IF($A85<>"",MONTH(BU85),"") -> 6 | CC85: =IF($BX85<>"",MONTH(BX85),"")
A86: 46196.362 | B86: 0 - MAL REGISTRADO | C86: MASIVO RESIDENCIAL | D86: NAYELI | F86: CLIENTE CON EXCLUSIVIDAD, SE IBA A RECUPERAR PERO CREARON SOT | I86: JESSICA | J86: 953750449 | K86: DNI | L86: 40495931 | M86: DANIEL DE JESUS CRUZ GUTIERREZ | N86: 23815 | O86: OTRO PAIS | P86: 090901 | AN86: Tacna | AQ86: JORGE | AR86: MARIA | AS86: dcruz@cmssac.com | AU86: 953750449 | AV86: 953750449 | AW86: Av. Basadre Y Forero 2361 | AX86: 2 | AY86: NA | AZ86: -17.99818403, -70.23703405 | BA86: Av. Francisco Paula Vigil | BB86: TCNA015-S | BC86: TACNA | BD86: =IF(COUNTA(Q86:AP86)>0,INDEX(Q86:AP86,,max(IF(Q86:AP86<>"",COLUMN(Q86:AP86)))-16),"") -> Tacna | BE86: FTTH | BF86: NO | BG86: ALTA NUEVA | BL86: 1 PLAY + L1MAX | BM86: Campaña Regular PRO | BN86: 110 | BO86: 500MBPS | BP86: NO | BQ86: NO | BR86: Ninguno | BS86: 1 | BU86: =IF($A86<>"", DATE(YEAR($A86),MONTH($A86),DAY($A86)),"") -> 46196 | BV86: =IF($E86<>"",DATE(YEAR($E86),MONTH($E86),DAY($E86)),"") | BW86: =IF($E86<>"",TEXT($E86,"HH"),"") | BZ86: =IF(B86<>"",VALUE(LEFT(B86)),"") -> 0 | CA86: {=IF($A86<>"",INDEX(LISTA!$M$2:$N$27,MATCH($BC86,LISTA!$N$2:$N$27,0),1),"")} -> 24 | CB86: =IF($A86<>"",MONTH(BU86),"") -> 6 | CC86: =IF($BX86<>"",MONTH(BX86),"")
A87: 46198.491 | B87: 0 - MAL REGISTRADO | C87: MASIVO RESIDENCIAL | F87: AXB CLIENTE YA TIENE SERVICIO EN MISMO DPTO | I87: ANTHONELLA | J87: 980517641 | K87: DNI | L87: 29560352 | M87: ELIZABETH AURORA LA TORRE CORDOVA | N87: 26690 | O87: LIMA | P87: 150101 | T87: Arequipa | AQ87: victor | AR87: ELIZABETH | AS87: ELIZABETH.LATORREC@gimail.com | AU87: 980517641 | AV87: 980517641 | AW87: AV GARCILAZO DE LA VEGA 100 Edificio: AV. GARCILAZO DE LA VEGA S/N (CHALLAPALCA VALLE BLANCO ETAPA 3) - BLOCK 10 | AX87: 2 | AY87: 203 | AZ87: -16.389817, -71.562811 | BA87: CALLE LAS DALIAS | BB87: AQCC024-S | BC87: AREQUIPA | BD87: =IF(COUNTA(Q87:AP87)>0,INDEX(Q87:AP87,,max(IF(Q87:AP87<>"",COLUMN(Q87:AP87)))-16),"") -> Arequipa | BE87: FTTH | BF87: SI | BG87: ALTA NUEVA | BL87: 1 PLAY | BM87: Campaña Promo Mediana | BN87: 89 | BO87: 400MBPS | BP87: SI | BQ87: NO | BR87: Ninguno | BS87: Ninguno | BU87: =IF($A87<>"", DATE(YEAR($A87),MONTH($A87),DAY($A87)),"") -> 46198 | BV87: =IF($E87<>"",DATE(YEAR($E87),MONTH($E87),DAY($E87)),"") | BW87: =IF($E87<>"",TEXT($E87,"HH"),"") | BZ87: =IF(B87<>"",VALUE(LEFT(B87)),"") -> 0 | CA87: {=IF($A87<>"",INDEX(LISTA!$M$2:$N$27,MATCH($BC87,LISTA!$N$2:$N$27,0),1),"")} -> 7 | CB87: =IF($A87<>"",MONTH(BU87),"") -> 6 | CC87: =IF($BX87<>"",MONTH(BX87),"")
A88: 46200.72 | B88: 0 - MAL REGISTRADO | C88: MASIVO RESIDENCIAL | D88: NAYELI | E88: 46202.667 | F88: SE JALA COBERTURA/ NO PROCEDE INDICAN QUE ESTA FUERA DE PLANO | G88: 104907822 | H88: 88678682 | I88: JESSICA | J88: 922024860 | K88: DNI | L88: 09910720 | M88: VERONICA JANETH ORTEGA MARTINEZ | N88: 27638 | O88: HUANUCO | P88: 090101 | AF88: Comas | AQ88: ADRIAN | AR88: GILDA | AS88: Vortega@padrechampagnat.edu.pe | AU88: 915252654 | AV88: 915252654 | AW88: CALLE SANTA PATRICIA 6589 ASOC. SANTA ROSA DE INFANTAS | AX88: 2 | AY88: NA | AZ88: -11.94583282, -77.07002383 | BA88: PASAJE SANTA ELENA | BB88: LMCO195-F | BC88: LIMA METROPOLITANA | BD88: =IF(COUNTA(Q88:AP88)>0,INDEX(Q88:AP88,,max(IF(Q88:AP88<>"",COLUMN(Q88:AP88)))-16),"") -> Comas | BE88: FTTH | BF88: SI | BG88: ALTA NUEVA | BL88: 1 PLAY | BM88: Campaña Promo Mediana | BN88: 89 | BO88: 400MBPS | BP88: NO | BQ88: NO | BR88: Ninguno | BS88: 1 | BU88: =IF($A88<>"", DATE(YEAR($A88),MONTH($A88),DAY($A88)),"") -> 46200 | BV88: =IF($E88<>"",DATE(YEAR($E88),MONTH($E88),DAY($E88)),"") -> 46202 | BW88: =IF($E88<>"",TEXT($E88,"HH"),"") -> 16 | BZ88: =IF(B88<>"",VALUE(LEFT(B88)),"") -> 0 | CA88: {=IF($A88<>"",INDEX(LISTA!$M$2:$N$27,MATCH($BC88,LISTA!$N$2:$N$27,0),1),"")} -> 1 | CB88: =IF($A88<>"",MONTH(BU88),"") -> 6 | CC88: =IF($BX88<>"",MONTH(BX88),"")
A89: 46197.721 | B89: 0 - GRABADO | C89: MASIVO RESIDENCIAL | D89: NAYELI | F89: REQUIERE EVALUACION CREDITICIA/SE ENVIA CORREO | I89: BRITNEY | J89: 932 628 600 | K89: DNI | L89: 09918623 | M89: KENETH ACKERMAN CASTILLO COSIO | N89: 27780 | O89: LIMA | P89: 150113 | AF89: Breña | AQ89: Luis | AR89: Juana | AS89: kenethacastillo04@gmail.com | AU89: 932 628 600 | AV89: 932 628 600 | AW89: JR. Mantaro 533 Dpto 104 Altura de la CDRA 17 de Av Venezuela. | AX89: 1 | AY89: 1 | AZ89: -12.054888, -77.056201 | BA89: Jiron Mantaro | BB89: LMBN031 | BC89: LIMA METROPOLITANA | BD89: =IF(COUNTA(Q89:AP89)>0,INDEX(Q89:AP89,,max(IF(Q89:AP89<>"",COLUMN(Q89:AP89)))-16),"") -> Breña | BE89: HFC | BF89: NO | BG89: ALTA NUEVA | BL89: 2 PLAY + TV ESTANDAR | BM89: Campaña Regular | BN89: 170 | BO89: 400MBPS | BP89: SI | BQ89: NO | BR89: 2 | BS89: Ninguno | BU89: =IF($A89<>"", DATE(YEAR($A89),MONTH($A89),DAY($A89)),"") -> 46197 | BV89: =IF($E89<>"",DATE(YEAR($E89),MONTH($E89),DAY($E89)),"") | BW89: =IF($E89<>"",TEXT($E89,"HH"),"") | BZ89: =IF(B89<>"",VALUE(LEFT(B89)),"") -> 0 | CA89: {=IF($A89<>"",INDEX(LISTA!$M$2:$N$27,MATCH($BC89,LISTA!$N$2:$N$27,0),1),"")} -> 1 | CB89: =IF($A89<>"",MONTH(BU89),"") -> 6 | CC89: =IF($BX89<>"",MONTH(BX89),"")
A90: 46199.424 | B90: 0 - GRABADO | C90: MASIVO RESIDENCIAL | D90: NAYELI | F90: PROCEDE/ NO PERMITE CREAR SOT | G90: 104858533 | I90: JUAN DIEGO | J90: 974775138 | K90: DNI | L90: 43013240 | M90: JESUS HUALLPARIMACHI ZUÑIGA | N90: 30276 | O90: CUSCO | P90: 080101 | X90: Cusco | AQ90: LUIS | AR90: PAULINA | AS90: jesushuzu@hotmail.com | AU90: 974775138 | AV90: 974775138 | AW90: AV PRIMAVERA 453 CUZCO | AX90: 2 | AY90: 203 | AZ90: -13.528558027251995, -71.96919630087847 | BA90: AVENIDA PERU | BB90: CZWQ018 | BC90: CUSCO | BD90: =IF(COUNTA(Q90:AP90)>0,INDEX(Q90:AP90,,max(IF(Q90:AP90<>"",COLUMN(Q90:AP90)))-16),"") -> Cusco | BE90: HFC | BF90: SI | BG90: ALTA NUEVA | BL90: 1 PLAY | BM90: Campaña Regular | BN90: 44 | BO90: 150MBPS | BP90: NO | BQ90: NO | BR90: Ninguno | BS90: Ninguno | BU90: =IF($A90<>"", DATE(YEAR($A90),MONTH($A90),DAY($A90)),"") -> 46199 | BV90: =IF($E90<>"",DATE(YEAR($E90),MONTH($E90),DAY($E90)),"") | BW90: =IF($E90<>"",TEXT($E90,"HH"),"") | BZ90: =IF(B90<>"",VALUE(LEFT(B90)),"") -> 0 | CA90: {=IF($A90<>"",INDEX(LISTA!$M$2:$N$27,MATCH($BC90,LISTA!$N$2:$N$27,0),1),"")} -> 10 | CB90: =IF($A90<>"",MONTH(BU90),"") -> 6 | CC90: =IF($BX90<>"",MONTH(BX90),"")
A91: 46199.685 | B91: 0 - GRABADO | C91: MASIVO RESIDENCIAL | D91: NAYELI | F91: PAGA INSTALACIÓN | I91: SAHIR | J91: 930604033 | K91: DNI | L91: 47363941 | M91: DAVID AROSQUIPA NINAHUAMAN | N91: 33765 | O91: CUSCO | P91: 080801 | X91: Espinar | AQ91: BENIGNO | AR91: FRANCISCA | AS91: dvid.aqpnina@gmail.com | AU91: 930604033 | AV91: 930604033 | AW91: CALLE ACLLUYO MZ B LT 1A URB SAN LUCAS | AX91: 2 | AY91: x | AZ91: -14.797103078563485, -71.41041966624528 | BA91: x | BB91: CZES017-F | BC91: CUSCO | BD91: =IF(COUNTA(Q91:AP91)>0,INDEX(Q91:AP91,,max(IF(Q91:AP91<>"",COLUMN(Q91:AP91)))-16),"") -> Espinar | BE91: FTTH | BF91: NO | BG91: ALTA NUEVA | BL91: 1 PLAY | BM91: Campaña Regular | BN91: 89 | BO91: 400MBPS | BP91: NO | BQ91: NO | BR91: Ninguno | BS91: 1 | BU91: =IF($A91<>"", DATE(YEAR($A91),MONTH($A91),DAY($A91)),"") -> 46199 | BV91: =IF($E91<>"",DATE(YEAR($E91),MONTH($E91),DAY($E91)),"") | BW91: =IF($E91<>"",TEXT($E91,"HH"),"") | BZ91: =IF(B91<>"",VALUE(LEFT(B91)),"") -> 0 | CA91: {=IF($A91<>"",INDEX(LISTA!$M$2:$N$27,MATCH($BC91,LISTA!$N$2:$N$27,0),1),"")} -> 10 | CB91: =IF($A91<>"",MONTH(BU91),"") -> 6 | CC91: =IF($BX91<>"",MONTH(BX91),"")
A92: 46203.641 | B92: 0 - GRABADO | C92: MASIVO RESIDENCIAL | D92: NAYELI | F92: PNDT PAGO INSTALACION | G92: 104971237 | H92: 88771398 | I92: JULIANA | J92: 924010496 | K92: DNI | L92: 74233873 | M92: JHEMY FABIAN PAICO PEREZ | N92: 38090 | O92: LIMA | P92: 140101 | AF92: Puente Piedra | AQ92: GUSTAVO | AR92: TERESITA | AS92: BRISASANTACRUZ10@GMAIL.COM | AU92: 951124863 | AV92: 951124863 | AW92: CALLE 5 MZ 5 LOTE 5 URB. LOS MANANTIALES, PUENTE PIEDRA PIEDRA. LIMA. | AX92: 3 | AY92: 1 | AZ92: -11.88884699095106 -77.06670516878908 | BA92: CERCA A UNA IGLESIA | BB92: LMPP038-F | BC92: LIMA METROPOLITANA | BD92: =IF(COUNTA(Q92:AP92)>0,INDEX(Q92:AP92,,max(IF(Q92:AP92<>"",COLUMN(Q92:AP92)))-16),"") -> Puente Piedra | BE92: FTTH | BF92: NO | BG92: ALTA NUEVA | BL92: 2PLAY + TELF | BM92: Campaña Regular | BN92: 94 | BO92: 400MBPS | BP92: NO | BQ92: SI | BR92: Ninguno | BS92: 1 | BU92: =IF($A92<>"", DATE(YEAR($A92),MONTH($A92),DAY($A92)),"") -> 46203 | BV92: =IF($E92<>"",DATE(YEAR($E92),MONTH($E92),DAY($E92)),"") | BW92: =IF($E92<>"",TEXT($E92,"HH"),"") | BZ92: =IF(B92<>"",VALUE(LEFT(B92)),"") -> 0 | CA92: {=IF($A92<>"",INDEX(LISTA!$M$2:$N$27,MATCH($BC92,LISTA!$N$2:$N$27,0),1),"")} -> 1 | CB92: =IF($A92<>"",MONTH(BU92),"") -> 6 | CC92: =IF($BX92<>"",MONTH(BX92),"")
A93: 46196.622 | B93: 0 - DUPLICADO | C93: MASIVO RESIDENCIAL | D93: NAYELI | E93: 46199.75 | F93: SOT DUPLICADA, SE TIENE QUE ENVIAR CORREO | G93: 104782174 | H93: 88567487 | I93: JULIANA | J93: 929457958 | K93: DNI | L93: 46131332 | M93: MARIO SAUL ATAYUPANQUI YAÑEZ | N93: 32767 | O93: CUSCO | P93: 070101 | X93: Canchis | AQ93: MARIO | AR93: PIEDAD | AS93: MARIOSAUL160989@GMAIL.COM | AU93: 929457958 | AV93: 929457958 | AW93: AV. 2 DE MAYO 738, SICUANI - CUZCO | AX93: 2 | AY93: 1 | AZ93: -14.26693598, -71.22699577 | BA93: A DOS CASAS DEL COLEGIO SANTANDER | BB93: CZSC005-F | BC93: CUSCO | BD93: =IF(COUNTA(Q93:AP93)>0,INDEX(Q93:AP93,,max(IF(Q93:AP93<>"",COLUMN(Q93:AP93)))-16),"") -> Canchis | BE93: FTTH | BF93: SI | BG93: ALTA NUEVA | BL93: 1 PLAY + L1MAX | BM93: Campaña Regular | BN93: 110 | BO93: 500MBPS | BP93: SI | BQ93: NO | BR93: Ninguno | BS93: 1 | BU93: =IF($A93<>"", DATE(YEAR($A93),MONTH($A93),DAY($A93)),"") -> 46196 | BV93: =IF($E93<>"",DATE(YEAR($E93),MONTH($E93),DAY($E93)),"") -> 46199 | BW93: =IF($E93<>"",TEXT($E93,"HH"),"") -> 18 | BZ93: =IF(B93<>"",VALUE(LEFT(B93)),"") -> 0 | CA93: {=IF($A93<>"",INDEX(LISTA!$M$2:$N$27,MATCH($BC93,LISTA!$N$2:$N$27,0),1),"")} -> 10 | CB93: =IF($A93<>"",MONTH(BU93),"") -> 6 | CC93: =IF($BX93<>"",MONTH(BX93),"")
A94: 46195.378 | B94: 0 - CHANCADA / SIN INGRESAR | C94: MASIVO RESIDENCIAL | D94: NAYELI | F94: FULL CLARO - CLIENTE RECIBIO INFORMACION DE OTRO ASESOR, QUE LE INDICO 55 SOLES DE MANERA PERMANENTE | I94: JESSICA | J94: 926547879 | K94: DNI | L94: 70836334 | M94: BIMBI MELISSA TORRES RIVEROS | N94: 35830 | O94: CUSCO | P94: 070108 | AN94: Tacna | AQ94: JUAN CARLOS | AR94: GLORIA | AS94: meli20.04@hotmail.com | AU94: 926547879 | AV94: 926547879 | AW94: URB. VIRGEN ASUNTA MZ J LT 1 | AX94: 1 | AY94: NA | AZ94: -17.996855, -70.259879 | BA94: IEI 418 SEÑOR DE LOS MILAGROS | BB94: TCAL002-F | BC94: TACNA | BD94: =IF(COUNTA(Q94:AP94)>0,INDEX(Q94:AP94,,max(IF(Q94:AP94<>"",COLUMN(Q94:AP94)))-16),"") -> Tacna | BE94: FTTH | BF94: SI | BG94: ALTA NUEVA | BL94: 1 PLAY | BM94: Campaña Promo Mediana | BN94: 89 | BO94: 400MBPS | BP94: NO | BQ94: NO | BR94: Ninguno | BS94: 1 | BU94: =IF($A94<>"", DATE(YEAR($A94),MONTH($A94),DAY($A94)),"") -> 46195 | BV94: =IF($E94<>"",DATE(YEAR($E94),MONTH($E94),DAY($E94)),"") | BW94: =IF($E94<>"",TEXT($E94,"HH"),"") | BZ94: =IF(B94<>"",VALUE(LEFT(B94)),"") -> 0 | CA94: {=IF($A94<>"",INDEX(LISTA!$M$2:$N$27,MATCH($BC94,LISTA!$N$2:$N$27,0),1),"")} -> 24 | CB94: =IF($A94<>"",MONTH(BU94),"") -> 6 | CC94: =IF($BX94<>"",MONTH(BX94),"")
A95: 46204.408 | B95: 7 - INSTALADA | C95: MASIVO RESIDENCIAL | D95: NAYELI | E95: 46204.667 | F95: PROCEDE | G95: 104981811 | H95: 88771950 | I95: YESSENIA | J95: 969711326 | K95: DNI | L95: 41841147 | M95: PRINCIPE DE LA CRUZ, JACKSON ALEJANDRO | N95: 29437 | O95: LIMA METROPOLITANA | P95: 150143 | AF95: Villa María del Triunfo | AQ95: CORNELIO | AR95: VILMA | AS95: jack.principe@gmail.com | AU95: 969711326 | AV95: 969711326 | AW95: urbanizaciòn pachacamac tercera etapa mz y lt 06 villa el salvador | AX95: 2 | AY95: 1 | AZ95: -12.2260794895239, -76.92394627063364 | BA95: av 200 millas | BB95: LMVS108-F | BC95: LIMA METROPOLITANA | BD95: =IF(COUNTA(Q95:AP95)>0,INDEX(Q95:AP95,,max(IF(Q95:AP95<>"",COLUMN(Q95:AP95)))-16),"") -> Villa María del Triunfo | BE95: FTTH | BF95: SI | BG95: ALTA NUEVA | BL95: 2PLAY + TELF | BM95: Campaña Regular | BN95: 94 | BO95: 400MBPS | BP95: NO | BQ95: SI | BR95: Ninguno | BS95: 1 | BU95: =IF($A95<>"", DATE(YEAR($A95),MONTH($A95),DAY($A95)),"") -> 46204 | BV95: =IF($E95<>"",DATE(YEAR($E95),MONTH($E95),DAY($E95)),"") -> 46204 | BW95: =IF($E95<>"",TEXT($E95,"HH"),"") -> 16 | BX95: 46204 | BY95: 1 | BZ95: =IF(B95<>"",VALUE(LEFT(B95)),"") -> 7 | CA95: {=IF($A95<>"",INDEX(LISTA!$M$2:$N$27,MATCH($BC95,LISTA!$N$2:$N$27,0),1),"")} -> 1 | CB95: =IF($A95<>"",MONTH(BU95),"") -> 7 | CC95: =IF($BX95<>"",MONTH(BX95),"") -> 7
A96: 46204.387 | B96: 3 - PROGRAMADA | C96: MASIVO RESIDENCIAL | D96: NAYELI | E96: 46205.375 | F96: PROCEDE NO SE ENCUENTRA PLANO | G96: 104993156 | H96: 88780388 | I96: JUAN DIEGO | J96: 975 669 815 | K96: DNI | L96: 70408073 | M96: LUIS ANGEL SANCHEZ VEREAU | N96: 37242 | O96: LA LIBERTAD | P96: 130101 | AC96: Trujillo | AQ96: Luis | AR96: aracely | AS96: Angeligo1217@gmail.com | AU96: 925181197 | AV96: 975 669 815 | AW96: Mz b lote 12 -urb libertad | AX96: 3 | AY96: NA | AZ96: -8.08906280418708, -78.99615148219792 | BA96: Av. Cam. Real | BB96: TREP001-S | BC96: LA LIBERTAD | BD96: =IF(COUNTA(Q96:AP96)>0,INDEX(Q96:AP96,,max(IF(Q96:AP96<>"",COLUMN(Q96:AP96)))-16),"") -> Trujillo | BE96: FTTH | BF96: NO | BG96: ALTA NUEVA | BL96: 1 PLAY | BM96: Campaña Regular | BN96: 100 | BO96: 800MBPS | BP96: NO | BQ96: NO | BR96: Ninguno | BS96: 2 | BU96: =IF($A96<>"", DATE(YEAR($A96),MONTH($A96),DAY($A96)),"") -> 46204 | BV96: =IF($E96<>"",DATE(YEAR($E96),MONTH($E96),DAY($E96)),"") -> 46205 | BW96: =IF($E96<>"",TEXT($E96,"HH"),"") -> 09 | BZ96: =IF(B96<>"",VALUE(LEFT(B96)),"") -> 3 | CA96: {=IF($A96<>"",INDEX(LISTA!$M$2:$N$27,MATCH($BC96,LISTA!$N$2:$N$27,0),1),"")} -> 15 | CB96: =IF($A96<>"",MONTH(BU96),"") -> 7 | CC96: =IF($BX96<>"",MONTH(BX96),"")
A97: 46204.45 | B97: 3 - PROGRAMADA | C97: MASIVO RESIDENCIAL | D97: NAYELI | E97: 46204.667 | F97: PROCEDE | G97: 104986149 | H97: 88775710 | I97: YESSENIA | J97: 984130492 | K97: DNI | L97: 42854321 | M97: ANALIZ VANESSA QUISPE ARAPA | N97: 31058 | O97: PUNO | P97: 210101 | T97: Arequipa | AQ97: JESUS | AR97: MARTHA | AS97: analizarteaga0408@gmail.com | AU97: 984130492 | AV97: 984130492 | AW97: analizarteaga0408@gmail.com | AX97: 5 | AY97: 1 | AZ97: -16.438452,-71.559963 | BA97: av las americas | BB97: AQHU019-S | BC97: AREQUIPA | BD97: =IF(COUNTA(Q97:AP97)>0,INDEX(Q97:AP97,,max(IF(Q97:AP97<>"",COLUMN(Q97:AP97)))-16),"") -> Arequipa | BE97: FTTH | BF97: NO | BG97: ALTA NUEVA | BL97: 2PLAY + TELF | BM97: Campaña Regular | BN97: 94 | BO97: 400MBPS | BP97: NO | BQ97: SI | BR97: Ninguno | BS97: 1 | BU97: =IF($A97<>"", DATE(YEAR($A97),MONTH($A97),DAY($A97)),"") -> 46204 | BV97: =IF($E97<>"",DATE(YEAR($E97),MONTH($E97),DAY($E97)),"") -> 46204 | BW97: =IF($E97<>"",TEXT($E97,"HH"),"") -> 16 | BZ97: =IF(B97<>"",VALUE(LEFT(B97)),"") -> 3 | CA97: {=IF($A97<>"",INDEX(LISTA!$M$2:$N$27,MATCH($BC97,LISTA!$N$2:$N$27,0),1),"")} -> 7 | CB97: =IF($A97<>"",MONTH(BU97),"") -> 7 | CC97: =IF($BX97<>"",MONTH(BX97),"")
A98: 46204.555 | B98: 3 - PROGRAMADA | C98: MASIVO RESIDENCIAL | D98: NAYELI | E98: 46205.375 | F98: PROCEDE | G98: 104992735 | H98: 88779992 | I98: ANGHELL | J98: 988653785 | K98: DNI | L98: 29625180 | M98: ROSA CANDELARIA GOMEZ GONZALES | N98: 25815 | O98: APURIMAC | P98: 030405 | T98: Arequipa | AQ98: calixto | AR98: fortunata | AS98: gliz64300@gmail.com | AU98: 988653785 | AV98: 988653785 | AW98: calle gamaliel churata mz c1 lt a4 urb paisajista | AX98: 2 | AY98: na | AZ98: -16.457434391502236, -71.55459055521064 | BA98: calle jose maria arguedas | BB98: AQHU017 | BC98: AREQUIPA | BD98: =IF(COUNTA(Q98:AP98)>0,INDEX(Q98:AP98,,max(IF(Q98:AP98<>"",COLUMN(Q98:AP98)))-16),"") -> Arequipa | BE98: HFC | BF98: NO | BG98: ALTA NUEVA | BL98: 1 PLAY | BM98: Campaña Regular | BN98: 44 | BO98: 150MBPS | BP98: NO | BQ98: NO | BR98: Ninguno | BS98: Ninguno | BU98: =IF($A98<>"", DATE(YEAR($A98),MONTH($A98),DAY($A98)),"") -> 46204 | BV98: =IF($E98<>"",DATE(YEAR($E98),MONTH($E98),DAY($E98)),"") -> 46205 | BW98: =IF($E98<>"",TEXT($E98,"HH"),"") -> 09 | BZ98: =IF(B98<>"",VALUE(LEFT(B98)),"") -> 3 | CA98: {=IF($A98<>"",INDEX(LISTA!$M$2:$N$27,MATCH($BC98,LISTA!$N$2:$N$27,0),1),"")} -> 7 | CB98: =IF($A98<>"",MONTH(BU98),"") -> 7 | CC98: =IF($BX98<>"",MONTH(BX98),"")
A99: 46204.37 | B99: 0 - NO CONTESTA | C99: MASIVO RESIDENCIAL | F99: CL QUIERE DECO | I99: JUAN DIEGO | J99: 997473584 | K99: DNI | L99: 44031141 | M99: ERIKA NEDA ENRIQUEZ CHURA | N99: 31702 | O99: CUSCO | P99: 080101 | AF99: Rimac | AQ99: ISIDRO | AR99: BARBARA | AS99: akire1430@hotmail.com | AU99: 997473584 | AV99: 997473584 | AW99: Calle Antares Nte. 474 Rimac | AX99: 3 | AY99: NA | AZ99: -12.027606290743691, -77.03682097494125 | BA99: AVENIDA GUARDIA REPUBLICANA | BB99: LMRC018-S | BC99: LIMA METROPOLITANA | BD99: =IF(COUNTA(Q99:AP99)>0,INDEX(Q99:AP99,,max(IF(Q99:AP99<>"",COLUMN(Q99:AP99)))-16),"") -> Rimac | BE99: FTTH | BF99: SI | BG99: ALTA NUEVA | BL99: 2PLAY + TELF | BM99: Campaña Regular | BN99: 94 | BO99: 400MBPS | BP99: NO | BQ99: SI | BR99: Ninguno | BS99: 1 | BU99: =IF($A99<>"", DATE(YEAR($A99),MONTH($A99),DAY($A99)),"") -> 46204 | BV99: =IF($E99<>"",DATE(YEAR($E99),MONTH($E99),DAY($E99)),"") | BW99: =IF($E99<>"",TEXT($E99,"HH"),"") | BZ99: =IF(B99<>"",VALUE(LEFT(B99)),"") -> 0 | CA99: {=IF($A99<>"",INDEX(LISTA!$M$2:$N$27,MATCH($BC99,LISTA!$N$2:$N$27,0),1),"")} -> 1 | CB99: =IF($A99<>"",MONTH(BU99),"") -> 7 | CC99: =IF($BX99<>"",MONTH(BX99),"")
A100: 46204.496 | B100: 0 - GRABADO | C100: MASIVO RESIDENCIAL | D100: NAYELI | F100: GRABADO/PNDT CREAR SOT | G100: 104988933 | I100: JUAN DIEGO | J100: 937 073 497 | K100: DNI | L100: 43268116 | M100: CARMEN DEL ROSARIO ARISPE PINELO | N100: 31298 | O100: AREQUIPA | P100: 040101 | T100: Arequipa | AQ100: HENRY | AR100: NILA | AS100: Carmen.arispe.pineli@gmail.com | AU100: 937 073 497 | AV100: 937 073 497 | AW100: URB RAFEL HOYOS RUBIO MZ A LT16 | AX100: 2 | AY100: NA | AZ100: -16.374931, -71.51744 | BA100: PARQUE DE LA JUVENTUD | BB100: AQSA006-S | BC100: AREQUIPA | BD100: =IF(COUNTA(Q100:AP100)>0,INDEX(Q100:AP100,,max(IF(Q100:AP100<>"",COLUMN(Q100:AP100)))-16),"") -> Arequipa | BE100: FTTH | BF100: SI | BG100: ALTA NUEVA | BL100: 2PLAY + TELF | BM100: Campaña Regular | BN100: 94 | BO100: 400MBPS | BP100: NO | BQ100: SI | BR100: Ninguno | BS100: 1 | BU100: =IF($A100<>"", DATE(YEAR($A100),MONTH($A100),DAY($A100)),"") -> 46204 | BV100: =IF($E100<>"",DATE(YEAR($E100),MONTH($E100),DAY($E100)),"") | BW100: =IF($E100<>"",TEXT($E100,"HH"),"") | BZ100: =IF(B100<>"",VALUE(LEFT(B100)),"") -> 0 | CA100: {=IF($A100<>"",INDEX(LISTA!$M$2:$N$27,MATCH($BC100,LISTA!$N$2:$N$27,0),1),"")} -> 7 | CB100: =IF($A100<>"",MONTH(BU100),"") -> 7 | CC100: =IF($BX100<>"",MONTH(BX100),"")
...

Sheet PREVENTAS
A1: Marca temporal | B1: STATUS | C1: SEGMENTO | D1: ASESOR BO | E1: PROGRAMACION BO | F1: COMENTARIOS BO | G1: SEC | H1: SOT | I1: ASESOR | J1: LEAD | K1: TIPO DOCUMENTO | L1: N° DOCUMENTO | M1: NOMBRE COMPLETO CLIENTE | N1: FECHA NACIMIENTO | O1: LUGAR NACIMIENTO | P1: UBIGEO | Q1: AMAZONAS | R1: ANCASH | S1: APURIMAC | T1: AREQUIPA | U1: AYACUCHO | V1: CAJAMARCA | W1: CALLAO | X1: CUSCO | Y1: HUANCAVELICA | Z1: HUANUCO | AA1: ICA | AB1: JUNIN | AC1: LA LIBERTAD | AD1: LAMBAYEQUE | AE1: LIMA | AF1: LIMA METROPOLITANA | AG1: LORETO | AH1: MADRE DE DIOS | AI1: MOQUEGUA | AJ1: PASCO | AK1: PIURA | AL1: PUNO | AM1: SAN MARTIN | AN1: TACNA | AO1: TUMBES | AP1: UCAYALI | AQ1: NOMBRE PADRE | AR1: NOMBRE MADRE | AS1: CORREO ELECTRONICO | AT1: TELF REGISTRO | AU1: TELF GRABACION | AV1: TELF REFERENCIA | AW1: DIRECCION INSTALACION | AX1: PISO | AY1: INTERIOR | AZ1: COORDENADAS | BA1: REFERENCIAS | BB1: PLANO | BC1: DEPARTAMENTO | BD1: PROV / DISTRITO | BE1: TECNOLOGIA | BF1: FULL CLARO | BG1: OPERACION | BH1: OPERADOR ORIGEN | BI1: TELF A PORTAR | BJ1: MODALIDAD | BK1: TIPO SERVICIO | BL1: SERVICIO A CONTRATAR | BM1: OFERTA COMERCIAL ALTA NUEVA | BN1: PRECIO REGULAR | BO1: VELOCIDAD PLAN | BP1: LIGA1 MAX | BQ1: TELEFONO | BR1: N° DECODIFICADORES | BS1: N° MESH | BT1: FECHA INSTALACIÓN | BU1: ORDEN INSTALACION | BV1: FECHA REGISTRO | BW1: FECHA PROGRAMACION | BX1: TRAMO PROGRAMACION | BY1: COD STATUS | BZ1: COD DPTO | CA1: MES REG | CB1: MES INSTAL | CC1: CUSTOMER ID
A2: 46179.52 | B2: 5 - INSTALADA | C2: MASIVO RESIDENCIAL | D2: NAYELI | E2: 46185.583 | F2: LYBTEL | G2: 104457724 | H2: 88271126 | I2: ROCIO | J2: 998357850 | K2: DNI | L2: 43729341 | M2: HUGO HERRERA NUÑEZ | N2: 31658 | O2: LIMA | P2: 150131 | AF2: Santiago de Surco | AQ2: HUGO | AR2: MARIA | AS2: jnunezo@hotmail.es | AT2: 997351175 | AU2: 997351175 | AV2: 997351175 | AW2: ayacucho 942 santiago de surco dto 402 | AX2: 4 | AY2: 402 | AZ2: -12.136189335877416, -76.99837869182522 | BA2: AV DOñA RAQUEL | BB2: LMSC293-F | BC2: LIMA METROPOLITANA | BD2: =IF(COUNTA(Q2:AP2)>0,INDEX(Q2:AP2,,max(IF(Q2:AP2<>"",COLUMN(Q2:AP2)))-16),"") -> Santiago de Surco | BE2: FTTH | BF2: NO | BG2: ALTA NUEVA | BL2: 2 PLAY + TV ESTANDAR | BM2: Campaña Regular | BN2: 170 | BO2: 400MBPS | BP2: NO | BQ2: NO | BR2: Ninguno | BS2: Ninguno | BT2: 46185 | BU2: 1 | BV2: =IF($A2<>"", DATE(YEAR($A2),MONTH($A2),DAY($A2)),"") -> 46179 | BW2: =IF($E2<>"",DATE(YEAR($E2),MONTH($E2),DAY($E2)),"") -> 46185 | BX2: =IF($E2<>"",TEXT($E2,"HH"),"") -> 14 | BY2: =IF(B2<>"",VALUE(LEFT(B2)),"") -> 5 | BZ2: {=IF($A2<>"",INDEX(LISTA!$M$2:$N$27,MATCH($BC2,LISTA!$N$2:$N$27,0),1),"")} -> 1 | CA2: =IF($A2<>"",MONTH(BV2),"") -> 6 | CB2: =IF($BT2<>"",MONTH(BT2),"") -> 6 | CC2: 57896117
A3: 46184.543 | B3: 5 - INSTALADA | C3: MASIVO RESIDENCIAL | D3: NAYELI | E3: 46185.667 | F3: LYBTEL | G3: 104449975 | H3: 88267394 | I3: ROCIO | J3: 985871277 | K3: DNI | L3: 43252312 | M3: SUSAN IVONNE HEREDIA CORDOVA | N3: 31371 | O3: JUNIN | P3: 110101 | AF3: San Martín de Porres | AQ3: luis | AR3: lucila | AS3: Gabycina@hotmail.com | AT3: 985871277 | AU3: 985871277 | AV3: 985871277 | AW3: Urb.San german Jr Ávila Godoy 657 | AX3: 4 | AY3: 1 | AZ3: -12.015793, -77.071245 | BA3: ingreso es por el jardín inicial Germancito | BB3: LMMP233-F | BC3: LIMA METROPOLITANA | BD3: =IF(COUNTA(Q3:AP3)>0,INDEX(Q3:AP3,,max(IF(Q3:AP3<>"",COLUMN(Q3:AP3)))-16),"") -> San Martín de Porres | BE3: FTTH | BF3: SI | BG3: ALTA NUEVA | BL3: 1 PLAY | BM3: Campaña Regular | BN3: 110 | BO3: 500MBPS | BP3: SI | BQ3: NO | BR3: Ninguno | BS3: 1 | BT3: 46186 | BU3: 1 | BV3: =IF($A3<>"", DATE(YEAR($A3),MONTH($A3),DAY($A3)),"") -> 46184 | BW3: =IF($E3<>"",DATE(YEAR($E3),MONTH($E3),DAY($E3)),"") -> 46185 | BX3: =IF($E3<>"",TEXT($E3,"HH"),"") -> 16 | BY3: =IF(B3<>"",VALUE(LEFT(B3)),"") -> 5 | BZ3: {=IF($A3<>"",INDEX(LISTA!$M$2:$N$27,MATCH($BC3,LISTA!$N$2:$N$27,0),1),"")} -> 1 | CA3: =IF($A3<>"",MONTH(BV3),"") -> 6 | CB3: =IF($BT3<>"",MONTH(BT3),"") -> 6 | CC3: 57895552
A4: 46190.379 | B4: 5 - INSTALADA | C4: MASIVO RESIDENCIAL | D4: NAYELI | E4: 46191.583 | F4: PROCEDE/ EDIFICIO HABILITADO | G4: 104605460 | H4: 88405389 | I4: JESSICA | J4: 987579907 | K4: DNI | L4: 70350550 | M4: CLAUDIA ISABEL GIL VIDAL | N4: 33362 | O4: LIMA | P4: 140115 | AF4: Miraflores | AQ4: FERNANDO HUMBERTO | AR4: IRMA BETTY | AS4: cgilvidal@gmail.com | AT4: 987579907 | AU4: 987579907 | AV4: 987579907 | AW4: AVENIDA PASEO DE LA REPUBLICA 6373 URBANIZACION SAN ANTONIO | AX4: 16 | AY4: 1601 | AZ4: -12.132422, -77.021475 | BA4: VIA EXPRESA LUIS FERNAN BEDOYA REYES | BB4: LMMF083 | BC4: LIMA METROPOLITANA | BD4: =IF(COUNTA(Q4:AP4)>0,INDEX(Q4:AP4,,max(IF(Q4:AP4<>"",COLUMN(Q4:AP4)))-16),"") -> Miraflores | BE4: HFC | BF4: SI | BG4: ALTA NUEVA | BL4: 1 PLAY + L1MAX | BM4: Campaña Regular PRO | BN4: 110 | BO4: 500MBPS | BP4: SI | BQ4: NO | BR4: Ninguno | BS4: Ninguno | BT4: 46191 | BU4: 1 | BV4: =IF($A4<>"", DATE(YEAR($A4),MONTH($A4),DAY($A4)),"") -> 46190 | BW4: =IF($E4<>"",DATE(YEAR($E4),MONTH($E4),DAY($E4)),"") -> 46191 | BX4: =IF($E4<>"",TEXT($E4,"HH"),"") -> 14 | BY4: =IF(B4<>"",VALUE(LEFT(B4)),"") -> 5 | BZ4: {=IF($A4<>"",INDEX(LISTA!$M$2:$N$27,MATCH($BC4,LISTA!$N$2:$N$27,0),1),"")} -> 1 | CA4: =IF($A4<>"",MONTH(BV4),"") -> 6 | CB4: =IF($BT4<>"",MONTH(BT4),"") -> 6 | CC4: 57934319
A5: 46190.494 | B5: 5 - INSTALADA | C5: MASIVO RESIDENCIAL | D5: PAOLA | E5: 46193.458 | F5: LLAMAR 12:30 | G5: 104649549 | H5: 88437602 | I5: PAOLA | J5: 915992860 | K5: DNI | L5: 40537157 | M5: JOHANA MEDALITH MELENDEZ CHINGA | N5: 29369 | O5: LIMA | P5: 140101 | AE5: Huaura | AQ5: JULIO | AR5: ELENA | AS5: RICHARDTJ_3@HOTMAIL.COM | AT5: 963877220 | AU5: 963877220 | AV5: 915992860 | AW5: Urb Martir Jose Olaya mz g lote 12 | AX5: 2 | AY5: NA | AZ5: -11.09480528124759, -77.62592378552375 | BA5: JR 28 OCTUBRE | BB5: LMCQ002 | BC5: LIMA | BD5: =IF(COUNTA(Q5:AP5)>0,INDEX(Q5:AP5,,max(IF(Q5:AP5<>"",COLUMN(Q5:AP5)))-16),"") -> Huaura | BE5: HFC | BF5: SI | BG5: ALTA NUEVA | BL5: 1 PLAY | BM5: Campaña Regular | BN5: 110 | BO5: 500MBPS | BP5: NO | BQ5: NO | BR5: 1 | BS5: 1 | BT5: 46192 | BU5: 1 | BV5: =IF($A5<>"", DATE(YEAR($A5),MONTH($A5),DAY($A5)),"") -> 46190 | BW5: =IF($E5<>"",DATE(YEAR($E5),MONTH($E5),DAY($E5)),"") -> 46193 | BX5: =IF($E5<>"",TEXT($E5,"HH"),"") -> 11 | BY5: =IF(B5<>"",VALUE(LEFT(B5)),"") -> 5 | BZ5: {=IF($A5<>"",INDEX(LISTA!$M$2:$N$27,MATCH($BC5,LISTA!$N$2:$N$27,0),1),"")} -> 3 | CA5: =IF($A5<>"",MONTH(BV5),"") -> 6 | CB5: =IF($BT5<>"",MONTH(BT5),"") -> 6 | CC5: 57946138
A6: 46192.657 | B6: 5 - INSTALADA | C6: MASIVO RESIDENCIAL | D6: PAOLA | E6: 46193.458 | F6: SE MANDA A ANULAR SOT LOS DATOS DE DIRECCIÓN ES INCORRECTO/ CORREGIDO | G6: 104692164 | H6: 88475969 | I6: SAHIR | J6: 995048683 | K6: DNI | L6: 43379508 | M6: JULIO RAMON CHUNG GONZALES | N6: 31436 | O6: LIMA METROPOLITANA | P6: 150121 | AF6: Lince | AQ6: luis fernando | AR6: elvira marina | AS6: julianchungonzales@gmail.com | AT6: 995048683 | AU6: 995048683 | AV6: 995048683 | AW6: JIRON INCA GARCILASO DE LA VEGA 1874 URBANIZACION RISSO LINCE | AX6: 1 | AY6: 1 | AZ6: -12.084034, -77.040746 | BA6: av canebaro | BB6: LMLC077-F | BC6: LIMA METROPOLITANA | BD6: =IF(COUNTA(Q6:AP6)>0,INDEX(Q6:AP6,,max(IF(Q6:AP6<>"",COLUMN(Q6:AP6)))-16),"") -> Lince | BE6: FTTH | BF6: SI | BG6: ALTA NUEVA | BL6: 2PLAY + TELF | BM6: Campaña Regular | BN6: 94 | BO6: 400MBPS | BP6: NO | BQ6: SI | BR6: Ninguno | BS6: 1 | BT6: 46194 | BU6: 1 | BV6: =IF($A6<>"", DATE(YEAR($A6),MONTH($A6),DAY($A6)),"") -> 46192 | BW6: =IF($E6<>"",DATE(YEAR($E6),MONTH($E6),DAY($E6)),"") -> 46193 | BX6: =IF($E6<>"",TEXT($E6,"HH"),"") -> 11 | BY6: =IF(B6<>"",VALUE(LEFT(B6)),"") -> 5 | BZ6: {=IF($A6<>"",INDEX(LISTA!$M$2:$N$27,MATCH($BC6,LISTA!$N$2:$N$27,0),1),"")} -> 1 | CA6: =IF($A6<>"",MONTH(BV6),"") -> 6 | CB6: =IF($BT6<>"",MONTH(BT6),"") -> 6 | CC6: 57955168
A7: 46193.5 | B7: 5 - INSTALADA | C7: MASIVO RESIDENCIAL | D7: PAOLA | E7: 46195.458 | F7: no coincide | G7: 104449975 | H7: 88480813 | I7: ANGHELL | J7: 977370315 | K7: DNI | L7: 75081907 | M7: MANUEL ALDAYR MONTUFAR LAIME | N7: 37189 | O7: CUSCO | P7: 07081 | X7: Espinar | AQ7: MANUEL | AR7: FILOMENA | AS7: AQPFEX1@GMAIL.COM | AT7: 977370315 | AU7: 977370315 | AV7: 977370315 | AW7: ubr huarcanto mz a1 lt 17 | AX7: 2 | AY7: 2A | AZ7: -14.799989, -71.411517 | BA7: calle nueva baja | BB7: CZES020-F | BC7: CUSCO | BD7: =IF(COUNTA(Q7:AP7)>0,INDEX(Q7:AP7,,max(IF(Q7:AP7<>"",COLUMN(Q7:AP7)))-16),"") -> Espinar | BE7: FTTH | BF7: NO | BG7: ALTA NUEVA | BL7: 2PLAY + TELF | BM7: Campaña Relámpago | BN7: 94 | BO7: 400MBPS | BP7: NO | BQ7: SI | BR7: Ninguno | BS7: Ninguno | BT7: 46194 | BU7: 2 | BV7: =IF($A7<>"", DATE(YEAR($A7),MONTH($A7),DAY($A7)),"") -> 46193 | BW7: =IF($E7<>"",DATE(YEAR($E7),MONTH($E7),DAY($E7)),"") -> 46195 | BX7: =IF($E7<>"",TEXT($E7,"HH"),"") -> 11 | BY7: =IF(B7<>"",VALUE(LEFT(B7)),"") -> 5 | BZ7: {=IF($A7<>"",INDEX(LISTA!$M$2:$N$27,MATCH($BC7,LISTA!$N$2:$N$27,0),1),"")} -> 10 | CA7: =IF($A7<>"",MONTH(BV7),"") -> 6 | CB7: =IF($BT7<>"",MONTH(BT7),"") -> 6 | CC7: 57959805
A8: 46190.704 | B8: 5 - INSTALADA | C8: MASIVO RESIDENCIAL | D8: NAYELI | E8: 46196.583 | F8: PROCEDE | G8: 104715891 | H8: 88485225 | I8: JULIANA | J8: 960791381 | K8: DNI | L8: 72187246 | M8: MARIA DEL CARMEN SALAZAR JUUYPA | N8: 36141 | O8: AREQUIPA | P8: 912817 | T8: Arequipa | AQ8: VICTOR | AR8: GABRIELA | AS8: SALAZARMADECA@GMAIL.COM | AT8: 960791381 | AU8: 960791381 | AV8: 960791381 | AW8: AV. LOS BOSQUES PASAJE LOS MANGLARES MZ CH LOTE 2, LA CAMPIÑA, SOCABAYA. | AX8: 3 | AY8: 1 | AZ8: -16.45931970461676, -71.52429812641768 | BA8: ESPALDA DEL COLEGIO LA CAMPIÑA | BB8: AQSB022 | BC8: AREQUIPA | BD8: =IF(COUNTA(Q8:AP8)>0,INDEX(Q8:AP8,,max(IF(Q8:AP8<>"",COLUMN(Q8:AP8)))-16),"") -> Arequipa | BE8: HFC | BF8: SI | BG8: ALTA NUEVA | BL8: 1 PLAY | BM8: Campaña Regular | BN8: 89 | BO8: 400MBPS | BP8: NO | BQ8: NO | BR8: Ninguno | BS8: Ninguno | BT8: 46195 | BU8: 1 | BV8: =IF($A8<>"", DATE(YEAR($A8),MONTH($A8),DAY($A8)),"") -> 46190 | BW8: =IF($E8<>"",DATE(YEAR($E8),MONTH($E8),DAY($E8)),"") -> 46196 | BX8: =IF($E8<>"",TEXT($E8,"HH"),"") -> 14 | BY8: =IF(B8<>"",VALUE(LEFT(B8)),"") -> 5 | BZ8: {=IF($A8<>"",INDEX(LISTA!$M$2:$N$27,MATCH($BC8,LISTA!$N$2:$N$27,0),1),"")} -> 7 | CA8: =IF($A8<>"",MONTH(BV8),"") -> 6 | CB8: =IF($BT8<>"",MONTH(BT8),"") -> 6 | CC8: 57962165
A9: 46193.413 | B9: 5 - INSTALADA | C9: MASIVO RESIDENCIAL | D9: PAOLA | E9: 46196.458 | F9: PROCEDE ERROR EN DIRECCION | G9: 104714476 | H9: 88484483 | I9: YESSENIA | J9: 937542448 | K9: DNI | L9: 74602108 | M9: BRYAN ALFREDO MOREANO OBANDO | N9: 35956 | O9: CALLAO | P9: 070103 | AF9: La Victoria | AQ9: ALFREDO | AR9: MARITA | AS9: bmoreanoo@gmail.com | AT9: 937542448 | AU9: 937542448 | AV9: 937542448 | AW9: Jr. Carlos Gutiérrez Noriega 480 | AX9: 5 | AY9: 504 | AZ9: -12.07782297,-77.01624108 | BA9: JR CARLOS LOPEZ ALDANA | BB9: LMLV009-S | BC9: LIMA METROPOLITANA | BD9: =IF(COUNTA(Q9:AP9)>0,INDEX(Q9:AP9,,max(IF(Q9:AP9<>"",COLUMN(Q9:AP9)))-16),"") -> La Victoria | BE9: FTTH | BF9: NO | BG9: ALTA NUEVA | BL9: 1 PLAY | BM9: Campaña Promo Mediana | BN9: 89 | BO9: 400MBPS | BP9: NO | BQ9: NO | BR9: Ninguno | BS9: 1 | BT9: 46196 | BU9: 1 | BV9: =IF($A9<>"", DATE(YEAR($A9),MONTH($A9),DAY($A9)),"") -> 46193 | BW9: =IF($E9<>"",DATE(YEAR($E9),MONTH($E9),DAY($E9)),"") -> 46196 | BX9: =IF($E9<>"",TEXT($E9,"HH"),"") -> 11 | BY9: =IF(B9<>"",VALUE(LEFT(B9)),"") -> 5 | BZ9: {=IF($A9<>"",INDEX(LISTA!$M$2:$N$27,MATCH($BC9,LISTA!$N$2:$N$27,0),1),"")} -> 1 | CA9: =IF($A9<>"",MONTH(BV9),"") -> 6 | CB9: =IF($BT9<>"",MONTH(BT9),"") -> 6 | CC9: 57961785
A10: 46195.509 | B10: 5 - INSTALADA | C10: MASIVO RESIDENCIAL | D10: NAYELI | E10: 46196.458 | F10: PROCEDE AXB | G10: 104742955 | H10: 88519977 | I10: JESSICA | J10: 935195970 | K10: DNI | L10: 42520693 | M10: MARCO ANTONIO JAMANCA ESPINOZA | N10: 30888 | O10: ANCASH | P10: 020101 | R10: Huaraz | AQ10: DIONICIO | AR10: EUGENIA MARCELA | AS10: Marcojmanca@gmail.com | AT10: 935195970 | AU10: 935195970 | AV10: 935195970 | AW10: PS. SANTO DOMINGO 120 | AX10: 3 | AY10: 1 | AZ10: -9.508119659146413, -77.5320333439741 | BA10: JIRON INDUSTRIAL | BB10: HZIN044-F | BC10: ANCASH | BD10: =IF(COUNTA(Q10:AP10)>0,INDEX(Q10:AP10,,max(IF(Q10:AP10<>"",COLUMN(Q10:AP10)))-16),"") -> Huaraz | BE10: FTTH | BF10: NO | BG10: ALTA NUEVA | BL10: 1 PLAY | BM10: Campaña Regular PRO | BN10: 110 | BO10: 500MBPS | BP10: SI | BQ10: NO | BR10: Ninguno | BS10: 1 | BT10: 46196 | BU10: 2 | BV10: =IF($A10<>"", DATE(YEAR($A10),MONTH($A10),DAY($A10)),"") -> 46195 | BW10: =IF($E10<>"",DATE(YEAR($E10),MONTH($E10),DAY($E10)),"") -> 46196 | BX10: =IF($E10<>"",TEXT($E10,"HH"),"") -> 11 | BY10: =IF(B10<>"",VALUE(LEFT(B10)),"") -> 5 | BZ10: {=IF($A10<>"",INDEX(LISTA!$M$2:$N$27,MATCH($BC10,LISTA!$N$2:$N$27,0),1),"")} -> 5 | CA10: =IF($A10<>"",MONTH(BV10),"") -> 6 | CB10: =IF($BT10<>"",MONTH(BT10),"") -> 6 | CC10: 57966743
A11: 46196.508 | B11: 5 - INSTALADA | C11: MASIVO RESIDENCIAL | D11: NAYELI | E11: 46197.458 | F11: PAGO DE INSTALACION - CLIENTE ADELANTA VISITA 24/06 | G11: 104776353 | H11: 88565685 | I11: JUAN DIEGO | J11: 970168191 | K11: DNI | L11: 47430926 | M11: ELIZABETH CRISTINA BARRIENTOS OROSCO | N11: 33581 | O11: LIMA METROPOLITANA | P11: 150133 | AF11: Ate | AQ11: SEBASTIAN | AR11: GLORIA | AS11: eduorosco3@gmail.com | AT11: 970168191 | AU11: 970168191 | AV11: 999222641 | AW11: mz g lt 06 URBANIZACIÓN LAS PRADERAS DE PARIACHI tercera etapa | AX11: 2 | AY11: 0 | AZ11: -12.00525274093723, -76.8413549302252 | BA11: AV POSEIDON | BB11: LMAT142-F | BC11: LIMA METROPOLITANA | BD11: =IF(COUNTA(Q11:AP11)>0,INDEX(Q11:AP11,,max(IF(Q11:AP11<>"",COLUMN(Q11:AP11)))-16),"") -> Ate | BE11: FTTH | BF11: NO | BG11: ALTA NUEVA | BL11: 1 PLAY | BM11: Campaña Regular | BN11: 100 | BO11: 800MBPS | BP11: NO | BQ11: NO | BR11: Ninguno | BS11: 2 | BT11: 46197 | BU11: 1 | BV11: =IF($A11<>"", DATE(YEAR($A11),MONTH($A11),DAY($A11)),"") -> 46196 | BW11: =IF($E11<>"",DATE(YEAR($E11),MONTH($E11),DAY($E11)),"") -> 46197 | BX11: =IF($E11<>"",TEXT($E11,"HH"),"") -> 11 | BY11: =IF(B11<>"",VALUE(LEFT(B11)),"") -> 5 | BZ11: {=IF($A11<>"",INDEX(LISTA!$M$2:$N$27,MATCH($BC11,LISTA!$N$2:$N$27,0),1),"")} -> 1 | CA11: =IF($A11<>"",MONTH(BV11),"") -> 6 | CB11: =IF($BT11<>"",MONTH(BT11),"") -> 6 | CC11: 57976322
A12: 46196.789 | B12: 5 - INSTALADA | C12: MASIVO RESIDENCIAL | D12: PAOLA | E12: 46197.458 | F12: PROCEDE | G12: 104793755 | H12: 88574820 | I12: GABRIEL | J12: 959579554 | K12: DNI | L12: 72000616 | M12: KARELIA BEATRIZ GAVILAN PURILLA | N12: 33908 | O12: ICA | P12: 110101 | AA12: Ica | AQ12: Javier | AR12: Nancy | AS12: kareliagp.gp@gmail.com | AT12: 959579554 | AU12: 959579554 | AV12: 959579554 | AW12: Av pachacutec yupanqui 986 parcona , ica , ica | AX12: 1 | AY12: S/I | AZ12: -14.04519699, -75.70771398 | BA12: CADIMOTORS/MOTO REPUESTOS Y TALLER | BB12: ICPN008 | BC12: ICA | BD12: =IF(COUNTA(Q12:AP12)>0,INDEX(Q12:AP12,,max(IF(Q12:AP12<>"",COLUMN(Q12:AP12)))-16),"") -> Ica | BE12: HFC | BF12: NO | BG12: ALTA NUEVA | BL12: 1 PLAY | BM12: Campaña Promo Mediana | BN12: 89 | BO12: 400MBPS | BP12: NO | BQ12: NO | BR12: Ninguno | BS12: Ninguno | BT12: 46197 | BU12: 2 | BV12: =IF($A12<>"", DATE(YEAR($A12),MONTH($A12),DAY($A12)),"") -> 46196 | BW12: =IF($E12<>"",DATE(YEAR($E12),MONTH($E12),DAY($E12)),"") -> 46197 | BX12: =IF($E12<>"",TEXT($E12,"HH"),"") -> 11 | BY12: =IF(B12<>"",VALUE(LEFT(B12)),"") -> 5 | BZ12: {=IF($A12<>"",INDEX(LISTA!$M$2:$N$27,MATCH($BC12,LISTA!$N$2:$N$27,0),1),"")} -> 13 | CA12: =IF($A12<>"",MONTH(BV12),"") -> 6 | CB12: =IF($BT12<>"",MONTH(BT12),"") -> 6 | CC12: 57980272
A13: 46190.47 | B13: 5 - INSTALADA | C13: MASIVO RESIDENCIAL | D13: OTRO | E13: 46198.375 | F13: CONFIRMA VISITA /Rechazado por mala oferta - Campo - SE MANDO A LEVANTAR LA SOT | G13: 104610174 | H13: 88407642 | I13: JESSICA | J13: 993793126 | K13: DNI | L13: 06063811 | M13: ALEJANDRO ENRIQUE PALOMINO LEON | N13: 21472 | O13: JUNIN | P13: 110101 | AF13: Rimac | AQ13: ADALBERTO | AR13: OLGA | AS13: abogadopalomino@hotmail.com | AT13: 993793126 | AU13: 993793126 | AV13: 993793126 | AW13: PASAJE CENTRAL 123 | AX13: 4 | AY13: 401 | AZ13: -12.030148683042182, -77.04209244735932 | BA13: NEGOCIOS Y SERVICIOS D. ALCANTARA | BB13: LMRC044-F | BC13: LIMA METROPOLITANA | BD13: =IF(COUNTA(Q13:AP13)>0,INDEX(Q13:AP13,,max(IF(Q13:AP13<>"",COLUMN(Q13:AP13)))-16),"") -> Rimac | BE13: FTTH | BF13: SI | BG13: ALTA NUEVA | BL13: 1 PLAY + L1MAX | BM13: Campaña Regular PRO | BN13: 110 | BO13: 500MBPS | BP13: SI | BQ13: NO | BR13: Ninguno | BS13: 1 | BT13: 46198 | BU13: 1 | BV13: =IF($A13<>"", DATE(YEAR($A13),MONTH($A13),DAY($A13)),"") -> 46190 | BW13: =IF($E13<>"",DATE(YEAR($E13),MONTH($E13),DAY($E13)),"") -> 46198 | BX13: =IF($E13<>"",TEXT($E13,"HH"),"") -> 09 | BY13: =IF(B13<>"",VALUE(LEFT(B13)),"") -> 5 | BZ13: {=IF($A13<>"",INDEX(LISTA!$M$2:$N$27,MATCH($BC13,LISTA!$N$2:$N$27,0),1),"")} -> 1 | CA13: =IF($A13<>"",MONTH(BV13),"") -> 6 | CB13: =IF($BT13<>"",MONTH(BT13),"") -> 6 | CC13: 57935387
A14: 46198.421 | B14: 5 - INSTALADA | C14: MASIVO RESIDENCIAL | D14: NAYELI | E14: 46198.667 | F14: PROCEDE CL QUIERE PARA HOY SI O SI | G14: 104828763 | H14: 88612463 | I14: JESSICA | J14: 936888423 | K14: DNI | L14: 47139933 | M14: RICHARDSON LUIS CORDOVA RIVERA | N14: 33617 | O14: PASCO | P14: 180114 | AB14: Chanchamayo | AQ14: LUIS ALBERTO | AR14: NELLY GLADYS | AS14: richi_cr_92@hotmail.com | AT14: 936888423 | AU14: 936888423 | AV14: 936888423 | AW14: JR. LAS DUNAS 130 | AX14: 2 | AY14: NA | AZ14: -12.06481115, -75.22763426 | BA14: PASAJE LAS MESETAS | BB14: JNTB067-F | BC14: JUNIN | BD14: =IF(COUNTA(Q14:AP14)>0,INDEX(Q14:AP14,,max(IF(Q14:AP14<>"",COLUMN(Q14:AP14)))-16),"") -> Chanchamayo | BE14: FTTH | BF14: NO | BG14: ALTA NUEVA | BL14: 1 PLAY | BM14: Campaña Promo Mediana | BN14: 89 | BO14: 400MBPS | BP14: NO | BQ14: NO | BR14: Ninguno | BS14: 1 | BT14: 46198 | BU14: 2 | BV14: =IF($A14<>"", DATE(YEAR($A14),MONTH($A14),DAY($A14)),"") -> 46198 | BW14: =IF($E14<>"",DATE(YEAR($E14),MONTH($E14),DAY($E14)),"") -> 46198 | BX14: =IF($E14<>"",TEXT($E14,"HH"),"") -> 16 | BY14: =IF(B14<>"",VALUE(LEFT(B14)),"") -> 5 | BZ14: {=IF($A14<>"",INDEX(LISTA!$M$2:$N$27,MATCH($BC14,LISTA!$N$2:$N$27,0),1),"")} -> 14 | CA14: =IF($A14<>"",MONTH(BV14),"") -> 6 | CB14: =IF($BT14<>"",MONTH(BT14),"") -> 6 | CC14: 57989727
A15: 46197.502 | B15: 5 - INSTALADA | C15: MASIVO RESIDENCIAL | D15: NAYELI | E15: 46198.583 | F15: CONFIRMA VISITA | G15: 104805604 | H15: 88589466 | I15: JUAN DIEGO | J15: 944551713 | K15: DNI | L15: 42863482 | M15: MARCO ANTONIO BLAS ZUÑIGA | N15: 31111 | O15: LIMA METROPOLITANA | P15: 150113 | AF15: San Juan de Miraflores | AQ15: MANUEL | AR15: BLANCA | AS15: marcoantonioblaszuniga@gmail.com | AT15: 944 551 713 | AU15: 944 551 713 | AV15: 944 551 713 | AW15: Mz 90 lt 12 URB LOS BRILLANTES SAN JUAN DE MIRAFLORES LIMA | AX15: 2 | AY15: NA | AZ15: -12.144510048064456, -76.96690070477077 | BA15: AVENIDA CENTRAL CON PASAJE SANTA ROSA | BB15: LMJR114-F | BC15: LIMA METROPOLITANA | BD15: =IF(COUNTA(Q15:AP15)>0,INDEX(Q15:AP15,,max(IF(Q15:AP15<>"",COLUMN(Q15:AP15)))-16),"") -> San Juan de Miraflores | BE15: FTTH | BF15: SI | BG15: ALTA NUEVA | BL15: 2PLAY + TELF | BM15: Campaña Regular | BN15: 94 | BO15: 400MBPS | BP15: NO | BQ15: SI | BR15: Ninguno | BS15: 1 | BT15: 46198 | BU15: 3 | BV15: =IF($A15<>"", DATE(YEAR($A15),MONTH($A15),DAY($A15)),"") -> 46197 | BW15: =IF($E15<>"",DATE(YEAR($E15),MONTH($E15),DAY($E15)),"") -> 46198 | BX15: =IF($E15<>"",TEXT($E15,"HH"),"") -> 14 | BY15: =IF(B15<>"",VALUE(LEFT(B15)),"") -> 5 | BZ15: {=IF($A15<>"",INDEX(LISTA!$M$2:$N$27,MATCH($BC15,LISTA!$N$2:$N$27,0),1),"")} -> 1 | CA15: =IF($A15<>"",MONTH(BV15),"") -> 6 | CB15: =IF($BT15<>"",MONTH(BT15),"") -> 6 | CC15: 57983378
A16: 46198.862 | B16: 5 - INSTALADA | C16: MASIVO RESIDENCIAL | D16: PAOLA | E16: 46200.458 | F16: ENVIAR ADELANTO 26/06 | G16: 104856405 | H16: 88648893 | I16: ANNY | J16: 989050975 | K16: DNI | L16: 72539720 | M16: AMNER CALEP PEÑA PIÑA | N16: 37407 | O16: SAN MARTIN | P16: 210701 | AM16: San Martín | AQ16: EUSEBIO | AR16: ESTALI | AS16: amnercalep2002@gmail.com | AT16: 989050975 | AU16: 989050975 | AV16: 989050975 | AW16: JR 3 DE OCTUBRE URB 9 DE ABRIL | AX16: 1 | AY16: S/I | AZ16: -6.48287703, -76.37514139 | BA16: JR 9 DE ABRIL | BB16: SMTP025-F | BC16: SAN MARTIN | BD16: =IF(COUNTA(Q16:AP16)>0,INDEX(Q16:AP16,,max(IF(Q16:AP16<>"",COLUMN(Q16:AP16)))-16),"") -> San Martín | BE16: FTTH | BF16: SI | BG16: ALTA NUEVA | BL16: 1 PLAY | BM16: Campaña Regular | BN16: 89 | BO16: 400MBPS | BP16: NO | BQ16: NO | BR16: Ninguno | BS16: 1 | BT16: 46199 | BU16: 1 | BV16: =IF($A16<>"", DATE(YEAR($A16),MONTH($A16),DAY($A16)),"") -> 46198 | BW16: =IF($E16<>"",DATE(YEAR($E16),MONTH($E16),DAY($E16)),"") -> 46200 | BX16: =IF($E16<>"",TEXT($E16,"HH"),"") -> 11 | BY16: =IF(B16<>"",VALUE(LEFT(B16)),"") -> 5 | BZ16: {=IF($A16<>"",INDEX(LISTA!$M$2:$N$27,MATCH($BC16,LISTA!$N$2:$N$27,0),1),"")} -> 23 | CA16: =IF($A16<>"",MONTH(BV16),"") -> 6 | CB16: =IF($BT16<>"",MONTH(BT16),"") -> 6 | CC16: 57997036
A17: 46196.576 | B17: 5 - INSTALADA | C17: MASIVO RESIDENCIAL | D17: NAYELI | E17: 46199.583 | F17: PROCEDE, EDIFICIO HABILITADO | G17: 104780309 | H17: 88566260 | I17: ANTHONELLA | J17: 968906150 | K17: DNI | L17: 48294663 | M17: KEVIN JUSTIN GUERRA LÓPEZ | N17: 34087 | O17: LIMA METROPOLITANA | P17: 150117 | AF17: Surquillo | AQ17: OSCAR | AR17: MAXIMINA | AS17: kevin.04.gl@gmail.com | AT17: 968906150 | AU17: 968906150 | AV17: 968906150 | AW17: Av. Principal 915 Surquillo Edificio: VITTORIE | AX17: 9 | AY17: 901 | AZ17: -12.119644, -77.00413 | BA17: av principal | BB17: LMSQ089-S | BC17: LIMA METROPOLITANA | BD17: =IF(COUNTA(Q17:AP17)>0,INDEX(Q17:AP17,,max(IF(Q17:AP17<>"",COLUMN(Q17:AP17)))-16),"") -> Surquillo | BE17: FTTH | BF17: SI | BG17: ALTA NUEVA | BL17: 1 PLAY | BM17: Campaña Regular | BN17: 110 | BO17: 500MBPS | BP17: SI | BQ17: NO | BR17: Ninguno | BS17: Ninguno | BT17: 46199 | BU17: 2 | BV17: =IF($A17<>"", DATE(YEAR($A17),MONTH($A17),DAY($A17)),"") -> 46196 | BW17: =IF($E17<>"",DATE(YEAR($E17),MONTH($E17),DAY($E17)),"") -> 46199 | BX17: =IF($E17<>"",TEXT($E17,"HH"),"") -> 14 | BY17: =IF(B17<>"",VALUE(LEFT(B17)),"") -> 5 | BZ17: {=IF($A17<>"",INDEX(LISTA!$M$2:$N$27,MATCH($BC17,LISTA!$N$2:$N$27,0),1),"")} -> 1 | CA17: =IF($A17<>"",MONTH(BV17),"") -> 6 | CB17: =IF($BT17<>"",MONTH(BT17),"") -> 6 | CC17: 57976602
A18: 46198.728 | B18: 5 - INSTALADA | C18: MASIVO RESIDENCIAL | D18: NAYELI | E18: 46200.5 | F18: CL CONFIRMA VISITA | G18: 104849431 | H18: 88626343 | I18: JESSICA | J18: 974629301 | K18: DNI | L18: 45346787 | M18: LEWIS RICHARD CORDOVA HUAMAN | N18: 32425 | O18: CAJAMARCA | P18: 061102 | AF18: Comas | AQ18: HECTOR | AR18: ERNESTINA | AS18: lrcordovah88@gmail.com | AT18: 974629301 | AU18: 974629301 | AV18: 974629301 | AW18: AV MICAELA BASTIDAS Mz G Lt - BLOCK 6 ( AV. MICAELA BASTIDAS S/N BLOCK 06 - TORRE A ETAPA 7 MZ. G ) Edificio: VISTA SOL - SOL DE COLLIQUE - TORRE A - BLOCK 06 | AX18: 10 | AY18: 1008 | AZ18: -11.927046, -77.059691 | BA18: AV. LOS CHASQUIS | BB18: LMCO181 | BC18: LIMA METROPOLITANA | BD18: =IF(COUNTA(Q18:AP18)>0,INDEX(Q18:AP18,,max(IF(Q18:AP18<>"",COLUMN(Q18:AP18)))-16),"") -> Comas | BE18: HFC | BF18: SI | BG18: ALTA NUEVA | BL18: 2 PLAY + TV ESTANDAR | BM18: Campaña Regular PRO | BN18: 170 | BO18: 400MBPS | BP18: SI | BQ18: NO | BR18: 2 | BS18: Ninguno | BT18: 46200 | BU18: 1 | BV18: =IF($A18<>"", DATE(YEAR($A18),MONTH($A18),DAY($A18)),"") -> 46198 | BW18: =IF($E18<>"",DATE(YEAR($E18),MONTH($E18),DAY($E18)),"") -> 46200 | BX18: =IF($E18<>"",TEXT($E18,"HH"),"") -> 12 | BY18: =IF(B18<>"",VALUE(LEFT(B18)),"") -> 5 | BZ18: {=IF($A18<>"",INDEX(LISTA!$M$2:$N$27,MATCH($BC18,LISTA!$N$2:$N$27,0),1),"")} -> 1 | CA18: =IF($A18<>"",MONTH(BV18),"") -> 6 | CB18: =IF($BT18<>"",MONTH(BT18),"") -> 6 | CC18: 57995429
A19: 46198.601 | B19: 5 - INSTALADA | C19: MASIVO RESIDENCIAL | D19: NAYELI | E19: 46201.375 | F19: PROCEDE SE ENVIA ADELANTO 26/06 | G19: 104842396 | H19: 88622310 | I19: ANTHONELLA | J19: 959466891 | K19: DNI | L19: 75454838 | M19: ROCIO LESLY FIGUEROA RODRIGUEZ | N19: 35060 | O19: LIMA | P19: 150101 | W19: Callao | AQ19: TEODOSIO | AR19: BETTY | AS19: figeroa.air23@gmail.com | AT19: 959466891 | AU19: 959466891 | AV19: 976269839 | AW19: Albino Herrera 2da Etp. Mz.B1 Lt.20 - Callao | AX19: 3 | AY19: SIN | AZ19: -12.010193, -77.095981 | BA19: AV LOS DOMINICOS | BB19: LMCA009-S | BC19: CALLAO | BD19: =IF(COUNTA(Q19:AP19)>0,INDEX(Q19:AP19,,max(IF(Q19:AP19<>"",COLUMN(Q19:AP19)))-16),"") -> Callao | BE19: FTTH | BF19: NO | BG19: ALTA NUEVA | BL19: 1 PLAY | BM19: Campaña Regular | BN19: 89 | BO19: 400MBPS | BP19: SI | BQ19: NO | BR19: Ninguno | BS19: Ninguno | BT19: 46201 | BU19: 1 | BV19: =IF($A19<>"", DATE(YEAR($A19),MONTH($A19),DAY($A19)),"") -> 46198 | BW19: =IF($E19<>"",DATE(YEAR($E19),MONTH($E19),DAY($E19)),"") -> 46201 | BX19: =IF($E19<>"",TEXT($E19,"HH"),"") -> 09 | BY19: =IF(B19<>"",VALUE(LEFT(B19)),"") -> 5 | BZ19: {=IF($A19<>"",INDEX(LISTA!$M$2:$N$27,MATCH($BC19,LISTA!$N$2:$N$27,0),1),"")} -> 2 | CA19: =IF($A19<>"",MONTH(BV19),"") -> 6 | CB19: =IF($BT19<>"",MONTH(BT19),"") -> 6 | CC19: 57993555
A20: 46199.594 | B20: 5 - INSTALADA | C20: MASIVO RESIDENCIAL | D20: NAYELI | E20: 46201.458 | F20: CL QUIERE INSTALACION PARA EL LUNES | G20: 104872550 | H20: 88659360 | I20: JESSICA | J20: 959385387 | K20: DNI | L20: 40494768 | M20: TEODORO SAICO SUCLLE | N20: 28834 | O20: CUSCO | P20: 070801 | T20: Arequipa | AQ20: NOLASCO | AR20: PAULINA | AS20: Teosaico@hotmail.com | AT20: 959385387 | AU20: 959385387 | AV20: 959385387 | AW20: CALLE CAHUIDE 315 URB. LA LIBERTAD | AX20: 2 | AY20: NA | AZ20: -16.37709499, -71.56237894 | BA20: CALLE MIGUEL GRAU | BB20: AQCC004-S | BC20: AREQUIPA | BD20: =IF(COUNTA(Q20:AP20)>0,INDEX(Q20:AP20,,max(IF(Q20:AP20<>"",COLUMN(Q20:AP20)))-16),"") -> Arequipa | BE20: FTTH | BF20: SI | BG20: ALTA NUEVA | BL20: 1 PLAY + L1MAX | BM20: Campaña Regular PRO | BN20: 110 | BO20: 500MBPS | BP20: SI | BQ20: NO | BR20: Ninguno | BS20: 1 | BT20: 46201 | BU20: 2 | BV20: =IF($A20<>"", DATE(YEAR($A20),MONTH($A20),DAY($A20)),"") -> 46199 | BW20: =IF($E20<>"",DATE(YEAR($E20),MONTH($E20),DAY($E20)),"") -> 46201 | BX20: =IF($E20<>"",TEXT($E20,"HH"),"") -> 11 | BY20: =IF(B20<>"",VALUE(LEFT(B20)),"") -> 5 | BZ20: {=IF($A20<>"",INDEX(LISTA!$M$2:$N$27,MATCH($BC20,LISTA!$N$2:$N$27,0),1),"")} -> 7 | CA20: =IF($A20<>"",MONTH(BV20),"") -> 6 | CB20: =IF($BT20<>"",MONTH(BT20),"") -> 6 | CC20: 58001237
A21: 46199.708 | B21: 5 - INSTALADA | C21: MASIVO RESIDENCIAL | D21: NAYELI | E21: 46202.458 | F21: PROCEDE | G21: 104878027 | H21: 88663022 | I21: GABRIEL | J21: 946215729 | K21: DNI | L21: 75416717 | M21: CRISTEL NICOLT LOPEZ ESPADA | N21: 38508 | O21: LIMA | P21: 140501 | AE21: Huaura | AQ21: HILMER | AR21: MARIA | AS21: Crisle.0506@gmail.com | AT21: 946215729 | AU21: 946215729 | AV21: 946215729 | AW21: FRANSISCO ROSAS 346 | AX21: 3 | AY21: 1 | AZ21: -11.104527221283575, -77.60735781101647 | BA21: AL COSTADO DE FERRETERIA NANCY | BB21: LMHU018-S | BC21: LIMA | BD21: =IF(COUNTA(Q21:AP21)>0,INDEX(Q21:AP21,,max(IF(Q21:AP21<>"",COLUMN(Q21:AP21)))-16),"") -> Huaura | BE21: FTTH | BF21: NO | BG21: ALTA NUEVA | BL21: 1 PLAY | BM21: Campaña Regular | BN21: 69 | BO21: 200MBPS | BP21: NO | BQ21: NO | BR21: Ninguno | BS21: Ninguno | BT21: 46202 | BU21: 1 | BV21: =IF($A21<>"", DATE(YEAR($A21),MONTH($A21),DAY($A21)),"") -> 46199 | BW21: =IF($E21<>"",DATE(YEAR($E21),MONTH($E21),DAY($E21)),"") -> 46202 | BX21: =IF($E21<>"",TEXT($E21,"HH"),"") -> 11 | BY21: =IF(B21<>"",VALUE(LEFT(B21)),"") -> 5 | BZ21: {=IF($A21<>"",INDEX(LISTA!$M$2:$N$27,MATCH($BC21,LISTA!$N$2:$N$27,0),1),"")} -> 3 | CA21: =IF($A21<>"",MONTH(BV21),"") -> 6 | CB21: =IF($BT21<>"",MONTH(BT21),"") -> 6 | CC21: 58001957
A22: 46191.528 | B22: 5 - INSTALADA | C22: MASIVO RESIDENCIAL | D22: NAYELI | E22: 46200.458 | F22: PROCEDE FULL CLARO | G22: 104645330 | H22: 88434668 | I22: JESSICA | J22: 952589629 | K22: DNI | L22: 10811695 | M22: JENNY PAOLY ROJAS BENITO | N22: 28323 | O22: LIMA | P22: 140125 | AF22: Santiago de Surco | AQ22: GUSTAVO | AR22: MARGARITA | AS22: jainy31@hotmail.com | AT22: 953735960 | AU22: 953735960 | AV22: 953735960 | AW22: ASENTAMIENTO HUMANO LOS VIÑEDOS DE SURCO MZ H LT 35 | AX22: 3 | AY22: NA | AZ22: -12.162537454 -76.9885167909999 | BA22: Losa deportiva Los viñedos | BB22: LMSC325-F | BC22: LIMA METROPOLITANA | BD22: =IF(COUNTA(Q22:AP22)>0,INDEX(Q22:AP22,,max(IF(Q22:AP22<>"",COLUMN(Q22:AP22)))-16),"") -> Santiago de Surco | BE22: FTTH | BF22: SI | BG22: ALTA NUEVA | BL22: 2 PLAY + TV ESTANDAR | BM22: Campaña Regular PRO | BN22: 170 | BO22: 400MBPS | BP22: SI | BQ22: NO | BR22: 2 | BS22: 1 | BT22: 46202 | BU22: 2 | BV22: =IF($A22<>"", DATE(YEAR($A22),MONTH($A22),DAY($A22)),"") -> 46191 | BW22: =IF($E22<>"",DATE(YEAR($E22),MONTH($E22),DAY($E22)),"") -> 46200 | BX22: =IF($E22<>"",TEXT($E22,"HH"),"") -> 11 | BY22: =IF(B22<>"",VALUE(LEFT(B22)),"") -> 5 | BZ22: {=IF($A22<>"",INDEX(LISTA!$M$2:$N$27,MATCH($BC22,LISTA!$N$2:$N$27,0),1),"")} -> 1 | CA22: =IF($A22<>"",MONTH(BV22),"") -> 6 | CB22: =IF($BT22<>"",MONTH(BT22),"") -> 6 | CC22: 57944685
A23: 46200.619 | B23: 5 - INSTALADA | C23: MASIVO RESIDENCIAL | D23: NAYELI | E23: 46202.458 | F23: PROCEDE | G23: 104901334 | H23: 88675788 | I23: JESSICA | J23: 998420484 | K23: DNI | L23: 32221145 | M23: RUSBEL MANUEL OQUEÑA PASTOR | N23: 27314 | O23: ANCASH | P23: 020601 | AF23: Comas | AQ23: MANUEL | AR23: HISABEL | AS23: roquenap@gmail.com | AT23: 998420484 | AU23: 998420484 | AV23: 998420484 | AW23: CALLE JOSE BERNARDO ALCEDO 370 URB. COLLIQUE | AX23: 3 | AY23: 302 | AZ23: -11.91581521571454, -77.02561845492386 | BA23: CALLE CHICLAYO | BB23: LMCO226-F | BC23: LIMA METROPOLITANA | BD23: =IF(COUNTA(Q23:AP23)>0,INDEX(Q23:AP23,,max(IF(Q23:AP23<>"",COLUMN(Q23:AP23)))-16),"") -> Comas | BE23: FTTH | BF23: NO | BG23: ALTA NUEVA | BL23: 1 PLAY | BM23: Campaña Promo Mediana | BN23: 89 | BO23: 400MBPS | BP23: NO | BQ23: NO | BR23: Ninguno | BS23: 1 | BT23: 46202 | BU23: 3 | BV23: =IF($A23<>"", DATE(YEAR($A23),MONTH($A23),DAY($A23)),"") -> 46200 | BW23: =IF($E23<>"",DATE(YEAR($E23),MONTH($E23),DAY($E23)),"") -> 46202 | BX23: =IF($E23<>"",TEXT($E23,"HH"),"") -> 11 | BY23: =IF(B23<>"",VALUE(LEFT(B23)),"") -> 5 | BZ23: {=IF($A23<>"",INDEX(LISTA!$M$2:$N$27,MATCH($BC23,LISTA!$N$2:$N$27,0),1),"")} -> 1 | CA23: =IF($A23<>"",MONTH(BV23),"") -> 6 | CB23: =IF($BT23<>"",MONTH(BT23),"") -> 6 | CC23: 58008151
A24: 46200.495 | B24: 5 - INSTALADA | C24: MASIVO RESIDENCIAL | D24: NAYELI | E24: 46202.458 | F24: PROCEDE | G24: 104896460 | H24: 88673676 | I24: JESSICA | J24: 954973060 | K24: DNI | L24: 80064841 | M24: LUIS ALBERTO DAVILA PAREDES | N24: 28883 | O24: PASCO | P24: 180101 | Z24: Huánuco | AQ24: DIOGENES | AR24: AMANDA | AS24: Luisalberto22davila79@gmail.com | AT24: 954973060 | AU24: 954973060 | AV24: 954973060 | AW24: AV. ANDRES FERNANDEZ GARRIDO URB. LAS GARDENIAS | AX24: 2 | AY24: NA | AZ24: -9.96498585, -76.245660663 | BA24: JR. SAN FAUSTO | BB24: HUPM008-S | BC24: HUANUCO | BD24: =IF(COUNTA(Q24:AP24)>0,INDEX(Q24:AP24,,max(IF(Q24:AP24<>"",COLUMN(Q24:AP24)))-16),"") -> Huánuco | BE24: FTTH | BF24: NO | BG24: ALTA NUEVA | BL24: 1 PLAY + L1MAX | BM24: Campaña Regular PRO | BN24: 110 | BO24: 500MBPS | BQ24: NO | BR24: Ninguno | BS24: 1 | BT24: 46202 | BU24: 4 | BV24: =IF($A24<>"", DATE(YEAR($A24),MONTH($A24),DAY($A24)),"") -> 46200 | BW24: =IF($E24<>"",DATE(YEAR($E24),MONTH($E24),DAY($E24)),"") -> 46202 | BX24: =IF($E24<>"",TEXT($E24,"HH"),"") -> 11 | BY24: =IF(B24<>"",VALUE(LEFT(B24)),"") -> 5 | BZ24: {=IF($A24<>"",INDEX(LISTA!$M$2:$N$27,MATCH($BC24,LISTA!$N$2:$N$27,0),1),"")} -> 12 | CA24: =IF($A24<>"",MONTH(BV24),"") -> 6 | CB24: =IF($BT24<>"",MONTH(BT24),"") -> 6 | CC24: 58006971
A25: 46200.749 | B25: 5 - INSTALADA | C25: MASIVO RESIDENCIAL | D25: NAYELI | E25: 46203.375 | F25: PROCEDE | G25: 104909457 | H25: 88679217 | I25: GABRIEL | J25: 997867217 | K25: DNI | L25: 08450266 | M25: NORMA MONICA, PACHECHO AGUILAR | N25: 24235 | O25: CUSCO | P25: 080101 | AF25: San Martín de Porres | AQ25: CARLOS | AR25: ANA | AS25: monikapachecho840@gmail.com | AT25: 997867217 | AU25: 997867217 | AV25: 997867217 | AW25: AV UNIVERSITARIA 621 URB SEÑOR DE CONDEVILLA | AX25: 2 | AY25: S/I | AZ25: -12.020495, -77.075867 | BA25: JR LAS AMERICAS | BB25: LMMP059-S | BC25: LIMA METROPOLITANA | BD25: =IF(COUNTA(Q25:AP25)>0,INDEX(Q25:AP25,,max(IF(Q25:AP25<>"",COLUMN(Q25:AP25)))-16),"") -> San Martín de Porres | BE25: FTTH | BF25: NO | BG25: ALTA NUEVA | BL25: 3 PLAY + TV ESTANDAR | BM25: Campaña Regular | BN25: 155 | BO25: 200MBPS | BP25: NO | BQ25: NO | BR25: Ninguno | BS25: Ninguno | BT25: 46203 | BU25: 1 | BV25: =IF($A25<>"", DATE(YEAR($A25),MONTH($A25),DAY($A25)),"") -> 46200 | BW25: =IF($E25<>"",DATE(YEAR($E25),MONTH($E25),DAY($E25)),"") -> 46203 | BX25: =IF($E25<>"",TEXT($E25,"HH"),"") -> 09 | BY25: =IF(B25<>"",VALUE(LEFT(B25)),"") -> 5 | BZ25: {=IF($A25<>"",INDEX(LISTA!$M$2:$N$27,MATCH($BC25,LISTA!$N$2:$N$27,0),1),"")} -> 1 | CA25: =IF($A25<>"",MONTH(BV25),"") -> 6 | CB25: =IF($BT25<>"",MONTH(BT25),"") -> 6 | CC25: 58010030
A26: 46192.698 | B26: 5 - INSTALADA | C26: MASIVO RESIDENCIAL | D26: PAOLA | E26: 46200.458 | F26: INSTALACION A MEDIAS - RESERVA TERMINARAN EL 28/06 POR DECOS, CONFIRMADO CON CLIENTE. | G26: 104867348 | H26: 88655700 | I26: JULIANA | J26: 978345537 | K26: DNI | L26: 76586680 | M26: ERICK ABRAHAM HIGINIO SOTELO | N26: 36140 | O26: LIMA METROPOLITANA | P26: 150128 | AF26: Comas | AQ26: ABRAHAM | AR26: LUZ | AS26: ERICK_1199@HOTMAIL.COM | AT26: 978 345 537 | AU26: 978 345 537 | AV26: 978 345 537 | AW26: DIRECCION: MZ G2 LOTE 30 URB. EL ALAMO 2DA ETAPA, COMAS. | AX26: 2 | AY26: 1 | AZ26: -11.924353, -77.063183 | BA26: AV. MICAELA CON AV. TRAPICHE. | BB26: LMCO023 | BC26: LIMA METROPOLITANA | BD26: =IF(COUNTA(Q26:AP26)>0,INDEX(Q26:AP26,,max(IF(Q26:AP26<>"",COLUMN(Q26:AP26)))-16),"") -> Comas | BE26: HFC | BF26: SI | BG26: ALTA NUEVA | BL26: 2 PLAY + TV ESTANDAR | BM26: Campaña Regular | BN26: 170 | BO26: 400MBPS | BP26: SI | BQ26: NO | BR26: 2 | BS26: Ninguno | BT26: 46203 | BU26: 2 | BV26: =IF($A26<>"", DATE(YEAR($A26),MONTH($A26),DAY($A26)),"") -> 46192 | BW26: =IF($E26<>"",DATE(YEAR($E26),MONTH($E26),DAY($E26)),"") -> 46200 | BX26: =IF($E26<>"",TEXT($E26,"HH"),"") -> 11 | BY26: =IF(B26<>"",VALUE(LEFT(B26)),"") -> 5 | BZ26: {=IF($A26<>"",INDEX(LISTA!$M$2:$N$27,MATCH($BC26,LISTA!$N$2:$N$27,0),1),"")} -> 1 | CA26: =IF($A26<>"",MONTH(BV26),"") -> 6 | CB26: =IF($BT26<>"",MONTH(BT26),"") -> 6 | CC26: 57999609
A27: 46198.753 | B27: 5 - INSTALADA | C27: MASIVO RESIDENCIAL | D27: NAYELI | E27: 46203.375 | F27: PENDIENTE CULMINAR INSTALACION A LAS 3PM | G27: 104850593 | H27: 88626803 | I27: GABRIEL | J27: 923619505 | K27: DNI | L27: 47883104 | M27: MINES BALTIERREZ, FLOR STEFANY | N27: 34151 | O27: LIMA METROPOLITANA | P27: 150113 | AF27: Carabayllo | AQ27: RAFAEL | AR27: FLOR | AS27: stefmines2@gmail.com | AT27: 923619505 | AU27: 923619505 | AV27: 923619505 | AW27: JIRON 9 DE OCTUBRE 501 CARABAYLLO | AX27: 1 | AY27: S/I | AZ27: -11.886848358,-77.020306622 | BA27: A 1 CDRA DE HABLA BROSTER | BB27: LMBY014-S | BC27: LIMA METROPOLITANA | BD27: =IF(COUNTA(Q27:AP27)>0,INDEX(Q27:AP27,,max(IF(Q27:AP27<>"",COLUMN(Q27:AP27)))-16),"") -> Carabayllo | BE27: FTTH | BF27: NO | BG27: ALTA NUEVA | BL27: 1 PLAY | BM27: Campaña Promo Mediana | BN27: 89 | BO27: 400MBPS | BP27: NO | BQ27: NO | BR27: Ninguno | BS27: Ninguno | BT27: 46203 | BU27: 3 | BV27: =IF($A27<>"", DATE(YEAR($A27),MONTH($A27),DAY($A27)),"") -> 46198 | BW27: =IF($E27<>"",DATE(YEAR($E27),MONTH($E27),DAY($E27)),"") -> 46203 | BX27: =IF($E27<>"",TEXT($E27,"HH"),"") -> 09 | BY27: =IF(B27<>"",VALUE(LEFT(B27)),"") -> 5 | BZ27: {=IF($A27<>"",INDEX(LISTA!$M$2:$N$27,MATCH($BC27,LISTA!$N$2:$N$27,0),1),"")} -> 1 | CA27: =IF($A27<>"",MONTH(BV27),"") -> 6 | CB27: =IF($BT27<>"",MONTH(BT27),"") -> 6 | CC27: 57995668
A28: 46200.743 | B28: 5 - INSTALADA | C28: MASIVO RESIDENCIAL | D28: PAOLA | E28: 46203.375 | F28: direccion incompleta en sistema | G28: 104908032 | H28: 88679843 | I28: JESSICA | J28: 931807375 | K28: DNI | L28: 20083833 | M28: ROBERTH SALAS JORGE | N28: 27949 | O28: HUANCAVELICA | P28: 080311 | AB28: Huancayo | AQ28: HERMINIO | AR28: DELIA | AS28: sajo0707@hotmail.com | AT28: 931807375 | AU28: 931807375 | AV28: 931807375 | AW28: PASAJE JESÚS MARÍA 00 OSEA S/N | AX28: 2 | AY28: NA | AZ28: -12.05561432456769, -75.19688191632616 | BA28: OLAYA, PUENTE, RIACHUELO | BB28: JNHY023-F | BC28: JUNIN | BD28: =IF(COUNTA(Q28:AP28)>0,INDEX(Q28:AP28,,max(IF(Q28:AP28<>"",COLUMN(Q28:AP28)))-16),"") -> Huancayo | BE28: FTTH | BF28: SI | BG28: ALTA NUEVA | BL28: 1 PLAY + L1MAX | BM28: Campaña Regular PRO | BN28: 110 | BO28: 500MBPS | BP28: SI | BQ28: NO | BR28: Ninguno | BS28: 1 | BT28: 46203 | BU28: 4 | BV28: =IF($A28<>"", DATE(YEAR($A28),MONTH($A28),DAY($A28)),"") -> 46200 | BW28: =IF($E28<>"",DATE(YEAR($E28),MONTH($E28),DAY($E28)),"") -> 46203 | BX28: =IF($E28<>"",TEXT($E28,"HH"),"") -> 09 | BY28: =IF(B28<>"",VALUE(LEFT(B28)),"") -> 5 | BZ28: {=IF($A28<>"",INDEX(LISTA!$M$2:$N$27,MATCH($BC28,LISTA!$N$2:$N$27,0),1),"")} -> 14 | CA28: =IF($A28<>"",MONTH(BV28),"") -> 6 | CB28: =IF($BT28<>"",MONTH(BT28),"") -> 6 | CC28: 58010324
A29: 46203.554 | B29: 5 - INSTALADA | C29: MASIVO RESIDENCIAL | D29: NAYELI | E29: 46205.375 | F29: PROCEDE EN HFC | G29: 104984180 | H29: 88773507 | I29: ENMANUEL | J29: 912327595 | K29: DNI | L29: 42138364 | M29: MIRIAM GARDENIA CHAVEZ ZAVALETA | N29: 24524 | O29: CAJAMARCA | P29: 06 | AF29: Comas | AQ29: TERMOPILO | AR29: AURELIA | AS29: chacezzavaletamiriangardenia@gmail.com | AT29: 912327595 | AU29: 912327595 | AV29: 912327595 | AW29: av lima 358 | AX29: 1 | AY29: 1 | AZ29: -11.9043606,-77.04013908 | BA29: parque Manhatan | BB29: LMCO047 | BC29: LIMA METROPOLITANA | BD29: =IF(COUNTA(Q29:AP29)>0,INDEX(Q29:AP29,,max(IF(Q29:AP29<>"",COLUMN(Q29:AP29)))-16),"") -> Comas | BE29: HFC | BF29: NO | BG29: ALTA NUEVA | BL29: 2PLAY + TELF | BM29: Campaña Regular | BN29: 94 | BO29: 400MBPS | BP29: NO | BQ29: SI | BR29: Ninguno | BS29: Ninguno | BT29: 46205 | BU29: 1 | BV29: =IF($A29<>"", DATE(YEAR($A29),MONTH($A29),DAY($A29)),"") -> 46203 | BW29: =IF($E29<>"",DATE(YEAR($E29),MONTH($E29),DAY($E29)),"") -> 46205 | BX29: =IF($E29<>"",TEXT($E29,"HH"),"") -> 09 | BY29: =IF(B29<>"",VALUE(LEFT(B29)),"") -> 5 | BZ29: {=IF($A29<>"",INDEX(LISTA!$M$2:$N$27,MATCH($BC29,LISTA!$N$2:$N$27,0),1),"")} -> 1 | CA29: =IF($A29<>"",MONTH(BV29),"") -> 6 | CB29: =IF($BT29<>"",MONTH(BT29),"") -> 7 | CC29: 58028537
A30: 46198.74 | B30: 5 - INSTALADA | C30: MASIVO RESIDENCIAL | D30: NAYELI | E30: 46205.375 | F30: EN EJECUCION | G30: 104848535 | H30: 88625537 | I30: BRITNEY | J30: 955847780 | K30: DNI | L30: 40152975 | M30: GROWER HONORATO GARRO HUERTAS | N30: 28048 | O30: ANCASH | P30: 020509 | AF30: Los Olivos | AQ30: Fernando | AR30: Jacoba | AS30: growergarrohuertas@gmail.com | AT30: 955 847 780 | AU30: 955 847 780 | AV30: 955 847 780 | AW30: calle las gardenias mz c lt10 | AX30: 3 | AY30: 1 | AZ30: -11.944502 , -77.073282 | BA30: URBANIZACIÓN LAS GARDENIAS DE PRO | BB30: LMLO101 | BC30: LIMA METROPOLITANA | BD30: =IF(COUNTA(Q30:AP30)>0,INDEX(Q30:AP30,,max(IF(Q30:AP30<>"",COLUMN(Q30:AP30)))-16),"") -> Los Olivos | BE30: HFC | BF30: SI | BG30: ALTA NUEVA | BL30: 1 PLAY + L1MAX | BM30: Campaña Regular | BN30: 110 | BO30: 500MBPS | BP30: SI | BQ30: NO | BR30: Ninguno | BS30: Ninguno | BT30: 46205 | BU30: 2 | BV30: =IF($A30<>"", DATE(YEAR($A30),MONTH($A30),DAY($A30)),"") -> 46198 | BW30: =IF($E30<>"",DATE(YEAR($E30),MONTH($E30),DAY($E30)),"") -> 46205 | BX30: =IF($E30<>"",TEXT($E30,"HH"),"") -> 09 | BY30: =IF(B30<>"",VALUE(LEFT(B30)),"") -> 5 | BZ30: {=IF($A30<>"",INDEX(LISTA!$M$2:$N$27,MATCH($BC30,LISTA!$N$2:$N$27,0),1),"")} -> 1 | CA30: =IF($A30<>"",MONTH(BV30),"") -> 6 | CB30: =IF($BT30<>"",MONTH(BT30),"") -> 7 | CC30: 57995098
A31: 46203.601 | B31: 5 - INSTALADA | C31: MASIVO RESIDENCIAL | D31: NAYELI | E31: 46205.458 | F31: PROCEDE | G31: 105002855 | H31: 88788798 | I31: JESSICA | J31: 920604149 | K31: DNI | L31: 16625471 | M31: ADRIAN PAICO CHUCAS | N31: 17771 | O31: LAMBAYEQUE | P31: 130202 | AD31: Chiclayo | AQ31: GENARO | AR31: ISIDORA | AS31: mv_henrypaico@hotmail.com | AT31: 920604149 | AU31: 920604149 | AV31: 920604149 | AW31: AV. VENEZUELA 160 URB. URRUNAGA | AX31: 1 | AY31: 1 | AZ31: -6.75555372, -79.83194353 | BA31: AV. MEXICO | BB31: LBLO007-F | BC31: LAMBAYEQUE | BD31: =IF(COUNTA(Q31:AP31)>0,INDEX(Q31:AP31,,max(IF(Q31:AP31<>"",COLUMN(Q31:AP31)))-16),"") -> Chiclayo | BE31: FTTH | BF31: NO | BG31: ALTA NUEVA | BL31: 1 PLAY + L1MAX | BM31: Campaña Regular PRO | BN31: 110 | BO31: 500MBPS | BP31: SI | BQ31: NO | BR31: Ninguno | BS31: 1 | BT31: 46205 | BU31: 3 | BV31: =IF($A31<>"", DATE(YEAR($A31),MONTH($A31),DAY($A31)),"") -> 46203 | BW31: =IF($E31<>"",DATE(YEAR($E31),MONTH($E31),DAY($E31)),"") -> 46205 | BX31: =IF($E31<>"",TEXT($E31,"HH"),"") -> 11 | BY31: =IF(B31<>"",VALUE(LEFT(B31)),"") -> 5 | BZ31: {=IF($A31<>"",INDEX(LISTA!$M$2:$N$27,MATCH($BC31,LISTA!$N$2:$N$27,0),1),"")} -> 16 | CA31: =IF($A31<>"",MONTH(BV31),"") -> 6 | CB31: =IF($BT31<>"",MONTH(BT31),"") -> 7 | CC31: 58033635
A32: 46203.545 | B32: 5 - INSTALADA | C32: MASIVO RESIDENCIAL | D32: NAYELI | E32: 46205.375 | F32: TIENE SEC CREADA DE AYER 29/06 POR TIENDA VIRTUAL | G32: 104965766 | H32: 88724375 | I32: ANTHONELLA | J32: 961883833 | K32: DNI | L32: 72679082 | M32: DANIEL OCTAVIO LUDEÑA ROJAS | N32: 33323 | O32: PIURA | P32: 200000 | AK32: Piura | AQ32: ABEL | AR32: MARI | AS32: dolr2691@gmail.com | AT32: 961883833 | AU32: 961883833 | AV32: 961883833 | AW32: urb. FELIPE COSSIO DEL POMAR mz z3 lt 10 | AX32: 2 | AY32: nd | AZ32: -5.183216211245893 -80.59044531819954 | BA32: referencia altura ferretería Jeova mi pastor espaldas | BB32: -5.183216211245893 -80.59044531819954 | BC32: PIURA | BD32: =IF(COUNTA(Q32:AP32)>0,INDEX(Q32:AP32,,max(IF(Q32:AP32<>"",COLUMN(Q32:AP32)))-16),"") -> Piura | BE32: FTTH | BF32: NO | BG32: ALTA NUEVA | BL32: 2PLAY + TELF | BM32: Campaña Regular | BN32: 94 | BO32: 400MBPS | BP32: NO | BQ32: SI | BR32: Ninguno | BS32: Ninguno | BT32: 46205 | BU32: 4 | BV32: =IF($A32<>"", DATE(YEAR($A32),MONTH($A32),DAY($A32)),"") -> 46203 | BW32: =IF($E32<>"",DATE(YEAR($E32),MONTH($E32),DAY($E32)),"") -> 46205 | BX32: =IF($E32<>"",TEXT($E32,"HH"),"") -> 09 | BY32: =IF(B32<>"",VALUE(LEFT(B32)),"") -> 5 | BZ32: {=IF($A32<>"",INDEX(LISTA!$M$2:$N$27,MATCH($BC32,LISTA!$N$2:$N$27,0),1),"")} -> 21 | CA32: =IF($A32<>"",MONTH(BV32),"") -> 6 | CB32: =IF($BT32<>"",MONTH(BT32),"") -> 7 | CC32: 58023666
A33: 46203.565 | B33: 5 - INSTALADA | C33: MASIVO RESIDENCIAL | D33: NAYELI | E33: 46205.583 | F33: EN EJECUCION | G33: 104963507 | H33: 88721861 | I33: ANTHONELLA | J33: 904383310 | K33: DNI | L33: 78717821 | M33: ADRIANA MARIA NATALIA RIVAS GRIMALDO | N33: 38561 | O33: LIMA | P33: 150135 | AF33: San Martín de Porres | AQ33: MIGUEL | AR33: NATALIA | AS33: eithanmibebe63@gmail.com | AT33: 904383310 | AU33: 904383310 | AV33: 904383310 | AW33: Jirón Alberto Bartón 310 | AX33: 5 | AY33: ND | AZ33: -12.023854272942264 -77.07918538474682 | BA33: JR. THOMAS COCHRANE | BB33: -12.023854272942264 -77.07918538474682 | BC33: LIMA METROPOLITANA | BD33: =IF(COUNTA(Q33:AP33)>0,INDEX(Q33:AP33,,max(IF(Q33:AP33<>"",COLUMN(Q33:AP33)))-16),"") -> San Martín de Porres | BE33: FTTH | BF33: NO | BG33: ALTA NUEVA | BL33: 2PLAY + TELF | BM33: Campaña Regular | BN33: 94 | BO33: 400MBPS | BP33: NO | BQ33: SI | BR33: Ninguno | BS33: Ninguno | BT33: 46205 | BU33: 5 | BV33: =IF($A33<>"", DATE(YEAR($A33),MONTH($A33),DAY($A33)),"") -> 46203 | BW33: =IF($E33<>"",DATE(YEAR($E33),MONTH($E33),DAY($E33)),"") -> 46205 | BX33: =IF($E33<>"",TEXT($E33,"HH"),"") -> 14 | BY33: =IF(B33<>"",VALUE(LEFT(B33)),"") -> 5 | BZ33: {=IF($A33<>"",INDEX(LISTA!$M$2:$N$27,MATCH($BC33,LISTA!$N$2:$N$27,0),1),"")} -> 1 | CA33: =IF($A33<>"",MONTH(BV33),"") -> 6 | CB33: =IF($BT33<>"",MONTH(BT33),"") -> 7 | CC33: 58023004
A34: 46200.384 | B34: 5 - INSTALADA | C34: MASIVO RESIDENCIAL | D34: NAYELI | E34: 46206.375 | F34: SE ENVIO RESCATE COMERCIAL 01/07 | G34: 104886907 | H34: 88670638 | I34: FABRIZIO | J34: 980808162 | K34: DNI | L34: 09989234 | M34: DINO IVAN GALLARDO ESTELA | N34: 22897 | O34: LIMA | P34: 150804 | AF34: Los Olivos | AQ34: SANTIAGO | AR34: CELINA | AS34: gallardoandres089@gmail.com | AT34: 930860834 | AU34: 930860834 | AV34: 948294957 | AW34: URBANIZACIÒN LOS OLIVOS DE PRO mz s2 lt 3 | AX34: 2 | AY34: 0 | AZ34: -11.947674165824195, -77.08054264511327 | BA34: av betancourt | BB34: LMLO099-S | BC34: LIMA METROPOLITANA | BD34: =IF(COUNTA(Q34:AP34)>0,INDEX(Q34:AP34,,max(IF(Q34:AP34<>"",COLUMN(Q34:AP34)))-16),"") -> Los Olivos | BE34: FTTH | BF34: SI | BG34: ALTA NUEVA | BL34: 1 PLAY | BM34: Campaña Promo Mediana | BN34: 89 | BO34: 400MBPS | BP34: NO | BQ34: NO | BR34: Ninguno | BS34: 1 | BT34: 46206 | BU34: 2 | BV34: =IF($A34<>"", DATE(YEAR($A34),MONTH($A34),DAY($A34)),"") -> 46200 | BW34: =IF($E34<>"",DATE(YEAR($E34),MONTH($E34),DAY($E34)),"") -> 46206 | BX34: =IF($E34<>"",TEXT($E34,"HH"),"") -> 09 | BY34: =IF(B34<>"",VALUE(LEFT(B34)),"") -> 5 | BZ34: {=IF($A34<>"",INDEX(LISTA!$M$2:$N$27,MATCH($BC34,LISTA!$N$2:$N$27,0),1),"")} -> 1 | CA34: =IF($A34<>"",MONTH(BV34),"") -> 6 | CB34: =IF($BT34<>"",MONTH(BT34),"") -> 7 | CC34: 58004758
A35: 46203.746 | B35: 5 - INSTALADA | C35: MASIVO RESIDENCIAL | D35: NAYELI | E35: 46206.667 | F35: PROCEDE | G35: 104974476 | H35: 88740283 | I35: GABRIEL | J35: 949588974 | K35: DNI | L35: 72118081 | M35: ESTHER JHAJANDRA, SANTIAGO HUANCA | N35: 36128 | O35: HUANUCO | P35: 100101 | Z35: Huánuco | AQ35: FAUSTINO | AR35: NILDA | AS35: jhajandrasantiagohuanca@gmail.com | AT35: 949588974 | AU35: 949588974 | AV35: 949588974 | AW35: AV UNIVERSITARIA 2076 | AX35: 2 | AY35: S/I | AZ35: -9.961946198761577, -76.24575559893029 | BA35: Referencia el colegio Juan Velasco Alvarado | BB35: HUPM010-S | BC35: HUANUCO | BD35: =IF(COUNTA(Q35:AP35)>0,INDEX(Q35:AP35,,max(IF(Q35:AP35<>"",COLUMN(Q35:AP35)))-16),"") -> Huánuco | BE35: FTTH | BF35: NO | BG35: ALTA NUEVA | BL35: 2PLAY + TELF | BM35: Campaña Regular | BN35: 94 | BO35: 400MBPS | BQ35: SI | BR35: Ninguno | BS35: Ninguno | BT35: 46206 | BU35: 3 | BV35: =IF($A35<>"", DATE(YEAR($A35),MONTH($A35),DAY($A35)),"") -> 46203 | BW35: =IF($E35<>"",DATE(YEAR($E35),MONTH($E35),DAY($E35)),"") -> 46206 | BX35: =IF($E35<>"",TEXT($E35,"HH"),"") -> 16 | BY35: =IF(B35<>"",VALUE(LEFT(B35)),"") -> 5 | BZ35: {=IF($A35<>"",INDEX(LISTA!$M$2:$N$27,MATCH($BC35,LISTA!$N$2:$N$27,0),1),"")} -> 12 | CA35: =IF($A35<>"",MONTH(BV35),"") -> 6 | CB35: =IF($BT35<>"",MONTH(BT35),"") -> 7 | CC35: 58026003
A36: 46203.481 | B36: 5 - INSTALADA | C36: MASIVO RESIDENCIAL | D36: NAYELI | E36: 46206.375 | F36: CLIENTE REPROGRAMO PARA MAÑANA 02/07 | G36: 104986822 | H36: 88776097 | I36: ANTHONELLA | J36: 982340413 | K36: DNI | L36: 29676009 | M36: YESENIA TERESA CASTRO NINACONDOR | N36: 27999 | O36: AREQUIPA | P36: 0406 | T36: Arequipa | AQ36: HUGO | AR36: BACILISA | AS36: dediscueva@gmail.com | AT36: 982340413 | AU36: 982340413 | AV36: 982340413 | AW36: Asoc- villa confraternidad zona A MZ- j. Lte 4 alto selva alegre AQP | AX36: 2 | AY36: ND | AZ36: -16.358099664125213 -71.5245148240071 | BA36: Cancha caira | BB36: AQSA044-F | BC36: AREQUIPA | BD36: =IF(COUNTA(Q36:AP36)>0,INDEX(Q36:AP36,,max(IF(Q36:AP36<>"",COLUMN(Q36:AP36)))-16),"") -> Arequipa | BE36: FTTH | BF36: SI | BG36: ALTA NUEVA | BL36: 2PLAY + TELF | BM36: Campaña Regular | BN36: 94 | BO36: 400MBPS | BP36: NO | BQ36: NO | BR36: Ninguno | BS36: 1 | BT36: 46206 | BU36: 5 | BV36: =IF($A36<>"", DATE(YEAR($A36),MONTH($A36),DAY($A36)),"") -> 46203 | BW36: =IF($E36<>"",DATE(YEAR($E36),MONTH($E36),DAY($E36)),"") -> 46206 | BX36: =IF($E36<>"",TEXT($E36,"HH"),"") -> 09 | BY36: =IF(B36<>"",VALUE(LEFT(B36)),"") -> 5 | BZ36: {=IF($A36<>"",INDEX(LISTA!$M$2:$N$27,MATCH($BC36,LISTA!$N$2:$N$27,0),1),"")} -> 7 | CA36: =IF($A36<>"",MONTH(BV36),"") -> 6 | CB36: =IF($BT36<>"",MONTH(BT36),"") -> 7 | CC36: 58029133
A37: 46203.575 | B37: 5 - INSTALADA | C37: MASIVO RESIDENCIAL | D37: NAYELI | E37: 46206.375 | F37: SE ENVIA TARDANZA TECNICA | G37: 104964242 | H37: 88722956 | I37: JESSICA | J37: 947587852 | K37: DNI | L37: 06430190 | M37: CESAR AUGUSTO ALARCON FARFAN | N37: 24562 | O37: JUNIN | P37: 110101 | AF37: Santiago de Surco | AQ37: GILBERTO | AR37: JULIA | AS37: calarconfarfan67@gmail.com | AT37: 957603615 | AU37: 957603615 | AV37: 957603615 | AW37: CALLE TACNA 146 URB. MANSERICHE | AX37: 2 | AY37: NA | AZ37: -12.143664623, -77.004367208 | BA37: FRANCISCO BOLOGNESI | BB37: LMSC347-F | BC37: LIMA METROPOLITANA | BD37: =IF(COUNTA(Q37:AP37)>0,INDEX(Q37:AP37,,max(IF(Q37:AP37<>"",COLUMN(Q37:AP37)))-16),"") -> Santiago de Surco | BE37: FTTH | BF37: SI | BG37: ALTA NUEVA | BL37: 1 PLAY + L1MAX | BM37: Campaña Regular PRO | BN37: 110 | BO37: 500MBPS | BP37: SI | BQ37: NO | BR37: Ninguno | BS37: 1 | BT37: 46206 | BU37: 6 | BV37: =IF($A37<>"", DATE(YEAR($A37),MONTH($A37),DAY($A37)),"") -> 46203 | BW37: =IF($E37<>"",DATE(YEAR($E37),MONTH($E37),DAY($E37)),"") -> 46206 | BX37: =IF($E37<>"",TEXT($E37,"HH"),"") -> 09 | BY37: =IF(B37<>"",VALUE(LEFT(B37)),"") -> 5 | BZ37: {=IF($A37<>"",INDEX(LISTA!$M$2:$N$27,MATCH($BC37,LISTA!$N$2:$N$27,0),1),"")} -> 1 | CA37: =IF($A37<>"",MONTH(BV37),"") -> 6 | CB37: =IF($BT37<>"",MONTH(BT37),"") -> 7 | CC37: 58023332
A38: 46200.406 | B38: 5 - INSTALADA | C38: MASIVO RESIDENCIAL | D38: NAYELI | E38: 46206.542 | F38: TARDANZA TECNICA | G38: 104887811 | H38: 88670937 | I38: JUAN DIEGO | J38: 935507175 | K38: DNI | L38: 26961099 | M38: CESAR WILMAN SALAZAR GAMBOA | N38: 28087 | O38: CAJAMARCA | P38: 060101 | V38: Cajabamba | AQ38: ENRIQUE | AR38: WILBERTA | AS38: Frankzrodriguezsalazar@gmail.com | AT38: 935 507 175 | AU38: 935 507 175 | AV38: 935 507 175 | AW38: JIRON SUAREZ 190 | AX38: 1 | AY38: NA | AZ38: -7.622846114469324, -78.04942980699167 | BA38: JIRON JOSE LEAL | BB38: CJCB005-F | BC38: CAJAMARCA | BD38: =IF(COUNTA(Q38:AP38)>0,INDEX(Q38:AP38,,max(IF(Q38:AP38<>"",COLUMN(Q38:AP38)))-16),"") -> Cajabamba | BE38: FTTH | BF38: SI | BG38: ALTA NUEVA | BL38: 1 PLAY | BM38: Campaña Regular | BN38: 100 | BO38: 800MBPS | BP38: NO | BQ38: NO | BR38: Ninguno | BS38: 1 | BT38: 46206 | BU38: 7 | BV38: =IF($A38<>"", DATE(YEAR($A38),MONTH($A38),DAY($A38)),"") -> 46200 | BW38: =IF($E38<>"",DATE(YEAR($E38),MONTH($E38),DAY($E38)),"") -> 46206 | BX38: =IF($E38<>"",TEXT($E38,"HH"),"") -> 13 | BY38: =IF(B38<>"",VALUE(LEFT(B38)),"") -> 5 | BZ38: {=IF($A38<>"",INDEX(LISTA!$M$2:$N$27,MATCH($BC38,LISTA!$N$2:$N$27,0),1),"")} -> 9 | CA38: =IF($A38<>"",MONTH(BV38),"") -> 6 | CB38: =IF($BT38<>"",MONTH(BT38),"") -> 7 | CC38: 58004934
A39: 46203.436 | B39: 5 - INSTALADA | C39: MASIVO RESIDENCIAL | D39: NAYELI | E39: 46207.458 | F39: EN EJECUCION - DESEA PARA EL SABADO | G39: 104953424 | H39: 88716374 | I39: JESSICA | J39: 984741682 | K39: DNI | L39: 45622906 | M39: FABIOLA ISABEL PEREZ IBARRA | N39: 32454 | O39: CUSCO | P39: 070108 | X39: Cusco | AQ39: MARCIAL | AR39: MARGARITA | AS39: isabel.fiti@gmail.com | AT39: 984741682 | AU39: 984741682 | AV39: 984741682 | AW39: H. VIVA EL PERU ETAPA 1 MZ J LT 10 | AX39: 2 | AY39: 2B | AZ39: -13.539285, -71.960379 | BA39: COLEGIO, AV VIVA EL PERU | BB39: CZST011-S | BC39: CUSCO | BD39: =IF(COUNTA(Q39:AP39)>0,INDEX(Q39:AP39,,max(IF(Q39:AP39<>"",COLUMN(Q39:AP39)))-16),"") -> Cusco | BE39: FTTH | BF39: SI | BG39: ALTA NUEVA | BL39: 1 PLAY | BM39: Campaña Promo Mediana | BN39: 89 | BO39: 400MBPS | BQ39: NO | BR39: Ninguno | BS39: 1 | BT39: 46207 | BU39: 1 | BV39: =IF($A39<>"", DATE(YEAR($A39),MONTH($A39),DAY($A39)),"") -> 46203 | BW39: =IF($E39<>"",DATE(YEAR($E39),MONTH($E39),DAY($E39)),"") -> 46207 | BX39: =IF($E39<>"",TEXT($E39,"HH"),"") -> 11 | BY39: =IF(B39<>"",VALUE(LEFT(B39)),"") -> 5 | BZ39: {=IF($A39<>"",INDEX(LISTA!$M$2:$N$27,MATCH($BC39,LISTA!$N$2:$N$27,0),1),"")} -> 10 | CA39: =IF($A39<>"",MONTH(BV39),"") -> 6 | CB39: =IF($BT39<>"",MONTH(BT39),"") -> 7 | CC39: 58020247
A40: 46200.733 | B40: 5 - INSTALADA | C40: MASIVO RESIDENCIAL | D40: NAYELI | E40: 46209.583 | F40: SE ENVIO RESCATE COMERCIAL PARA EL 04/07 | G40: 104907359 | H40: 88678780 | I40: FABRIZIO | J40: 925811235 | K40: DNI | L40: 48046824 | M40: BEYKER VIERA ARIZA | N40: 34310 | O40: LIMA | P40: 150125 | AF40: San Martín de Porres | AQ40: Croas | AR40: Aydee | AS40: beyker_japones@hotmail.com | AT40: 925811235 | AU40: 925811235 | AV40: 925811235 | AW40: SAN JUAN BAUTISTA 344 | AX40: 1 | AY40: nada | AZ40: -12.016565071032252, -77.05693506451682 | BA40: jiron alheli | BB40: LMMP008-S | BC40: LIMA METROPOLITANA | BD40: =IF(COUNTA(Q40:AP40)>0,INDEX(Q40:AP40,,max(IF(Q40:AP40<>"",COLUMN(Q40:AP40)))-16),"") -> San Martín de Porres | BE40: FTTH | BF40: SI | BG40: ALTA NUEVA | BL40: 2PLAY + TELF | BM40: Campaña Regular | BN40: 94 | BO40: 400MBPS | BP40: NO | BQ40: SI | BR40: Ninguno | BS40: 1 | BT40: 46209 | BU40: 2 | BV40: =IF($A40<>"", DATE(YEAR($A40),MONTH($A40),DAY($A40)),"") -> 46200 | BW40: =IF($E40<>"",DATE(YEAR($E40),MONTH($E40),DAY($E40)),"") -> 46209 | BX40: =IF($E40<>"",TEXT($E40,"HH"),"") -> 14 | BY40: =IF(B40<>"",VALUE(LEFT(B40)),"") -> 5 | BZ40: {=IF($A40<>"",INDEX(LISTA!$M$2:$N$27,MATCH($BC40,LISTA!$N$2:$N$27,0),1),"")} -> 1 | CA40: =IF($A40<>"",MONTH(BV40),"") -> 6 | CB40: =IF($BT40<>"",MONTH(BT40),"") -> 7 | CC40: 58009872
A41: 46196.622 | B41: 3 - CON SOT - DUPLICADO | C41: MASIVO RESIDENCIAL | D41: NAYELI | E41: 46199.75 | F41: SOT DUPLICADA, SE TIENE QUE ENVIAR CORREO | G41: 104782174 | H41: 88567487 | I41: JULIANA | J41: 929457958 | K41: DNI | L41: 46131332 | M41: MARIO SAUL ATAYUPANQUI YAÑEZ | N41: 32767 | O41: CUSCO | P41: 070101 | X41: Canchis | AQ41: MARIO | AR41: PIEDAD | AS41: MARIOSAUL160989@GMAIL.COM | AT41: 929457958 | AU41: 929457958 | AV41: 929457958 | AW41: AV. 2 DE MAYO 738, SICUANI - CUZCO | AX41: 2 | AY41: 1 | AZ41: -14.26693598, -71.22699577 | BA41: A DOS CASAS DEL COLEGIO SANTANDER | BB41: CZSC005-F | BC41: CUSCO | BD41: =IF(COUNTA(Q41:AP41)>0,INDEX(Q41:AP41,,max(IF(Q41:AP41<>"",COLUMN(Q41:AP41)))-16),"") -> Canchis | BE41: FTTH | BF41: SI | BG41: ALTA NUEVA | BL41: 1 PLAY + L1MAX | BM41: Campaña Regular | BN41: 110 | BO41: 500MBPS | BP41: SI | BQ41: NO | BR41: Ninguno | BS41: 1 | BV41: =IF($A41<>"", DATE(YEAR($A41),MONTH($A41),DAY($A41)),"") -> 46196 | BW41: =IF($E41<>"",DATE(YEAR($E41),MONTH($E41),DAY($E41)),"") -> 46199 | BX41: =IF($E41<>"",TEXT($E41,"HH"),"") -> 18 | BY41: =IF(B41<>"",VALUE(LEFT(B41)),"") -> 3 | BZ41: {=IF($A41<>"",INDEX(LISTA!$M$2:$N$27,MATCH($BC41,LISTA!$N$2:$N$27,0),1),"")} -> 10 | CA41: =IF($A41<>"",MONTH(BV41),"") -> 6 | CB41: =IF($BT41<>"",MONTH(BT41),"")
A42: 46193.495 | B42: 3 - CANCELADA-CARRUSEL | C42: MASIVO RESIDENCIAL | D42: PAOLA | E42: 46200.583 | F42: REPRO PARA EL 27/06 | G42: 104702456 | H42: 88479774 | I42: JUAN DIEGO | J42: 920477366 | K42: DNI | L42: 76423649 | M42: ZHANDLER PINEDA SANCHEZ | N42: 37529 | O42: HUANUCO | P42: 100102 | Z42: Huánuco | AQ42: Zacarias | AR42: Mercedes | AS42: zhatisa3909@gmail.com | AT42: 920477366 | AU42: 920477366 | AV42: 920477366 | AW42: jiron brasil mz t lt 1 URBANIZACION san luis sector 12 | AX42: 2 | AY42: 1A | AZ42: -9.9401925, -76.236067995 | BA42: Avenida Ricardo Palma | BB42: HNAM002-F | BC42: HUANUCO | BD42: =IF(COUNTA(Q42:AP42)>0,INDEX(Q42:AP42,,max(IF(Q42:AP42<>"",COLUMN(Q42:AP42)))-16),"") -> Huánuco | BE42: FTTH | BF42: SI | BG42: ALTA NUEVA | BL42: 1 PLAY | BM42: Campaña Regular | BN42: 110 | BO42: 500MBPS | BP42: SI | BQ42: NO | BR42: Ninguno | BS42: 1 | BV42: =IF($A42<>"", DATE(YEAR($A42),MONTH($A42),DAY($A42)),"") -> 46193 | BW42: =IF($E42<>"",DATE(YEAR($E42),MONTH($E42),DAY($E42)),"") -> 46200 | BX42: =IF($E42<>"",TEXT($E42,"HH"),"") -> 14 | BY42: =IF(B42<>"",VALUE(LEFT(B42)),"") -> 3 | BZ42: {=IF($A42<>"",INDEX(LISTA!$M$2:$N$27,MATCH($BC42,LISTA!$N$2:$N$27,0),1),"")} -> 12 | CA42: =IF($A42<>"",MONTH(BV42),"") -> 6 | CB42: =IF($BT42<>"",MONTH(BT42),"")
A43: 46200.44 | B43: 3 - CANCELADA-CARRUSEL | C43: MASIVO RESIDENCIAL | D43: NAYELI | E43: 46200.667 | F43: PROCEDE | G43: 104889152 | H43: 88671317 | I43: ANTHONELLA | J43: 974306888 | K43: DNI | L43: 74861925 | M43: JUAN JOSE MARTIN GUTIERREZ ESCALANTE | N43: 35107 | O43: LIMA METROPOLITANA | P43: 150101 | AF43: Carabayllo | AQ43: GILBERTO | AR43: DELA | AS43: JUANJO.GUTIERRESES GMAIL.COM | AT43: 974306888 | AU43: 974306888 | AV43: 974306888 | AW43: CALLE LOS LAURES MZ D LT 33 , UB LA RIVERA CARABAYLLO | AX43: 1 | AY43: ND | AZ43: -11.878564699683325 -77.02282265736812 | BA43: URBANIZACION LA RIVERA | BB43: LMBY009-S | BC43: LIMA METROPOLITANA | BD43: =IF(COUNTA(Q43:AP43)>0,INDEX(Q43:AP43,,max(IF(Q43:AP43<>"",COLUMN(Q43:AP43)))-16),"") -> Carabayllo | BE43: FTTH | BF43: SI | BG43: ALTA NUEVA | BL43: 1 PLAY | BM43: Campaña Regular | BN43: 94 | BO43: 400MBPS | BP43: NO | BQ43: SI | BR43: Ninguno | BS43: Ninguno | BV43: =IF($A43<>"", DATE(YEAR($A43),MONTH($A43),DAY($A43)),"") -> 46200 | BW43: =IF($E43<>"",DATE(YEAR($E43),MONTH($E43),DAY($E43)),"") -> 46200 | BX43: =IF($E43<>"",TEXT($E43,"HH"),"") -> 16 | BY43: =IF(B43<>"",VALUE(LEFT(B43)),"") -> 3 | BZ43: {=IF($A43<>"",INDEX(LISTA!$M$2:$N$27,MATCH($BC43,LISTA!$N$2:$N$27,0),1),"")} -> 1 | CA43: =IF($A43<>"",MONTH(BV43),"") -> 6 | CB43: =IF($BT43<>"",MONTH(BT43),"")
A44: 46191.475 | B44: 2 - CON SOT - TRANSACCIÓN N/A | C44: MASIVO RESIDENCIAL | D44: PAOLA | E44: 46193.083 | F44: ERROR EN EL CONTRATO - Transacción no autorizada - Motor : Control de irregularidades | G44: 104677835 | H44: 88465583 | I44: PAOLA | J44: 922088573 | K44: DNI | L44: 42880941 | M44: ESTHER JAIMES INGA | N44: 31043 | O44: HUANUCO | P44: 090101 | AF44: San Juan de Lurigancho | AQ44: BENANCIO | AR44: LIBERATA | AS44: aylaniosorioparedes@gmail.com | AT44: 922 088 573 | AU44: 922 088 573 | AV44: 969384309 | AW44: JR LOS QUINUALES 329 | AX44: 1 | AY44: NA | AZ44: -12 .022425,-77013923 | BA44: LOS QUINUALES | BB44: LMJL079-S | BC44: LIMA METROPOLITANA | BD44: =IF(COUNTA(Q44:AP44)>0,INDEX(Q44:AP44,,max(IF(Q44:AP44<>"",COLUMN(Q44:AP44)))-16),"") -> San Juan de Lurigancho | BE44: HFC | BF44: NO | BG44: ALTA NUEVA | BL44: 2 PLAY + TV ESTANDAR | BM44: Campaña Regular | BN44: 170 | BO44: 400MBPS | BP44: SI | BQ44: NO | BR44: 2 | BS44: 1 | BV44: =IF($A44<>"", DATE(YEAR($A44),MONTH($A44),DAY($A44)),"") -> 46191 | BW44: =IF($E44<>"",DATE(YEAR($E44),MONTH($E44),DAY($E44)),"") -> 46193 | BX44: =IF($E44<>"",TEXT($E44,"HH"),"") -> 02 | BY44: =IF(B44<>"",VALUE(LEFT(B44)),"") -> 2 | BZ44: {=IF($A44<>"",INDEX(LISTA!$M$2:$N$27,MATCH($BC44,LISTA!$N$2:$N$27,0),1),"")} -> 1 | CA44: =IF($A44<>"",MONTH(BV44),"") -> 6 | CB44: =IF($BT44<>"",MONTH(BT44),"")
A45: 46191.551 | B45: 2 - CON SOT - TRANSACCIÓN N/A | C45: MASIVO RESIDENCIAL | D45: PAOLA | E45: 46195.458 | F45: 32 | G45: 104671134 | H45: 88471837 | I45: JESSICA | J45: 918416553 | K45: CE | L45: 007198876 | M45: NATHALY JOSE MARQUEZ MARIN | N45: 35994 | O45: OTRO PAIS | P45: 09 | AF45: La Victoria | AQ45: LEONEL | AR45: MARVYS | AS45: Leonardmarcano511@gmail.com | AT45: 918416553 | AU45: 918416553 | AV45: 918416553 | AW45: URB. MATUTE MZ B LT 25 | AX45: 2 | AY45: NA | AZ45: -12.070171587854961, -77.02040258202793 | BA45: Parque Marcos Calderón | BB45: LMLV073-F | BC45: LIMA METROPOLITANA | BD45: =IF(COUNTA(Q45:AP45)>0,INDEX(Q45:AP45,,max(IF(Q45:AP45<>"",COLUMN(Q45:AP45)))-16),"") -> La Victoria | BE45: FTTH | BF45: NO | BG45: ALTA NUEVA | BL45: 1 PLAY | BM45: Campaña Promo Mediana | BN45: 89 | BO45: 400MBPS | BP45: NO | BQ45: NO | BR45: Ninguno | BS45: 1 | BV45: =IF($A45<>"", DATE(YEAR($A45),MONTH($A45),DAY($A45)),"") -> 46191 | BW45: =IF($E45<>"",DATE(YEAR($E45),MONTH($E45),DAY($E45)),"") -> 46195 | BX45: =IF($E45<>"",TEXT($E45,"HH"),"") -> 11 | BY45: =IF(B45<>"",VALUE(LEFT(B45)),"") -> 2 | BZ45: {=IF($A45<>"",INDEX(LISTA!$M$2:$N$27,MATCH($BC45,LISTA!$N$2:$N$27,0),1),"")} -> 1 | CA45: =IF($A45<>"",MONTH(BV45),"") -> 6 | CB45: =IF($BT45<>"",MONTH(BT45),"")
A46: 46191.7 | B46: 2 - CON SOT - TRANSACCIÓN N/A | C46: MASIVO RESIDENCIAL | D46: PAOLA | E46: 46193.458 | F46: Rechazado por transacción no autorizada | G46: 104655056 | H46: 88439634 | I46: JUAN DIEGO | J46: 936929624 | K46: DNI | L46: 40545693 | M46: ERIKA MAGALI LEON PINILLOS | N46: 29300 | O46: LIMA | P46: 140101 | AF46: San Martín de Porres | AQ46: griserio | AR46: shirley | AS46: ekalepini@gmail.com | AT46: 936929624 | AU46: 936929624 | AV46: 936929624 | AW46: CALLE TOBIAS MELLER 289 SAN MARTIN DE PORRES | AX46: 3 | AY46: 1 | AZ46: -12.000458, -77.088086 | BA46: calle juan pichert | BB46: LMMP224-F | BC46: LIMA METROPOLITANA | BD46: =IF(COUNTA(Q46:AP46)>0,INDEX(Q46:AP46,,max(IF(Q46:AP46<>"",COLUMN(Q46:AP46)))-16),"") -> San Martín de Porres | BE46: FTTH | BF46: NO | BG46: ALTA NUEVA | BL46: 1 PLAY | BM46: Campaña 1 sol | BN46: 89 | BO46: 400MBPS | BP46: NO | BQ46: NO | BR46: Ninguno | BS46: Ninguno | BV46: =IF($A46<>"", DATE(YEAR($A46),MONTH($A46),DAY($A46)),"") -> 46191 | BW46: =IF($E46<>"",DATE(YEAR($E46),MONTH($E46),DAY($E46)),"") -> 46193 | BX46: =IF($E46<>"",TEXT($E46,"HH"),"") -> 11 | BY46: =IF(B46<>"",VALUE(LEFT(B46)),"") -> 2 | BZ46: {=IF($A46<>"",INDEX(LISTA!$M$2:$N$27,MATCH($BC46,LISTA!$N$2:$N$27,0),1),"")} -> 1 | CA46: =IF($A46<>"",MONTH(BV46),"") -> 6 | CB46: =IF($BT46<>"",MONTH(BT46),"")
A47: 46191.82 | B47: 2 - CON SOT - TRANSACCIÓN N/A | C47: MASIVO RESIDENCIAL | D47: PAOLA | F47: GRABADO - ADJUNTAR DNI ambas caras, Foto de cliente mostrando DNI y Recibo de Servicio de dirección de instalación DE AGUA o luz. | I47: ANGHELL | J47: 922379687 | K47: RUC | L47: 10327336962 | M47: AGUIRRE BLANQUILLO MIGUEL ANGEL | N47: 26631 | O47: ANCASH | P47: 021301 | AF47: Cercado de Lima | AQ47: AUGUSTO | AR47: CARMEN | AS47: aguirremiguel1972@gmail.com | AT47: 922 379 687 | AU47: 922 379 687 | AV47: 922 379 687 | AW47: Urbanización palomino mz m lt32 | AX47: 3 | AY47: 1 | AZ47: -12.060967, -77.070769 | BA47: Avenida santa catalina de Siena | BB47: LMLM 228-F | BC47: LIMA METROPOLITANA | BD47: =IF(COUNTA(Q47:AP47)>0,INDEX(Q47:AP47,,max(IF(Q47:AP47<>"",COLUMN(Q47:AP47)))-16),"") -> Cercado de Lima | BE47: FTTH | BF47: NO | BG47: ALTA NUEVA | BL47: 2 PLAY + TV ESTANDAR | BM47: Campaña Promo Entrada | BN47: 170 | BO47: 400MBPS | BP47: SI | BQ47: NO | BR47: 2 | BS47: 1 | BV47: =IF($A47<>"", DATE(YEAR($A47),MONTH($A47),DAY($A47)),"") -> 46191 | BW47: =IF($E47<>"",DATE(YEAR($E47),MONTH($E47),DAY($E47)),"") | BX47: =IF($E47<>"",TEXT($E47,"HH"),"") | BY47: =IF(B47<>"",VALUE(LEFT(B47)),"") -> 2 | BZ47: {=IF($A47<>"",INDEX(LISTA!$M$2:$N$27,MATCH($BC47,LISTA!$N$2:$N$27,0),1),"")} -> 1 | CA47: =IF($A47<>"",MONTH(BV47),"") -> 6 | CB47: =IF($BT47<>"",MONTH(BT47),"")
A48: 46196.809 | B48: 2 - CON SOT - TRANSACCIÓN N/A | C48: MASIVO RESIDENCIAL | D48: NAYELI | E48: 46197.583 | F48: ADJUNTAR DNI ambas caras, Foto de cliente mostrando DNI y Recibo de Servicio de dirección de instalación DE AGUA o luz. | G48: 104797604 | H48: 88585134 | I48: JULIANA | J48: 950490504 | K48: DNI | L48: 10180654 | M48: SIGIFREDO ALBERTO TAPIA LUQUE | N48: 27814 | O48: LIMA METROPOLITANA | P48: 140133 | U48: Huanta | AQ48: SIGIFREDO | AR48: MERCEDES | AS48: bet6otapia@hotmail.com | AT48: 950490504 | AU48: 950490504 | AV48: 950490504 | AW48: Jr Razuhuillca 438 URB. CERCADO HUANTA HUANTA AYACUCHO. | AX48: 1 | AY48: 1 | AZ48: -12.938042415, -74.246330888 | BA48: A DOS CUADRAS Y MEDIA DEL PARQUE DE LA MUNICIPALIDAD | BB48: AYHU005-F | BC48: AYACUCHO | BD48: =IF(COUNTA(Q48:AP48)>0,INDEX(Q48:AP48,,max(IF(Q48:AP48<>"",COLUMN(Q48:AP48)))-16),"") -> Huanta | BE48: FTTH | BF48: NO | BG48: ALTA NUEVA | BL48: 1 PLAY | BM48: Campaña Promo Mediana | BN48: 89 | BO48: 400MBPS | BP48: NO | BQ48: NO | BR48: Ninguno | BS48: 1 | BV48: =IF($A48<>"", DATE(YEAR($A48),MONTH($A48),DAY($A48)),"") -> 46196 | BW48: =IF($E48<>"",DATE(YEAR($E48),MONTH($E48),DAY($E48)),"") -> 46197 | BX48: =IF($E48<>"",TEXT($E48,"HH"),"") -> 14 | BY48: =IF(B48<>"",VALUE(LEFT(B48)),"") -> 2 | BZ48: {=IF($A48<>"",INDEX(LISTA!$M$2:$N$27,MATCH($BC48,LISTA!$N$2:$N$27,0),1),"")} -> 8 | CA48: =IF($A48<>"",MONTH(BV48),"") -> 6 | CB48: =IF($BT48<>"",MONTH(BT48),"")
A49: 46197.765 | B49: 2 - CON SOT - TRANSACCIÓN N/A | C49: MASIVO RESIDENCIAL | D49: NAYELI | E49: 46199.375 | F49: ADJUNTAR DNI ambas caras, Foto de cliente mostrando DNI y Recibo de Servicio de dirección de instalación DE AGUA o luz. | G49: 104819915 | H49: 88609906 | I49: BRITNEY | J49: 949875878 | K49: DNI | L49: 42906830 | M49: EDWIN ABNER PAICO CRUZ | N49: 31113 | O49: TUMBES | P49: 240101 | AO49: Tumbes | AQ49: Marcelino | AR49: Teresa | AS49: edwinpaico8@gmail.com | AT49: 949 875 878 | AU49: 949 875 878 | AV49: 949 875 878 | AW49: CIUDADELA NOE MZ H LT 7 PISO TUMBES | AX49: 1 | AY49: 1 | AZ49: -3.573075, -80.420756 | BA49: Urb ciudadela noe | BB49: TBTB029-S | BC49: TUMBES | BD49: =IF(COUNTA(Q49:AP49)>0,INDEX(Q49:AP49,,max(IF(Q49:AP49<>"",COLUMN(Q49:AP49)))-16),"") -> Tumbes | BE49: FTTH | BF49: NO | BG49: ALTA NUEVA | BL49: 2 PLAY + TV ESTANDAR | BM49: Campaña Regular | BN49: 170 | BO49: 400MBPS | BP49: SI | BQ49: NO | BR49: 2 | BS49: 1 | BV49: =IF($A49<>"", DATE(YEAR($A49),MONTH($A49),DAY($A49)),"") -> 46197 | BW49: =IF($E49<>"",DATE(YEAR($E49),MONTH($E49),DAY($E49)),"") -> 46199 | BX49: =IF($E49<>"",TEXT($E49,"HH"),"") -> 09 | BY49: =IF(B49<>"",VALUE(LEFT(B49)),"") -> 2 | BZ49: {=IF($A49<>"",INDEX(LISTA!$M$2:$N$27,MATCH($BC49,LISTA!$N$2:$N$27,0),1),"")} -> 25 | CA49: =IF($A49<>"",MONTH(BV49),"") -> 6 | CB49: =IF($BT49<>"",MONTH(BT49),"")
A50: 46193.676 | B50: 2 - CON SOT - EN REASIGNACION | C50: MASIVO RESIDENCIAL | D50: PAOLA | E50: 46196.458 | F50: Nos pidieron reasignación de esta venta | G50: 104713524 | H50: 88484062 | I50: JULIANA | J50: 927604817 | K50: DNI | L50: 02737885 | M50: MILAGROS INES GUERRA RIVERA | N50: 26578 | O50: PIURA | P50: 190101 | AK50: Piura | AQ50: RUBEN | AR50: OLINDA | AS50: Sebasgu1@hotmail.com | AT50: 927604817 | AU50: 927604817 | AV50: 927604817 | AW50: AAHH. LOPEZ ALBUJAR MZ P LOTE 18, 26 DE OCTUBRE, PIURA. | AX50: 2 | AY50: 1 | AZ50: -5.199136608082209, -80.65140110426609 | BA50: -5.199136608082209, -80.65140110426609 | BB50: PIOC002-F | BC50: PIURA | BD50: =IF(COUNTA(Q50:AP50)>0,INDEX(Q50:AP50,,max(IF(Q50:AP50<>"",COLUMN(Q50:AP50)))-16),"") -> Piura | BE50: FTTH | BF50: NO | BG50: ALTA NUEVA | BL50: 1 PLAY + L1MAX | BM50: Campaña Regular | BN50: 110 | BO50: 500MBPS | BP50: SI | BQ50: NO | BR50: Ninguno | BS50: 1 | BV50: =IF($A50<>"", DATE(YEAR($A50),MONTH($A50),DAY($A50)),"") -> 46193 | BW50: =IF($E50<>"",DATE(YEAR($E50),MONTH($E50),DAY($E50)),"") -> 46196 | BX50: =IF($E50<>"",TEXT($E50,"HH"),"") -> 11 | BY50: =IF(B50<>"",VALUE(LEFT(B50)),"") -> 2 | BZ50: {=IF($A50<>"",INDEX(LISTA!$M$2:$N$27,MATCH($BC50,LISTA!$N$2:$N$27,0),1),"")} -> 21 | CA50: =IF($A50<>"",MONTH(BV50),"") -> 6 | CB50: =IF($BT50<>"",MONTH(BT50),"")
A51: 46195.545 | B51: 2 - CANCELADA-RED SATURADA | C51: MASIVO RESIDENCIAL | D51: NAYELI | E51: 46197.583 | F51: LLAMARON A CLIENTE PARA INDICARLE QUE SU RED ESTA SATURADA, CLIENTE CONTRATÓ CON OTRO OPERADOR | G51: 104748456 | H51: 88524046 | I51: ANGHELL | J51: 963188744 | K51: DNI | L51: 74079616 | M51: PAMELA YVETTE MALDONADO QUISPE | N51: 35257 | O51: AREQUIPA | P51: 040109 | T51: Arequipa | AQ51: VICTOR MANUEL | AR51: DIONISIA | AS51: maldonadopamela986@gmail.com | AT51: 963188744 | AU51: 963188744 | AV51: 963188744 | AW51: urb CAMPO DE MARTE MZ P LT 42, PAUCARPATA, AREQUIPA | AX51: 3 | AY51: 0 | AZ51: -16.427180557097067, -71.4941595331016 | BA51: CALLE TUPAC AMARU | BB51: AQPP047 | BC51: AREQUIPA | BD51: =IF(COUNTA(Q51:AP51)>0,INDEX(Q51:AP51,,max(IF(Q51:AP51<>"",COLUMN(Q51:AP51)))-16),"") -> Arequipa | BE51: HFC | BF51: SI | BG51: ALTA NUEVA | BL51: 1 PLAY | BM51: Campaña Promo Mediana | BN51: 89 | BO51: 400MBPS | BP51: NO | BQ51: NO | BR51: Ninguno | BS51: 1 | BV51: =IF($A51<>"", DATE(YEAR($A51),MONTH($A51),DAY($A51)),"") -> 46195 | BW51: =IF($E51<>"",DATE(YEAR($E51),MONTH($E51),DAY($E51)),"") -> 46197 | BX51: =IF($E51<>"",TEXT($E51,"HH"),"") -> 14 | BY51: =IF(B51<>"",VALUE(LEFT(B51)),"") -> 2 | BZ51: {=IF($A51<>"",INDEX(LISTA!$M$2:$N$27,MATCH($BC51,LISTA!$N$2:$N$27,0),1),"")} -> 7 | CA51: =IF($A51<>"",MONTH(BV51),"") -> 6 | CB51: =IF($BT51<>"",MONTH(BT51),"")
A52: 46191.461 | B52: 2 - CANCELADA-NO DESEA | C52: MASIVO RESIDENCIAL | D52: NAYELI | E52: 46197.375 | F52: VENTA ANTIGUO, CLIENTE RECIBIO PROMOCION DE CLARO SOBRE SU INSTALACION ACTUAL, DECIDE QUEDARSE CON ELLOS. | G52: 104642463 | H52: 88433432 | I52: JESSICA | J52: 945547763 | K52: DNI | L52: 21122076 | M52: RAUL DIEGO YARASCA MANDUJANO | N52: 25972 | O52: JUNIN | P52: 110325 | AB52: Chanchamayo | AQ52: FELIX | AR52: ESTEFANIA | AS52: ryarasca123@gmail.com | AT52: 945547763 | AU52: 945547763 | AV52: 945547763 | AW52: AV. ASHANINKA 235 URB. EL PARAISO | AX52: 4 | AY52: 4A | AZ52: -11.0675295, -75.339234545 | BA52: IEP. Santa Maria Reyna | BB52: JNCM008-F | BC52: JUNIN | BD52: =IF(COUNTA(Q52:AP52)>0,INDEX(Q52:AP52,,max(IF(Q52:AP52<>"",COLUMN(Q52:AP52)))-16),"") -> Chanchamayo | BE52: FTTH | BF52: SI | BG52: ALTA NUEVA | BL52: 1 PLAY | BM52: Campaña Promo Mediana | BN52: 89 | BO52: 400MBPS | BP52: NO | BQ52: NO | BR52: Ninguno | BS52: 1 | BV52: =IF($A52<>"", DATE(YEAR($A52),MONTH($A52),DAY($A52)),"") -> 46191 | BW52: =IF($E52<>"",DATE(YEAR($E52),MONTH($E52),DAY($E52)),"") -> 46197 | BX52: =IF($E52<>"",TEXT($E52,"HH"),"") -> 09 | BY52: =IF(B52<>"",VALUE(LEFT(B52)),"") -> 2 | BZ52: {=IF($A52<>"",INDEX(LISTA!$M$2:$N$27,MATCH($BC52,LISTA!$N$2:$N$27,0),1),"")} -> 14 | CA52: =IF($A52<>"",MONTH(BV52),"") -> 6 | CB52: =IF($BT52<>"",MONTH(BT52),"")
A53: 46195.416 | B53: 2 - CANCELADA-NO DESEA | C53: MASIVO RESIDENCIAL | D53: NAYELI | E53: 46196.583 | F53: CLIENTE QUERIA SU INSTALACION PARA ESE MISMO DIA, SI O SI, NO DESEA REPROGRAMACION | G53: 104737775 | H53: 88515175 | I53: JESSICA | J53: 917707080 | K53: DNI | L53: 70090949 | M53: KRISTIAN COLLANQUI FLORES | N53: 33904 | O53: PUNO | P53: 200604 | AL53: San Román | AQ53: PASCUAL MARCIAL | AR53: LEONCIA | AS53: kristiancollanqui2705@gmail.com | AT53: 917707080 | AU53: 917707080 | AV53: 917707080 | AW53: kristiancollanqui2705@gmail.com | AX53: 2 | AY53: NA | AZ53: -15.466703, -70.143151 | BA53: JIRON COPACABANA | BB53: PUJL123-F | BC53: PUNO | BD53: =IF(COUNTA(Q53:AP53)>0,INDEX(Q53:AP53,,max(IF(Q53:AP53<>"",COLUMN(Q53:AP53)))-16),"") -> San Román | BE53: FTTH | BF53: SI | BG53: ALTA NUEVA | BL53: 1 PLAY | BM53: Campaña Promo Mediana | BN53: 89 | BO53: 400MBPS | BP53: NO | BQ53: NO | BR53: Ninguno | BS53: 1 | BV53: =IF($A53<>"", DATE(YEAR($A53),MONTH($A53),DAY($A53)),"") -> 46195 | BW53: =IF($E53<>"",DATE(YEAR($E53),MONTH($E53),DAY($E53)),"") -> 46196 | BX53: =IF($E53<>"",TEXT($E53,"HH"),"") -> 14 | BY53: =IF(B53<>"",VALUE(LEFT(B53)),"") -> 2 | BZ53: {=IF($A53<>"",INDEX(LISTA!$M$2:$N$27,MATCH($BC53,LISTA!$N$2:$N$27,0),1),"")} -> 22 | CA53: =IF($A53<>"",MONTH(BV53),"") -> 6 | CB53: =IF($BT53<>"",MONTH(BT53),"")
